Workbook

Sheet Read Me
A1: CSSP Task Control Hub — Quick Start
A2: Excel MVP for daily workload assignment, engineer updates, scope disposition, and target tracking.
A4: Purpose
A5: The workbook manages only CSSP tasks with status executing or processing. Source data is read-only; operational ownership, progress, targets, and scope decisions are recorded in separate append-only sheets.
A8: Daily Manager Workflow | E8: Engineer Workflow
A9: Step | B9: Action | C9: Control | E9: Step | F9: Action | G9: Control
A10: 1 | B10: Refresh / replace raw snapshots | C10: Load latest snapshots without editing Task Master formulas. | E10: 1 | F10: Find assigned work | G10: Filter by Current / Planned PIC.
A11: 2 | B11: Review processing queue | C11: Use Task Master and Engineer Capacity before assignment. | E11: 2 | F11: Append an update | G11: Add a new Engineer Updates row; never overwrite history.
A12: 3 | B12: Disposition to engineer | C12: Append Assignment History; Current Operational PIC updates automatically. | E12: 3 | F12: Record next action | G12: Include progress, next action, ETA, and blocker.
A13: 4 | B13: Publish daily targets | C13: Add executing tasks for the reporting date. | E13: 4 | F13: Flag scope issue | G13: Select Out-of-Scope Suspected and attach evidence.
A14: 5 | B14: Review scope exceptions | C14: Confirm or reject private-cloud/on-prem flags. | E14: 5 | F14: Record daily result | G14: Update Daily Targets result and completion evidence.
A15: 6 | B15: Close the day | C15: Review achieved, blocked, missed, and carried-over targets.
A18: Workbook Controls
A19: Blue cells | B19: User input.
A20: Gray cells | B20: Formula-driven; do not overwrite.
A21: Raw sheets | B21: Original daily snapshot values retained for traceability.
A22: Snapshot PIC | B22: Original gate_4_id from CSSP.
A23: Current Operational PIC | B23: Latest replacement, otherwise normalized Snapshot PIC.
A24: Confirmed OOS | B24: Excluded from workload but retained until CSSP reconciles.
A25: Daily target | B25: Historical date/request record; never delete misses or carryovers.
A28: Important Limitation
A29: Excel supports coauthoring, but it does not enforce strong row-level permissions. Store in SharePoint/OneDrive, protect source/formula sheets, retain version history, and restrict engineers to update input areas through team controls.

Sheet Dashboard
A1: Cloud Infrastructure Task Control Hub
A2: Operational view for executing and processing tasks. Reporting date is editable.
A4: Reporting Date | B4: 46252 | D4: Blue cells are manager/engineer inputs. Gray cells are formulas. Refresh raw snapshots only through the controlled import process.
A6: MANAGED BACKLOG | E6: EXECUTING | I6: PROCESSING / READY | M6: ASSIGNMENT EXCEPTIONS
A7: =COUNTIF('Task Master'!$A$5:$A$100,"<>") -> 96 | E7: =COUNTIF('Task Master'!$C$5:$C$100,"executing") -> 81 | I7: =COUNTIF('Task Master'!$C$5:$C$100,"processing") -> 15 | M7: =COUNTIF('Task Master'!$X$5:$X$100,"Executing without named engineer") -> 0
A12: TODAY'S TARGETS | E12: TARGETS ACHIEVED | I12: BLOCKED OR MISSED | M12: OOS PENDING REVIEW
A13: =COUNTIF('Daily Targets'!$A$5:$A$204,$B$4) -> 5 | E13: =COUNTIFS('Daily Targets'!$A$5:$A$204,$B$4,'Daily Targets'!$O$5:$O$204,"Yes") -> 0 | I13: =COUNTIFS('Daily Targets'!$A$5:$A$204,$B$4,'Daily Targets'!$K$5:$K$204,"Blocked")+COUNTIFS('Daily Targets'!$A$5:$A$204,$B$4,'Daily Targets'!$K$5:$K$204,"Missed") -> 0 | M13: =COUNTIF('Task Master'!$N$5:$N$100,"Pending Review") -> 0
A18: Engineer | B18: Projected Load | C18: Effective Capacity
A19: ='Engineer Capacity'!B5 -> Abdul Khoir | B19: ='Engineer Capacity'!K5 -> 26 | C19: ='Engineer Capacity'!F5 -> 12
A20: ='Engineer Capacity'!B6 -> Abhishek Bhowate | B20: ='Engineer Capacity'!K6 -> 8 | C20: ='Engineer Capacity'!F6 -> 12
A21: ='Engineer Capacity'!B7 -> Amarja Kawade | B21: ='Engineer Capacity'!K7 -> 42 | C21: ='Engineer Capacity'!F7 -> 12
A22: ='Engineer Capacity'!B8 -> Arun Karuppiah | B22: ='Engineer Capacity'!K8 -> 12 | C22: ='Engineer Capacity'!F8 -> 12
A23: ='Engineer Capacity'!B9 -> K Saktivelu | B23: ='Engineer Capacity'!K9 -> 6 | C23: ='Engineer Capacity'!F9 -> 12
A24: ='Engineer Capacity'!B10 -> Mardiansyah Rayasa | B24: ='Engineer Capacity'!K10 -> 17 | C24: ='Engineer Capacity'!F10 -> 12
A25: ='Engineer Capacity'!B11 -> Nilesh Sankpal | B25: ='Engineer Capacity'!K11 -> 0 | C25: ='Engineer Capacity'!F11 -> 12
A26: ='Engineer Capacity'!B12 -> Raditya Nugraha | B26: ='Engineer Capacity'!K12 -> 12 | C26: ='Engineer Capacity'!F12 -> 12
A27: ='Engineer Capacity'!B13 -> Sairam Villa | B27: ='Engineer Capacity'!K13 -> 0 | C27: ='Engineer Capacity'!F13 -> 12
A28: ='Engineer Capacity'!B14 -> Swaminadh Chirakala | B28: ='Engineer Capacity'!K14 -> 37 | C28: ='Engineer Capacity'!F14 -> 12
A29: ='Engineer Capacity'!B15 -> Venkatesh Kalikivayi | B29: ='Engineer Capacity'!K15 -> 8 | C29: ='Engineer Capacity'!F15 -> 12
A38: Backlog Status | B38: Count | C38: Share | E38: Today's Result | F38: Count | G38: Action
A39: executing | B39: =COUNTIF('Task Master'!$C$5:$C$100,A39) -> 81 | C39: =B39/SUM($B$39:$B$40) -> 0.84375 | E39: Achieved | F39: =COUNTIFS('Daily Targets'!$A$5:$A$204,$B$4,'Daily Targets'!$K$5:$K$204,"Achieved") -> 0 | G39: Review evidence
A40: processing | B40: =COUNTIF('Task Master'!$C$5:$C$100,A40) -> 15 | C40: =B40/SUM($B$39:$B$40) -> 0.15625 | E40: Blocked | F40: =COUNTIFS('Daily Targets'!$A$5:$A$204,$B$4,'Daily Targets'!$K$5:$K$204,"Blocked") -> 0 | G40: Escalate blocker
E41: Missed | F41: =COUNTIFS('Daily Targets'!$A$5:$A$204,$B$4,'Daily Targets'!$K$5:$K$204,"Missed") -> 0 | G41: Record carryover
E42: OOS Submitted | F42: =COUNTIFS('Daily Targets'!$A$5:$A$204,$B$4,'Daily Targets'!$K$5:$K$204,"Out-of-Scope Submitted") -> 0 | G42: Manager scope review

Sheet Task Master
A1: Task Master
A2: Read-only CSSP source fields plus formula-driven operational ownership, workload, progress, and exceptions.
A4: Request Number | B4: Task Type | C4: CSSP Status | D4: Snapshot Date | E4: Date Created | F4: Date Updated | G4: Application Name | H4: Project Name | I4: Request Size | J4: Snapshot PIC (gate_4_id) | K4: Current Operational PIC | L4: Assignment Mode | M4: Workload Points | N4: Manager Scope Decision | O4: Final Disposition | P4: Effective Workload | Q4: Latest Update | R4: Latest Engineer State | S4: Latest Workflow Stage | T4: Latest Progress | U4: Next Action | V4: Blocker | W4: ETA | X4: Exception | Y4: Source File
A5: CSSP10192809 | B5: Decommissioning | C5: processing | D5: 46251 | E5: 46196.13 | F5: 46237.316 | G5: Lab Information Management System - LIMS MLNG | H5: OCI MIGRATION - LIMS MLNG | I5: M | J5: CCoE Operations | K5: =IFERROR(LOOKUP(2,1/('Assignment History'!$B$5:$B$204=A5),'Assignment History'!$D$5:$D$204),IFERROR(VLOOKUP(J5,Configuration!$L$5:$M$50,2,FALSE),J5)) -> CCoE Operations | L5: =IF(K5=IFERROR(VLOOKUP(J5,Configuration!$L$5:$M$50,2,FALSE),J5),"Snapshot PIC","Replacement PIC") -> Snapshot PIC | M5: =IFERROR(VLOOKUP(I5,Configuration!$O$5:$P$8,2,FALSE),Configuration!$S$6) -> 2 | N5: =IFERROR(LOOKUP(2,1/('Scope Review'!$B$5:$B$204=A5),'Scope Review'!$G$5:$G$204),"Not Reviewed") -> Not Reviewed | O5: =IFERROR(LOOKUP(2,1/('Scope Review'!$B$5:$B$204=A5),'Scope Review'!$H$5:$H$204),"") | P5: =IF(AND(C5="executing",N5<>"Confirmed OOS"),M5,0) -> 0 | Q5: =IFERROR(LOOKUP(2,1/('Engineer Updates'!$B$5:$B$304=A5),'Engineer Updates'!$A$5:$A$304),"") | R5: =IFERROR(LOOKUP(2,1/('Engineer Updates'!$B$5:$B$304=A5),'Engineer Updates'!$E$5:$E$304),"") | S5: =IFERROR(LOOKUP(2,1/('Engineer Updates'!$B$5:$B$304=A5),'Engineer Updates'!$D$5:$D$304),"") | T5: =IFERROR(LOOKUP(2,1/('Engineer Updates'!$B$5:$B$304=A5),'Engineer Updates'!$F$5:$F$304),"") | U5: =IFERROR(LOOKUP(2,1/('Engineer Updates'!$B$5:$B$304=A5),'Engineer Updates'!$G$5:$G$304),"") | V5: =IFERROR(LOOKUP(2,1/('Engineer Updates'!$B$5:$B$304=A5),'Engineer Updates'!$H$5:$H$304),"") | W5: =IFERROR(LOOKUP(2,1/('Engineer Updates'!$B$5:$B$304=A5),'Engineer Updates'!$I$5:$I$304),"") | X5: =IF(AND(C5="executing",ISERROR(SEARCH("@",K5))),"Executing without named engineer",IF(AND(N5="Confirmed OOS",C5="executing"),"Confirmed OOS still executing","")) | Y5: CSSP-Decommisioning-1708.xlsx
A6: CSSP10237001 | B6: Decommissioning | C6: processing | D6: 46251 | E6: 46177.38 | F6: 46209.307 | G6: Energy Component as a Service - ECaaS | H6: PETRONAS Global Production System (PGPS) Energy Component as a Service (ECaaS) | I6: M | J6: CCoE Operations | K6: =IFERROR(LOOKUP(2,1/('Assignment History'!$B$5:$B$204=A6),'Assignment History'!$D$5:$D$204),IFERROR(VLOOKUP(J6,Configuration!$L$5:$M$50,2,FALSE),J6)) -> CCoE Operations | L6: =IF(K6=IFERROR(VLOOKUP(J6,Configuration!$L$5:$M$50,2,FALSE),J6),"Snapshot PIC","Replacement PIC") -> Snapshot PIC | M6: =IFERROR(VLOOKUP(I6,Configuration!$O$5:$P$8,2,FALSE),Configuration!$S$6) -> 2 | N6: =IFERROR(LOOKUP(2,1/('Scope Review'!$B$5:$B$204=A6),'Scope Review'!$G$5:$G$204),"Not Reviewed") -> Not Reviewed | O6: =IFERROR(LOOKUP(2,1/('Scope Review'!$B$5:$B$204=A6),'Scope Review'!$H$5:$H$204),"") | P6: =IF(AND(C6="executing",N6<>"Confirmed OOS"),M6,0) -> 0 | Q6: =IFERROR(LOOKUP(2,1/('Engineer Updates'!$B$5:$B$304=A6),'Engineer Updates'!$A$5:$A$304),"") | R6: =IFERROR(LOOKUP(2,1/('Engineer Updates'!$B$5:$B$304=A6),'Engineer Updates'!$E$5:$E$304),"") | S6: =IFERROR(LOOKUP(2,1/('Engineer Updates'!$B$5:$B$304=A6),'Engineer Updates'!$D$5:$D$304),"") | T6: =IFERROR(LOOKUP(2,1/('Engineer Updates'!$B$5:$B$304=A6),'Engineer Updates'!$F$5:$F$304),"") | U6: =IFERROR(LOOKUP(2,1/('Engineer Updates'!$B$5:$B$304=A6),'Engineer Updates'!$G$5:$G$304),"") | V6: =IFERROR(LOOKUP(2,1/('Engineer Updates'!$B$5:$B$304=A6),'Engineer Updates'!$H$5:$H$304),"") | W6: =IFERROR(LOOKUP(2,1/('Engineer Updates'!$B$5:$B$304=A6),'Engineer Updates'!$I$5:$I$304),"") | X6: =IF(AND(C6="executing",ISERROR(SEARCH("@",K6))),"Executing without named engineer",IF(AND(N6="Confirmed OOS",C6="executing"),"Confirmed OOS still executing","")) | Y6: CSSP-Decommisioning-1708.xlsx
A7: CSSP10340483 | B7: Decommissioning | C7: processing | D7: 46251 | E7: 46167.032 | F7: 46210.284 | G7: Instrument Reliability Digital Suite - IRIS | H7: [ALS] Implementation of Instrument Reliability Digital Suite (IRIS) for GTS | I7: S | J7: CCoE Operations | K7: =IFERROR(LOOKUP(2,1/('Assignment History'!$B$5:$B$204=A7),'Assignment History'!$D$5:$D$204),IFERROR(VLOOKUP(J7,Configuration!$L$5:$M$50,2,FALSE),J7)) -> CCoE Operations | L7: =IF(K7=IFERROR(VLOOKUP(J7,Configuration!$L$5:$M$50,2,FALSE),J7),"Snapshot PIC","Replacement PIC") -> Snapshot PIC | M7: =IFERROR(VLOOKUP(I7,Configuration!$O$5:$P$8,2,FALSE),Configuration!$S$6) -> 1 | N7: =IFERROR(LOOKUP(2,1/('Scope Review'!$B$5:$B$204=A7),'Scope Review'!$G$5:$G$204),"Not Reviewed") -> Not Reviewed | O7: =IFERROR(LOOKUP(2,1/('Scope Review'!$B$5:$B$204=A7),'Scope Review'!$H$5:$H$204),"") | P7: =IF(AND(C7="executing",N7<>"Confirmed OOS"),M7,0) -> 0 | Q7: =IFERROR(LOOKUP(2,1/('Engineer Updates'!$B$5:$B$304=A7),'Engineer Updates'!$A$5:$A$304),"") | R7: =IFERROR(LOOKUP(2,1/('Engineer Updates'!$B$5:$B$304=A7),'Engineer Updates'!$E$5:$E$304),"") | S7: =IFERROR(LOOKUP(2,1/('Engineer Updates'!$B$5:$B$304=A7),'Engineer Updates'!$D$5:$D$304),"") | T7: =IFERROR(LOOKUP(2,1/('Engineer Updates'!$B$5:$B$304=A7),'Engineer Updates'!$F$5:$F$304),"") | U7: =IFERROR(LOOKUP(2,1/('Engineer Updates'!$B$5:$B$304=A7),'Engineer Updates'!$G$5:$G$304),"") | V7: =IFERROR(LOOKUP(2,1/('Engineer Updates'!$B$5:$B$304=A7),'Engineer Updates'!$H$5:$H$304),"") | W7: =IFERROR(LOOKUP(2,1/('Engineer Updates'!$B$5:$B$304=A7),'Engineer Updates'!$I$5:$I$304),"") | X7: =IF(AND(C7="executing",ISERROR(SEARCH("@",K7))),"Executing without named engineer",IF(AND(N7="Confirmed OOS",C7="executing"),"Confirmed OOS still executing","")) | Y7: CSSP-Decommisioning-1708.xlsx
A8: CSSP10434338 | B8: Decommissioning | C8: processing | D8: 46251 | E8: 46196.125 | F8: 46209.312 | G8: Lab Information Management System - LIMS PPTSB | H8: OCI MIGRATION - Integrated Lab Information System (PPT) | I8: M | J8: CCoE Operations | K8: =IFERROR(LOOKUP(2,1/('Assignment History'!$B$5:$B$204=A8),'Assignment History'!$D$5:$D$204),IFERROR(VLOOKUP(J8,Configuration!$L$5:$M$50,2,FALSE),J8)) -> CCoE Operations | L8: =IF(K8=IFERROR(VLOOKUP(J8,Configuration!$L$5:$M$50,2,FALSE),J8),"Snapshot PIC","Replacement PIC") -> Snapshot PIC | M8: =IFERROR(VLOOKUP(I8,Configuration!$O$5:$P$8,2,FALSE),Configuration!$S$6) -> 2 | N8: =IFERROR(LOOKUP(2,1/('Scope Review'!$B$5:$B$204=A8),'Scope Review'!$G$5:$G$204),"Not Reviewed") -> Not Reviewed | O8: =IFERROR(LOOKUP(2,1/('Scope Review'!$B$5:$B$204=A8),'Scope Review'!$H$5:$H$204),"") | P8: =IF(AND(C8="executing",N8<>"Confirmed OOS"),M8,0) -> 0 | Q8: =IFERROR(LOOKUP(2,1/('Engineer Updates'!$B$5:$B$304=A8),'Engineer Updates'!$A$5:$A$304),"") | R8: =IFERROR(LOOKUP(2,1/('Engineer Updates'!$B$5:$B$304=A8),'Engineer Updates'!$E$5:$E$304),"") | S8: =IFERROR(LOOKUP(2,1/('Engineer Updates'!$B$5:$B$304=A8),'Engineer Updates'!$D$5:$D$304),"") | T8: =IFERROR(LOOKUP(2,1/('Engineer Updates'!$B$5:$B$304=A8),'Engineer Updates'!$F$5:$F$304),"") | U8: =IFERROR(LOOKUP(2,1/('Engineer Updates'!$B$5:$B$304=A8),'Engineer Updates'!$G$5:$G$304),"") | V8: =IFERROR(LOOKUP(2,1/('Engineer Updates'!$B$5:$B$304=A8),'Engineer Updates'!$H$5:$H$304),"") | W8: =IFERROR(LOOKUP(2,1/('Engineer Updates'!$B$5:$B$304=A8),'Engineer Updates'!$I$5:$I$304),"") | X8: =IF(AND(C8="executing",ISERROR(SEARCH("@",K8))),"Executing without named engineer",IF(AND(N8="Confirmed OOS",C8="executing"),"Confirmed OOS still executing","")) | Y8: CSSP-Decommisioning-1708.xlsx
A9: CSSP10958195 | B9: Decommissioning | C9: processing | D9: 46251 | E9: 46196.12 | F9: 46209.311 | G9: Lab Information Management System - LIMS MLNG | H9: OCI MIGRATION - Integrated Lab Information System (MLNG) | I9: M | J9: CCoE Operations | K9: =IFERROR(LOOKUP(2,1/('Assignment History'!$B$5:$B$204=A9),'Assignment History'!$D$5:$D$204),IFERROR(VLOOKUP(J9,Configuration!$L$5:$M$50,2,FALSE),J9)) -> CCoE Operations | L9: =IF(K9=IFERROR(VLOOKUP(J9,Configuration!$L$5:$M$50,2,FALSE),J9),"Snapshot PIC","Replacement PIC") -> Snapshot PIC | M9: =IFERROR(VLOOKUP(I9,Configuration!$O$5:$P$8,2,FALSE),Configuration!$S$6) -> 2 | N9: =IFERROR(LOOKUP(2,1/('Scope Review'!$B$5:$B$204=A9),'Scope Review'!$G$5:$G$204),"Not Reviewed") -> Not Reviewed | O9: =IFERROR(LOOKUP(2,1/('Scope Review'!$B$5:$B$204=A9),'Scope Review'!$H$5:$H$204),"") | P9: =IF(AND(C9="executing",N9<>"Confirmed OOS"),M9,0) -> 0 | Q9: =IFERROR(LOOKUP(2,1/('Engineer Updates'!$B$5:$B$304=A9),'Engineer Updates'!$A$5:$A$304),"") | R9: =IFERROR(LOOKUP(2,1/('Engineer Updates'!$B$5:$B$304=A9),'Engineer Updates'!$E$5:$E$304),"") | S9: =IFERROR(LOOKUP(2,1/('Engineer Updates'!$B$5:$B$304=A9),'Engineer Updates'!$D$5:$D$304),"") | T9: =IFERROR(LOOKUP(2,1/('Engineer Updates'!$B$5:$B$304=A9),'Engineer Updates'!$F$5:$F$304),"") | U9: =IFERROR(LOOKUP(2,1/('Engineer Updates'!$B$5:$B$304=A9),'Engineer Updates'!$G$5:$G$304),"") | V9: =IFERROR(LOOKUP(2,1/('Engineer Updates'!$B$5:$B$304=A9),'Engineer Updates'!$H$5:$H$304),"") | W9: =IFERROR(LOOKUP(2,1/('Engineer Updates'!$B$5:$B$304=A9),'Engineer Updates'!$I$5:$I$304),"") | X9: =IF(AND(C9="executing",ISERROR(SEARCH("@",K9))),"Executing without named engineer",IF(AND(N9="Confirmed OOS",C9="executing"),"Confirmed OOS still executing","")) | Y9: CSSP-Decommisioning-1708.xlsx
A10: CSSP10321088 | B10: Decommissioning | C10: processing | D10: 46251 | E10: 46245.32 | F10: 46251.168 | G10: RTMS | H10: Cloud Migration Program - PPTSB RTMS | I10: L | J10: IMS - CLOUD CSSP EXECUTOR | K10: =IFERROR(LOOKUP(2,1/('Assignment History'!$B$5:$B$204=A10),'Assignment History'!$D$5:$D$204),IFERROR(VLOOKUP(J10,Configuration!$L$5:$M$50,2,FALSE),J10)) -> IMS - CLOUD CSSP EXECUTOR | L10: =IF(K10=IFERROR(VLOOKUP(J10,Configuration!$L$5:$M$50,2,FALSE),J10),"Snapshot PIC","Replacement PIC") -> Snapshot PIC | M10: =IFERROR(VLOOKUP(I10,Configuration!$O$5:$P$8,2,FALSE),Configuration!$S$6) -> 3 | N10: =IFERROR(LOOKUP(2,1/('Scope Review'!$B$5:$B$204=A10),'Scope Review'!$G$5:$G$204),"Not Reviewed") -> Not Reviewed | O10: =IFERROR(LOOKUP(2,1/('Scope Review'!$B$5:$B$204=A10),'Scope Review'!$H$5:$H$204),"") | P10: =IF(AND(C10="executing",N10<>"Confirmed OOS"),M10,0) -> 0 | Q10: =IFERROR(LOOKUP(2,1/('Engineer Updates'!$B$5:$B$304=A10),'Engineer Updates'!$A$5:$A$304),"") | R10: =IFERROR(LOOKUP(2,1/('Engineer Updates'!$B$5:$B$304=A10),'Engineer Updates'!$E$5:$E$304),"") | S10: =IFERROR(LOOKUP(2,1/('Engineer Updates'!$B$5:$B$304=A10),'Engineer Updates'!$D$5:$D$304),"") | T10: =IFERROR(LOOKUP(2,1/('Engineer Updates'!$B$5:$B$304=A10),'Engineer Updates'!$F$5:$F$304),"") | U10: =IFERROR(LOOKUP(2,1/('Engineer Updates'!$B$5:$B$304=A10),'Engineer Updates'!$G$5:$G$304),"") | V10: =IFERROR(LOOKUP(2,1/('Engineer Updates'!$B$5:$B$304=A10),'Engineer Updates'!$H$5:$H$304),"") | W10: =IFERROR(LOOKUP(2,1/('Engineer Updates'!$B$5:$B$304=A10),'Engineer Updates'!$I$5:$I$304),"") | X10: =IF(AND(C10="executing",ISERROR(SEARCH("@",K10))),"Executing without named engineer",IF(AND(N10="Confirmed OOS",C10="executing"),"Confirmed OOS still executing","")) | Y10: CSSP-Decommisioning-1708.xlsx
A11: CSSP10484519 | B11: Decommissioning | C11: processing | D11: 46251 | E11: 46225.029 | F11: 46244.079 | G11: Danger Dodgers | H11: Pilot Deployment of Danger Dodgers at PCFK | I11: S | J11: IMS - CLOUD CSSP EXECUTOR | K11: =IFERROR(LOOKUP(2,1/('Assignment History'!$B$5:$B$204=A11),'Assignment History'!$D$5:$D$204),IFERROR(VLOOKUP(J11,Configuration!$L$5:$M$50,2,FALSE),J11)) -> IMS - CLOUD CSSP EXECUTOR | L11: =IF(K11=IFERROR(VLOOKUP(J11,Configuration!$L$5:$M$50,2,FALSE),J11),"Snapshot PIC","Replacement PIC") -> Snapshot PIC | M11: =IFERROR(VLOOKUP(I11,Configuration!$O$5:$P$8,2,FALSE),Configuration!$S$6) -> 1 | N11: =IFERROR(LOOKUP(2,1/('Scope Review'!$B$5:$B$204=A11),'Scope Review'!$G$5:$G$204),"Not Reviewed") -> Not Reviewed | O11: =IFERROR(LOOKUP(2,1/('Scope Review'!$B$5:$B$204=A11),'Scope Review'!$H$5:$H$204),"") | P11: =IF(AND(C11="executing",N11<>"Confirmed OOS"),M11,0) -> 0 | Q11: =IFERROR(LOOKUP(2,1/('Engineer Updates'!$B$5:$B$304=A11),'Engineer Updates'!$A$5:$A$304),"") | R11: =IFERROR(LOOKUP(2,1/('Engineer Updates'!$B$5:$B$304=A11),'Engineer Updates'!$E$5:$E$304),"") | S11: =IFERROR(LOOKUP(2,1/('Engineer Updates'!$B$5:$B$304=A11),'Engineer Updates'!$D$5:$D$304),"") | T11: =IFERROR(LOOKUP(2,1/('Engineer Updates'!$B$5:$B$304=A11),'Engineer Updates'!$F$5:$F$304),"") | U11: =IFERROR(LOOKUP(2,1/('Engineer Updates'!$B$5:$B$304=A11),'Engineer Updates'!$G$5:$G$304),"") | V11: =IFERROR(LOOKUP(2,1/('Engineer Updates'!$B$5:$B$304=A11),'Engineer Updates'!$H$5:$H$304),"") | W11: =IFERROR(LOOKUP(2,1/('Engineer Updates'!$B$5:$B$304=A11),'Engineer Updates'!$I$5:$I$304),"") | X11: =IF(AND(C11="executing",ISERROR(SEARCH("@",K11))),"Executing without named engineer",IF(AND(N11="Confirmed OOS",C11="executing"),"Confirmed OOS still executing","")) | Y11: CSSP-Decommisioning-1708.xlsx
A12: CSSP10588883 | B12: Decommissioning | C12: processing | D12: 46251 | E12: 46233.11 | F12: 46251.168 | G12: Falcon | H12: Implementation of Falcon - Engineering Visual Analytics Program (Work Package 1) - Requirements Gathering, High Level Design, and Data Gathering for GTS | I12: L | J12: IMS - CLOUD CSSP EXECUTOR | K12: =IFERROR(LOOKUP(2,1/('Assignment History'!$B$5:$B$204=A12),'Assignment History'!$D$5:$D$204),IFERROR(VLOOKUP(J12,Configuration!$L$5:$M$50,2,FALSE),J12)) -> IMS - CLOUD CSSP EXECUTOR | L12: =IF(K12=IFERROR(VLOOKUP(J12,Configuration!$L$5:$M$50,2,FALSE),J12),"Snapshot PIC","Replacement PIC") -> Snapshot PIC | M12: =IFERROR(VLOOKUP(I12,Configuration!$O$5:$P$8,2,FALSE),Configuration!$S$6) -> 3 | N12: =IFERROR(LOOKUP(2,1/('Scope Review'!$B$5:$B$204=A12),'Scope Review'!$G$5:$G$204),"Not Reviewed") -> Not Reviewed | O12: =IFERROR(LOOKUP(2,1/('Scope Review'!$B$5:$B$204=A12),'Scope Review'!$H$5:$H$204),"") | P12: =IF(AND(C12="executing",N12<>"Confirmed OOS"),M12,0) -> 0 | Q12: =IFERROR(LOOKUP(2,1/('Engineer Updates'!$B$5:$B$304=A12),'Engineer Updates'!$A$5:$A$304),"") | R12: =IFERROR(LOOKUP(2,1/('Engineer Updates'!$B$5:$B$304=A12),'Engineer Updates'!$E$5:$E$304),"") | S12: =IFERROR(LOOKUP(2,1/('Engineer Updates'!$B$5:$B$304=A12),'Engineer Updates'!$D$5:$D$304),"") | T12: =IFERROR(LOOKUP(2,1/('Engineer Updates'!$B$5:$B$304=A12),'Engineer Updates'!$F$5:$F$304),"") | U12: =IFERROR(LOOKUP(2,1/('Engineer Updates'!$B$5:$B$304=A12),'Engineer Updates'!$G$5:$G$304),"") | V12: =IFERROR(LOOKUP(2,1/('Engineer Updates'!$B$5:$B$304=A12),'Engineer Updates'!$H$5:$H$304),"") | W12: =IFERROR(LOOKUP(2,1/('Engineer Updates'!$B$5:$B$304=A12),'Engineer Updates'!$I$5:$I$304),"") | X12: =IF(AND(C12="executing",ISERROR(SEARCH("@",K12))),"Executing without named engineer",IF(AND(N12="Confirmed OOS",C12="executing"),"Confirmed OOS still executing","")) | Y12: CSSP-Decommisioning-1708.xlsx
A13: CSSP10589613 | B13: Decommissioning | C13: processing | D13: 46251 | E13: 46227.313 | F13: 46251.167 | G13: Rystad Energy Auth Server | H13: Hosting of Rystad Energy Ucube and Database for Upstream Strategy & Commercial | I13: L | J13: IMS - CLOUD CSSP EXECUTOR | K13: =IFERROR(LOOKUP(2,1/('Assignment History'!$B$5:$B$204=A13),'Assignment History'!$D$5:$D$204),IFERROR(VLOOKUP(J13,Configuration!$L$5:$M$50,2,FALSE),J13)) -> IMS - CLOUD CSSP EXECUTOR | L13: =IF(K13=IFERROR(VLOOKUP(J13,Configuration!$L$5:$M$50,2,FALSE),J13),"Snapshot PIC","Replacement PIC") -> Snapshot PIC | M13: =IFERROR(VLOOKUP(I13,Configuration!$O$5:$P$8,2,FALSE),Configuration!$S$6) -> 3 | N13: =IFERROR(LOOKUP(2,1/('Scope Review'!$B$5:$B$204=A13),'Scope Review'!$G$5:$G$204),"Not Reviewed") -> Not Reviewed | O13: =IFERROR(LOOKUP(2,1/('Scope Review'!$B$5:$B$204=A13),'Scope Review'!$H$5:$H$204),"") | P13: =IF(AND(C13="executing",N13<>"Confirmed OOS"),M13,0) -> 0 | Q13: =IFERROR(LOOKUP(2,1/('Engineer Updates'!$B$5:$B$304=A13),'Engineer Updates'!$A$5:$A$304),"") | R13: =IFERROR(LOOKUP(2,1/('Engineer Updates'!$B$5:$B$304=A13),'Engineer Updates'!$E$5:$E$304),"") | S13: =IFERROR(LOOKUP(2,1/('Engineer Updates'!$B$5:$B$304=A13),'Engineer Updates'!$D$5:$D$304),"") | T13: =IFERROR(LOOKUP(2,1/('Engineer Updates'!$B$5:$B$304=A13),'Engineer Updates'!$F$5:$F$304),"") | U13: =IFERROR(LOOKUP(2,1/('Engineer Updates'!$B$5:$B$304=A13),'Engineer Updates'!$G$5:$G$304),"") | V13: =IFERROR(LOOKUP(2,1/('Engineer Updates'!$B$5:$B$304=A13),'Engineer Updates'!$H$5:$H$304),"") | W13: =IFERROR(LOOKUP(2,1/('Engineer Updates'!$B$5:$B$304=A13),'Engineer Updates'!$I$5:$I$304),"") | X13: =IF(AND(C13="executing",ISERROR(SEARCH("@",K13))),"Executing without named engineer",IF(AND(N13="Confirmed OOS",C13="executing"),"Confirmed OOS still executing","")) | Y13: CSSP-Decommisioning-1708.xlsx
A14: CSSP10684299 | B14: Decommissioning | C14: processing | D14: 46251 | E14: 46164.348 | F14: 46239.267 | G14: Refinery of the Future - ROTF PRPC | H14: CTP - Refinery of the future (ROTF) - Feedstock | J14: IMS - CLOUD CSSP EXECUTOR | K14: =IFERROR(LOOKUP(2,1/('Assignment History'!$B$5:$B$204=A14),'Assignment History'!$D$5:$D$204),IFERROR(VLOOKUP(J14,Configuration!$L$5:$M$50,2,FALSE),J14)) -> IMS - CLOUD CSSP EXECUTOR | L14: =IF(K14=IFERROR(VLOOKUP(J14,Configuration!$L$5:$M$50,2,FALSE),J14),"Snapshot PIC","Replacement PIC") -> Snapshot PIC | M14: =IFERROR(VLOOKUP(I14,Configuration!$O$5:$P$8,2,FALSE),Configuration!$S$6) -> 2 | N14: =IFERROR(LOOKUP(2,1/('Scope Review'!$B$5:$B$204=A14),'Scope Review'!$G$5:$G$204),"Not Reviewed") -> Not Reviewed | O14: =IFERROR(LOOKUP(2,1/('Scope Review'!$B$5:$B$204=A14),'Scope Review'!$H$5:$H$204),"") | P14: =IF(AND(C14="executing",N14<>"Confirmed OOS"),M14,0) -> 0 | Q14: =IFERROR(LOOKUP(2,1/('Engineer Updates'!$B$5:$B$304=A14),'Engineer Updates'!$A$5:$A$304),"") | R14: =IFERROR(LOOKUP(2,1/('Engineer Updates'!$B$5:$B$304=A14),'Engineer Updates'!$E$5:$E$304),"") | S14: =IFERROR(LOOKUP(2,1/('Engineer Updates'!$B$5:$B$304=A14),'Engineer Updates'!$D$5:$D$304),"") | T14: =IFERROR(LOOKUP(2,1/('Engineer Updates'!$B$5:$B$304=A14),'Engineer Updates'!$F$5:$F$304),"") | U14: =IFERROR(LOOKUP(2,1/('Engineer Updates'!$B$5:$B$304=A14),'Engineer Updates'!$G$5:$G$304),"") | V14: =IFERROR(LOOKUP(2,1/('Engineer Updates'!$B$5:$B$304=A14),'Engineer Updates'!$H$5:$H$304),"") | W14: =IFERROR(LOOKUP(2,1/('Engineer Updates'!$B$5:$B$304=A14),'Engineer Updates'!$I$5:$I$304),"") | X14: =IF(AND(C14="executing",ISERROR(SEARCH("@",K14))),"Executing without named engineer",IF(AND(N14="Confirmed OOS",C14="executing"),"Confirmed OOS still executing","")) | Y14: CSSP-Decommisioning-1708.xlsx
A15: CSSP10715182 | B15: Decommissioning | C15: processing | D15: 46251 | E15: 46251.284 | F15: 46251.316 | G15: Claim Tracking System - CTS | H15: Cloud Migration Program - Claim Tracking System (CTS) | J15: IMS - CLOUD CSSP EXECUTOR | K15: =IFERROR(LOOKUP(2,1/('Assignment History'!$B$5:$B$204=A15),'Assignment History'!$D$5:$D$204),IFERROR(VLOOKUP(J15,Configuration!$L$5:$M$50,2,FALSE),J15)) -> IMS - CLOUD CSSP EXECUTOR | L15: =IF(K15=IFERROR(VLOOKUP(J15,Configuration!$L$5:$M$50,2,FALSE),J15),"Snapshot PIC","Replacement PIC") -> Snapshot PIC | M15: =IFERROR(VLOOKUP(I15,Configuration!$O$5:$P$8,2,FALSE),Configuration!$S$6) -> 2 | N15: =IFERROR(LOOKUP(2,1/('Scope Review'!$B$5:$B$204=A15),'Scope Review'!$G$5:$G$204),"Not Reviewed") -> Not Reviewed | O15: =IFERROR(LOOKUP(2,1/('Scope Review'!$B$5:$B$204=A15),'Scope Review'!$H$5:$H$204),"") | P15: =IF(AND(C15="executing",N15<>"Confirmed OOS"),M15,0) -> 0 | Q15: =IFERROR(LOOKUP(2,1/('Engineer Updates'!$B$5:$B$304=A15),'Engineer Updates'!$A$5:$A$304),"") | R15: =IFERROR(LOOKUP(2,1/('Engineer Updates'!$B$5:$B$304=A15),'Engineer Updates'!$E$5:$E$304),"") | S15: =IFERROR(LOOKUP(2,1/('Engineer Updates'!$B$5:$B$304=A15),'Engineer Updates'!$D$5:$D$304),"") | T15: =IFERROR(LOOKUP(2,1/('Engineer Updates'!$B$5:$B$304=A15),'Engineer Updates'!$F$5:$F$304),"") | U15: =IFERROR(LOOKUP(2,1/('Engineer Updates'!$B$5:$B$304=A15),'Engineer Updates'!$G$5:$G$304),"") | V15: =IFERROR(LOOKUP(2,1/('Engineer Updates'!$B$5:$B$304=A15),'Engineer Updates'!$H$5:$H$304),"") | W15: =IFERROR(LOOKUP(2,1/('Engineer Updates'!$B$5:$B$304=A15),'Engineer Updates'!$I$5:$I$304),"") | X15: =IF(AND(C15="executing",ISERROR(SEARCH("@",K15))),"Executing without named engineer",IF(AND(N15="Confirmed OOS",C15="executing"),"Confirmed OOS still executing","")) | Y15: CSSP-Decommisioning-1708.xlsx
A16: CSSP10936121 | B16: Decommissioning | C16: processing | D16: 46251 | E16: 46248.17 | F16: 46251.169 | G16: Plant Information - PI PCASB | H16: Implementation of PI Asset Framework (AF) and PI Vision for PCASB | I16: L | J16: IMS - CLOUD CSSP EXECUTOR | K16: =IFERROR(LOOKUP(2,1/('Assignment History'!$B$5:$B$204=A16),'Assignment History'!$D$5:$D$204),IFERROR(VLOOKUP(J16,Configuration!$L$5:$M$50,2,FALSE),J16)) -> IMS - CLOUD CSSP EXECUTOR | L16: =IF(K16=IFERROR(VLOOKUP(J16,Configuration!$L$5:$M$50,2,FALSE),J16),"Snapshot PIC","Replacement PIC") -> Snapshot PIC | M16: =IFERROR(VLOOKUP(I16,Configuration!$O$5:$P$8,2,FALSE),Configuration!$S$6) -> 3 | N16: =IFERROR(LOOKUP(2,1/('Scope Review'!$B$5:$B$204=A16),'Scope Review'!$G$5:$G$204),"Not Reviewed") -> Not Reviewed | O16: =IFERROR(LOOKUP(2,1/('Scope Review'!$B$5:$B$204=A16),'Scope Review'!$H$5:$H$204),"") | P16: =IF(AND(C16="executing",N16<>"Confirmed OOS"),M16,0) -> 0 | Q16: =IFERROR(LOOKUP(2,1/('Engineer Updates'!$B$5:$B$304=A16),'Engineer Updates'!$A$5:$A$304),"") | R16: =IFERROR(LOOKUP(2,1/('Engineer Updates'!$B$5:$B$304=A16),'Engineer Updates'!$E$5:$E$304),"") | S16: =IFERROR(LOOKUP(2,1/('Engineer Updates'!$B$5:$B$304=A16),'Engineer Updates'!$D$5:$D$304),"") | T16: =IFERROR(LOOKUP(2,1/('Engineer Updates'!$B$5:$B$304=A16),'Engineer Updates'!$F$5:$F$304),"") | U16: =IFERROR(LOOKUP(2,1/('Engineer Updates'!$B$5:$B$304=A16),'Engineer Updates'!$G$5:$G$304),"") | V16: =IFERROR(LOOKUP(2,1/('Engineer Updates'!$B$5:$B$304=A16),'Engineer Updates'!$H$5:$H$304),"") | W16: =IFERROR(LOOKUP(2,1/('Engineer Updates'!$B$5:$B$304=A16),'Engineer Updates'!$I$5:$I$304),"") | X16: =IF(AND(C16="executing",ISERROR(SEARCH("@",K16))),"Executing without named engineer",IF(AND(N16="Confirmed OOS",C16="executing"),"Confirmed OOS still executing","")) | Y16: CSSP-Decommisioning-1708.xlsx
A17: CSSP10506137 | B17: Provisioning | C17: processing | D17: 46251 | E17: 46247.254 | F17: 46247.257 | G17: Ansible Enterprise Configuration Management - AECM | H17: Ansible Enterprise Configuration Management | J17: IMS - CLOUD CSSP EXECUTOR | K17: =IFERROR(LOOKUP(2,1/('Assignment History'!$B$5:$B$204=A17),'Assignment History'!$D$5:$D$204),IFERROR(VLOOKUP(J17,Configuration!$L$5:$M$50,2,FALSE),J17)) -> IMS - CLOUD CSSP EXECUTOR | L17: =IF(K17=IFERROR(VLOOKUP(J17,Configuration!$L$5:$M$50,2,FALSE),J17),"Snapshot PIC","Replacement PIC") -> Snapshot PIC | M17: =IFERROR(VLOOKUP(I17,Configuration!$O$5:$P$8,2,FALSE),Configuration!$S$6) -> 2 | N17: =IFERROR(LOOKUP(2,1/('Scope Review'!$B$5:$B$204=A17),'Scope Review'!$G$5:$G$204),"Not Reviewed") -> Not Reviewed | O17: =IFERROR(LOOKUP(2,1/('Scope Review'!$B$5:$B$204=A17),'Scope Review'!$H$5:$H$204),"") | P17: =IF(AND(C17="executing",N17<>"Confirmed OOS"),M17,0) -> 0 | Q17: =IFERROR(LOOKUP(2,1/('Engineer Updates'!$B$5:$B$304=A17),'Engineer Updates'!$A$5:$A$304),"") | R17: =IFERROR(LOOKUP(2,1/('Engineer Updates'!$B$5:$B$304=A17),'Engineer Updates'!$E$5:$E$304),"") | S17: =IFERROR(LOOKUP(2,1/('Engineer Updates'!$B$5:$B$304=A17),'Engineer Updates'!$D$5:$D$304),"") | T17: =IFERROR(LOOKUP(2,1/('Engineer Updates'!$B$5:$B$304=A17),'Engineer Updates'!$F$5:$F$304),"") | U17: =IFERROR(LOOKUP(2,1/('Engineer Updates'!$B$5:$B$304=A17),'Engineer Updates'!$G$5:$G$304),"") | V17: =IFERROR(LOOKUP(2,1/('Engineer Updates'!$B$5:$B$304=A17),'Engineer Updates'!$H$5:$H$304),"") | W17: =IFERROR(LOOKUP(2,1/('Engineer Updates'!$B$5:$B$304=A17),'Engineer Updates'!$I$5:$I$304),"") | X17: =IF(AND(C17="executing",ISERROR(SEARCH("@",K17))),"Executing without named engineer",IF(AND(N17="Confirmed OOS",C17="executing"),"Confirmed OOS still executing","")) | Y17: CSSP-Provisioning-1708.xlsx
A18: CSSP10675946 | B18: Provisioning | C18: processing | D18: 46251 | E18: 46247.26 | F18: 46251.171 | G18: Zentory+ | H18: Zentory+ Integration Layer | I18: M | J18: IMS - CLOUD CSSP EXECUTOR | K18: =IFERROR(LOOKUP(2,1/('Assignment History'!$B$5:$B$204=A18),'Assignment History'!$D$5:$D$204),IFERROR(VLOOKUP(J18,Configuration!$L$5:$M$50,2,FALSE),J18)) -> IMS - CLOUD CSSP EXECUTOR | L18: =IF(K18=IFERROR(VLOOKUP(J18,Configuration!$L$5:$M$50,2,FALSE),J18),"Snapshot PIC","Replacement PIC") -> Snapshot PIC | M18: =IFERROR(VLOOKUP(I18,Configuration!$O$5:$P$8,2,FALSE),Configuration!$S$6) -> 2 | N18: =IFERROR(LOOKUP(2,1/('Scope Review'!$B$5:$B$204=A18),'Scope Review'!$G$5:$G$204),"Not Reviewed") -> Not Reviewed | O18: =IFERROR(LOOKUP(2,1/('Scope Review'!$B$5:$B$204=A18),'Scope Review'!$H$5:$H$204),"") | P18: =IF(AND(C18="executing",N18<>"Confirmed OOS"),M18,0) -> 0 | Q18: =IFERROR(LOOKUP(2,1/('Engineer Updates'!$B$5:$B$304=A18),'Engineer Updates'!$A$5:$A$304),"") | R18: =IFERROR(LOOKUP(2,1/('Engineer Updates'!$B$5:$B$304=A18),'Engineer Updates'!$E$5:$E$304),"") | S18: =IFERROR(LOOKUP(2,1/('Engineer Updates'!$B$5:$B$304=A18),'Engineer Updates'!$D$5:$D$304),"") | T18: =IFERROR(LOOKUP(2,1/('Engineer Updates'!$B$5:$B$304=A18),'Engineer Updates'!$F$5:$F$304),"") | U18: =IFERROR(LOOKUP(2,1/('Engineer Updates'!$B$5:$B$304=A18),'Engineer Updates'!$G$5:$G$304),"") | V18: =IFERROR(LOOKUP(2,1/('Engineer Updates'!$B$5:$B$304=A18),'Engineer Updates'!$H$5:$H$304),"") | W18: =IFERROR(LOOKUP(2,1/('Engineer Updates'!$B$5:$B$304=A18),'Engineer Updates'!$I$5:$I$304),"") | X18: =IF(AND(C18="executing",ISERROR(SEARCH("@",K18))),"Executing without named engineer",IF(AND(N18="Confirmed OOS",C18="executing"),"Confirmed OOS still executing","")) | Y18: CSSP-Provisioning-1708.xlsx
A19: CSSP10933294 | B19: Provisioning | C19: processing | D19: 46251 | E19: 46248.337 | F19: 46251.157 | G19: Cyber Security SENTINEL | H19: Onboarding of Centralised Log Collector and Security Information & Event Management (SIEM) for SETEL | I19: S | J19: IMS - CLOUD CSSP EXECUTOR | K19: =IFERROR(LOOKUP(2,1/('Assignment History'!$B$5:$B$204=A19),'Assignment History'!$D$5:$D$204),IFERROR(VLOOKUP(J19,Configuration!$L$5:$M$50,2,FALSE),J19)) -> IMS - CLOUD CSSP EXECUTOR | L19: =IF(K19=IFERROR(VLOOKUP(J19,Configuration!$L$5:$M$50,2,FALSE),J19),"Snapshot PIC","Replacement PIC") -> Snapshot PIC | M19: =IFERROR(VLOOKUP(I19,Configuration!$O$5:$P$8,2,FALSE),Configuration!$S$6) -> 1 | N19: =IFERROR(LOOKUP(2,1/('Scope Review'!$B$5:$B$204=A19),'Scope Review'!$G$5:$G$204),"Not Reviewed") -> Not Reviewed | O19: =IFERROR(LOOKUP(2,1/('Scope Review'!$B$5:$B$204=A19),'Scope Review'!$H$5:$H$204),"") | P19: =IF(AND(C19="executing",N19<>"Confirmed OOS"),M19,0) -> 0 | Q19: =IFERROR(LOOKUP(2,1/('Engineer Updates'!$B$5:$B$304=A19),'Engineer Updates'!$A$5:$A$304),"") | R19: =IFERROR(LOOKUP(2,1/('Engineer Updates'!$B$5:$B$304=A19),'Engineer Updates'!$E$5:$E$304),"") | S19: =IFERROR(LOOKUP(2,1/('Engineer Updates'!$B$5:$B$304=A19),'Engineer Updates'!$D$5:$D$304),"") | T19: =IFERROR(LOOKUP(2,1/('Engineer Updates'!$B$5:$B$304=A19),'Engineer Updates'!$F$5:$F$304),"") | U19: =IFERROR(LOOKUP(2,1/('Engineer Updates'!$B$5:$B$304=A19),'Engineer Updates'!$G$5:$G$304),"") | V19: =IFERROR(LOOKUP(2,1/('Engineer Updates'!$B$5:$B$304=A19),'Engineer Updates'!$H$5:$H$304),"") | W19: =IFERROR(LOOKUP(2,1/('Engineer Updates'!$B$5:$B$304=A19),'Engineer Updates'!$I$5:$I$304),"") | X19: =IF(AND(C19="executing",ISERROR(SEARCH("@",K19))),"Executing without named engineer",IF(AND(N19="Confirmed OOS",C19="executing"),"Confirmed OOS still executing","")) | Y19: CSSP-Provisioning-1708.xlsx
A20: CSSP10916071 | B20: Decommissioning | C20: executing | D20: 46251 | E20: 46196.124 | F20: 46251.32 | G20: Lab Information Management System - LIMS PPTSB | H20: OCI MIGRATION - LIMS PPTSB | I20: M | J20: abdul.khoir@petronas.com | K20: =IFERROR(LOOKUP(2,1/('Assignment History'!$B$5:$B$204=A20),'Assignment History'!$D$5:$D$204),IFERROR(VLOOKUP(J20,Configuration!$L$5:$M$50,2,FALSE),J20)) -> abdul.khoir@petronas.com | L20: =IF(K20=IFERROR(VLOOKUP(J20,Configuration!$L$5:$M$50,2,FALSE),J20),"Snapshot PIC","Replacement PIC") -> Snapshot PIC | M20: =IFERROR(VLOOKUP(I20,Configuration!$O$5:$P$8,2,FALSE),Configuration!$S$6) -> 2 | N20: =IFERROR(LOOKUP(2,1/('Scope Review'!$B$5:$B$204=A20),'Scope Review'!$G$5:$G$204),"Not Reviewed") -> Not Reviewed | O20: =IFERROR(LOOKUP(2,1/('Scope Review'!$B$5:$B$204=A20),'Scope Review'!$H$5:$H$204),"") | P20: =IF(AND(C20="executing",N20<>"Confirmed OOS"),M20,0) -> 2 | Q20: =IFERROR(LOOKUP(2,1/('Engineer Updates'!$B$5:$B$304=A20),'Engineer Updates'!$A$5:$A$304),"") -> 46251 | R20: =IFERROR(LOOKUP(2,1/('Engineer Updates'!$B$5:$B$304=A20),'Engineer Updates'!$E$5:$E$304),"") -> Not Started | S20: =IFERROR(LOOKUP(2,1/('Engineer Updates'!$B$5:$B$304=A20),'Engineer Updates'!$D$5:$D$304),"") -> 0 | T20: =IFERROR(LOOKUP(2,1/('Engineer Updates'!$B$5:$B$304=A20),'Engineer Updates'!$F$5:$F$304),"") -> 0 | U20: =IFERROR(LOOKUP(2,1/('Engineer Updates'!$B$5:$B$304=A20),'Engineer Updates'!$G$5:$G$304),"") -> 0 | V20: =IFERROR(LOOKUP(2,1/('Engineer Updates'!$B$5:$B$304=A20),'Engineer Updates'!$H$5:$H$304),"") -> 0 | W20: =IFERROR(LOOKUP(2,1/('Engineer Updates'!$B$5:$B$304=A20),'Engineer Updates'!$I$5:$I$304),"") -> 0 | X20: =IF(AND(C20="executing",ISERROR(SEARCH("@",K20))),"Executing without named engineer",IF(AND(N20="Confirmed OOS",C20="executing"),"Confirmed OOS still executing","")) | Y20: CSSP-Decommisioning-1708.xlsx
A21: CSSP10372916 | B21: Decommissioning | C21: executing | D21: 46251 | E21: 46226.128 | F21: 46233.106 | G21: Plant Information - PI MLNG | H21: Plant Information - PI MLNG created for PRIVATECLOUD project record | I21: M | J21: abhishek.bhowate@petronas.com | K21: =IFERROR(LOOKUP(2,1/('Assignment History'!$B$5:$B$204=A21),'Assignment History'!$D$5:$D$204),IFERROR(VLOOKUP(J21,Configuration!$L$5:$M$50,2,FALSE),J21)) -> abdul.khoir@petronas.com | L21: =IF(K21=IFERROR(VLOOKUP(J21,Configuration!$L$5:$M$50,2,FALSE),J21),"Snapshot PIC","Replacement PIC") -> Replacement PIC | M21: =IFERROR(VLOOKUP(I21,Configuration!$O$5:$P$8,2,FALSE),Configuration!$S$6) -> 2 | N21: =IFERROR(LOOKUP(2,1/('Scope Review'!$B$5:$B$204=A21),'Scope Review'!$G$5:$G$204),"Not Reviewed") -> Not Reviewed | O21: =IFERROR(LOOKUP(2,1/('Scope Review'!$B$5:$B$204=A21),'Scope Review'!$H$5:$H$204),"") | P21: =IF(AND(C21="executing",N21<>"Confirmed OOS"),M21,0) -> 2 | Q21: =IFERROR(LOOKUP(2,1/('Engineer Updates'!$B$5:$B$304=A21),'Engineer Updates'!$A$5:$A$304),"") -> 46251 | R21: =IFERROR(LOOKUP(2,1/('Engineer Updates'!$B$5:$B$304=A21),'Engineer Updates'!$E$5:$E$304),"") -> Not Started | S21: =IFERROR(LOOKUP(2,1/('Engineer Updates'!$B$5:$B$304=A21),'Engineer Updates'!$D$5:$D$304),"") -> 0 | T21: =IFERROR(LOOKUP(2,1/('Engineer Updates'!$B$5:$B$304=A21),'Engineer Updates'!$F$5:$F$304),"") -> 0 | U21: =IFERROR(LOOKUP(2,1/('Engineer Updates'!$B$5:$B$304=A21),'Engineer Updates'!$G$5:$G$304),"") -> 0 | V21: =IFERROR(LOOKUP(2,1/('Engineer Updates'!$B$5:$B$304=A21),'Engineer Updates'!$H$5:$H$304),"") -> 0 | W21: =IFERROR(LOOKUP(2,1/('Engineer Updates'!$B$5:$B$304=A21),'Engineer Updates'!$I$5:$I$304),"") -> 0 | X21: =IF(AND(C21="executing",ISERROR(SEARCH("@",K21))),"Executing without named engineer",IF(AND(N21="Confirmed OOS",C21="executing"),"Confirmed OOS still executing","")) | Y21: CSSP-Decommisioning-1708.xlsx
A22: CSSP10989463 | B22: Decommissioning | C22: executing | D22: 46251 | E22: 46209.158 | F22: 46209.169 | G22: Cloud Self Service Portal - CSSP | H22: Cloud Digitization - Cloud Self Service Portal | I22: S | J22: abhishek.bhowate@petronas.com | K22: =IFERROR(LOOKUP(2,1/('Assignment History'!$B$5:$B$204=A22),'Assignment History'!$D$5:$D$204),IFERROR(VLOOKUP(J22,Configuration!$L$5:$M$50,2,FALSE),J22)) -> arun.karuppiah@petronas.com | L22: =IF(K22=IFERROR(VLOOKUP(J22,Configuration!$L$5:$M$50,2,FALSE),J22),"Snapshot PIC","Replacement PIC") -> Replacement PIC | M22: =IFERROR(VLOOKUP(I22,Configuration!$O$5:$P$8,2,FALSE),Configuration!$S$6) -> 1 | N22: =IFERROR(LOOKUP(2,1/('Scope Review'!$B$5:$B$204=A22),'Scope Review'!$G$5:$G$204),"Not Reviewed") -> Not Reviewed | O22: =IFERROR(LOOKUP(2,1/('Scope Review'!$B$5:$B$204=A22),'Scope Review'!$H$5:$H$204),"") | P22: =IF(AND(C22="executing",N22<>"Confirmed OOS"),M22,0) -> 1 | Q22: =IFERROR(LOOKUP(2,1/('Engineer Updates'!$B$5:$B$304=A22),'Engineer Updates'!$A$5:$A$304),"") -> 46251 | R22: =IFERROR(LOOKUP(2,1/('Engineer Updates'!$B$5:$B$304=A22),'Engineer Updates'!$E$5:$E$304),"") -> Not Started | S22: =IFERROR(LOOKUP(2,1/('Engineer Updates'!$B$5:$B$304=A22),'Engineer Updates'!$D$5:$D$304),"") -> 0 | T22: =IFERROR(LOOKUP(2,1/('Engineer Updates'!$B$5:$B$304=A22),'Engineer Updates'!$F$5:$F$304),"") -> 0 | U22: =IFERROR(LOOKUP(2,1/('Engineer Updates'!$B$5:$B$304=A22),'Engineer Updates'!$G$5:$G$304),"") -> 0 | V22: =IFERROR(LOOKUP(2,1/('Engineer Updates'!$B$5:$B$304=A22),'Engineer Updates'!$H$5:$H$304),"") -> 0 | W22: =IFERROR(LOOKUP(2,1/('Engineer Updates'!$B$5:$B$304=A22),'Engineer Updates'!$I$5:$I$304),"") -> 0 | X22: =IF(AND(C22="executing",ISERROR(SEARCH("@",K22))),"Executing without named engineer",IF(AND(N22="Confirmed OOS",C22="executing"),"Confirmed OOS still executing","")) | Y22: CSSP-Decommisioning-1708.xlsx
A23: CSSP10186192 | B23: Decommissioning | C23: executing | D23: 46251 | E23: 46233.11 | F23: 46246.652 | G23: Falcon | H23: FALCON for CORIMS Image Analytics (IA) for Composite Repair Module for GTS | I23: M | J23: amarja.kawade@petronas.com | K23: =IFERROR(LOOKUP(2,1/('Assignment History'!$B$5:$B$204=A23),'Assignment History'!$D$5:$D$204),IFERROR(VLOOKUP(J23,Configuration!$L$5:$M$50,2,FALSE),J23)) -> amarja.kawade@petronas.com | L23: =IF(K23=IFERROR(VLOOKUP(J23,Configuration!$L$5:$M$50,2,FALSE),J23),"Snapshot PIC","Replacement PIC") -> Snapshot PIC | M23: =IFERROR(VLOOKUP(I23,Configuration!$O$5:$P$8,2,FALSE),Configuration!$S$6) -> 2 | N23: =IFERROR(LOOKUP(2,1/('Scope Review'!$B$5:$B$204=A23),'Scope Review'!$G$5:$G$204),"Not Reviewed") -> Not Reviewed | O23: =IFERROR(LOOKUP(2,1/('Scope Review'!$B$5:$B$204=A23),'Scope Review'!$H$5:$H$204),"") | P23: =IF(AND(C23="executing",N23<>"Confirmed OOS"),M23,0) -> 2 | Q23: =IFERROR(LOOKUP(2,1/('Engineer Updates'!$B$5:$B$304=A23),'Engineer Updates'!$A$5:$A$304),"") -> 46251 | R23: =IFERROR(LOOKUP(2,1/('Engineer Updates'!$B$5:$B$304=A23),'Engineer Updates'!$E$5:$E$304),"") -> Not Started | S23: =IFERROR(LOOKUP(2,1/('Engineer Updates'!$B$5:$B$304=A23),'Engineer Updates'!$D$5:$D$304),"") -> 0 | T23: =IFERROR(LOOKUP(2,1/('Engineer Updates'!$B$5:$B$304=A23),'Engineer Updates'!$F$5:$F$304),"") -> 0 | U23: =IFERROR(LOOKUP(2,1/('Engineer Updates'!$B$5:$B$304=A23),'Engineer Updates'!$G$5:$G$304),"") -> 0 | V23: =IFERROR(LOOKUP(2,1/('Engineer Updates'!$B$5:$B$304=A23),'Engineer Updates'!$H$5:$H$304),"") -> 0 | W23: =IFERROR(LOOKUP(2,1/('Engineer Updates'!$B$5:$B$304=A23),'Engineer Updates'!$I$5:$I$304),"") -> 0 | X23: =IF(AND(C23="executing",ISERROR(SEARCH("@",K23))),"Executing without named engineer",IF(AND(N23="Confirmed OOS",C23="executing"),"Confirmed OOS still executing","")) | Y23: CSSP-Decommisioning-1708.xlsx
A24: CSSP10187579 | B24: Decommissioning | C24: executing | D24: 46251 | E24: 46226.089 | F24: 46231.205 | G24: IMIM / PCSB - Sabah Asset Project | H24: IMIM / PCSB - Sabah Asset Project created for PRIVATECLOUD project record | I24: S | J24: amarja.kawade@petronas.com | K24: =IFERROR(LOOKUP(2,1/('Assignment History'!$B$5:$B$204=A24),'Assignment History'!$D$5:$D$204),IFERROR(VLOOKUP(J24,Configuration!$L$5:$M$50,2,FALSE),J24)) -> amarja.kawade@petronas.com | L24: =IF(K24=IFERROR(VLOOKUP(J24,Configuration!$L$5:$M$50,2,FALSE),J24),"Snapshot PIC","Replacement PIC") -> Snapshot PIC | M24: =IFERROR(VLOOKUP(I24,Configuration!$O$5:$P$8,2,FALSE),Configuration!$S$6) -> 1 | N24: =IFERROR(LOOKUP(2,1/('Scope Review'!$B$5:$B$204=A24),'Scope Review'!$G$5:$G$204),"Not Reviewed") -> Not Reviewed | O24: =IFERROR(LOOKUP(2,1/('Scope Review'!$B$5:$B$204=A24),'Scope Review'!$H$5:$H$204),"") | P24: =IF(AND(C24="executing",N24<>"Confirmed OOS"),M24,0) -> 1 | Q24: =IFERROR(LOOKUP(2,1/('Engineer Updates'!$B$5:$B$304=A24),'Engineer Updates'!$A$5:$A$304),"") -> 46251 | R24: =IFERROR(LOOKUP(2,1/('Engineer Updates'!$B$5:$B$304=A24),'Engineer Updates'!$E$5:$E$304),"") -> Not Started | S24: =IFERROR(LOOKUP(2,1/('Engineer Updates'!$B$5:$B$304=A24),'Engineer Updates'!$D$5:$D$304),"") -> 0 | T24: =IFERROR(LOOKUP(2,1/('Engineer Updates'!$B$5:$B$304=A24),'Engineer Updates'!$F$5:$F$304),"") -> 0 | U24: =IFERROR(LOOKUP(2,1/('Engineer Updates'!$B$5:$B$304=A24),'Engineer Updates'!$G$5:$G$304),"") -> 0 | V24: =IFERROR(LOOKUP(2,1/('Engineer Updates'!$B$5:$B$304=A24),'Engineer Updates'!$H$5:$H$304),"") -> 0 | W24: =IFERROR(LOOKUP(2,1/('Engineer Updates'!$B$5:$B$304=A24),'Engineer Updates'!$I$5:$I$304),"") -> 0 | X24: =IF(AND(C24="executing",ISERROR(SEARCH("@",K24))),"Executing without named engineer",IF(AND(N24="Confirmed OOS",C24="executing"),"Confirmed OOS still executing","")) | Y24: CSSP-Decommisioning-1708.xlsx
A25: CSSP10323752 | B25: Decommissioning | C25: executing | D25: 46251 | E25: 46199.354 | F25: 46247.116 | G25: M365 Exchange 2016 for Centralised Automation Management Console | H25: M365-Microsoft Exchange Edge server for Address Rewriting | I25: S | J25: amarja.kawade@petronas.com | K25: =IFERROR(LOOKUP(2,1/('Assignment History'!$B$5:$B$204=A25),'Assignment History'!$D$5:$D$204),IFERROR(VLOOKUP(J25,Configuration!$L$5:$M$50,2,FALSE),J25)) -> amarja.kawade@petronas.com | L25: =IF(K25=IFERROR(VLOOKUP(J25,Configuration!$L$5:$M$50,2,FALSE),J25),"Snapshot PIC","Replacement PIC") -> Snapshot PIC | M25: =IFERROR(VLOOKUP(I25,Configuration!$O$5:$P$8,2,FALSE),Configuration!$S$6) -> 1 | N25: =IFERROR(LOOKUP(2,1/('Scope Review'!$B$5:$B$204=A25),'Scope Review'!$G$5:$G$204),"Not Reviewed") -> Not Reviewed | O25: =IFERROR(LOOKUP(2,1/('Scope Review'!$B$5:$B$204=A25),'Scope Review'!$H$5:$H$204),"") | P25: =IF(AND(C25="executing",N25<>"Confirmed OOS"),M25,0) -> 1 | Q25: =IFERROR(LOOKUP(2,1/('Engineer Updates'!$B$5:$B$304=A25),'Engineer Updates'!$A$5:$A$304),"") -> 46251 | R25: =IFERROR(LOOKUP(2,1/('Engineer Updates'!$B$5:$B$304=A25),'Engineer Updates'!$E$5:$E$304),"") -> Not Started | S25: =IFERROR(LOOKUP(2,1/('Engineer Updates'!$B$5:$B$304=A25),'Engineer Updates'!$D$5:$D$304),"") -> 0 | T25: =IFERROR(LOOKUP(2,1/('Engineer Updates'!$B$5:$B$304=A25),'Engineer Updates'!$F$5:$F$304),"") -> 0 | U25: =IFERROR(LOOKUP(2,1/('Engineer Updates'!$B$5:$B$304=A25),'Engineer Updates'!$G$5:$G$304),"") -> 0 | V25: =IFERROR(LOOKUP(2,1/('Engineer Updates'!$B$5:$B$304=A25),'Engineer Updates'!$H$5:$H$304),"") -> 0 | W25: =IFERROR(LOOKUP(2,1/('Engineer Updates'!$B$5:$B$304=A25),'Engineer Updates'!$I$5:$I$304),"") -> 0 | X25: =IF(AND(C25="executing",ISERROR(SEARCH("@",K25))),"Executing without named engineer",IF(AND(N25="Confirmed OOS",C25="executing"),"Confirmed OOS still executing","")) | Y25: CSSP-Decommisioning-1708.xlsx
A26: CSSP10327858 | B26: Decommissioning | C26: executing | D26: 46251 | E26: 46226.263 | F26: 46233.105 | G26: Data Logger ODM with OSISoft PI System | H26: Data Logger ODM with OSISoft PI System created for PRIVATECLOUD project record | I26: M | J26: amarja.kawade@petronas.com | K26: =IFERROR(LOOKUP(2,1/('Assignment History'!$B$5:$B$204=A26),'Assignment History'!$D$5:$D$204),IFERROR(VLOOKUP(J26,Configuration!$L$5:$M$50,2,FALSE),J26)) -> amarja.kawade@petronas.com | L26: =IF(K26=IFERROR(VLOOKUP(J26,Configuration!$L$5:$M$50,2,FALSE),J26),"Snapshot PIC","Replacement PIC") -> Snapshot PIC | M26: =IFERROR(VLOOKUP(I26,Configuration!$O$5:$P$8,2,FALSE),Configuration!$S$6) -> 2 | N26: =IFERROR(LOOKUP(2,1/('Scope Review'!$B$5:$B$204=A26),'Scope Review'!$G$5:$G$204),"Not Reviewed") -> Not Reviewed | O26: =IFERROR(LOOKUP(2,1/('Scope Review'!$B$5:$B$204=A26),'Scope Review'!$H$5:$H$204),"") | P26: =IF(AND(C26="executing",N26<>"Confirmed OOS"),M26,0) -> 2 | Q26: =IFERROR(LOOKUP(2,1/('Engineer Updates'!$B$5:$B$304=A26),'Engineer Updates'!$A$5:$A$304),"") -> 46251 | R26: =IFERROR(LOOKUP(2,1/('Engineer Updates'!$B$5:$B$304=A26),'Engineer Updates'!$E$5:$E$304),"") -> Not Started | S26: =IFERROR(LOOKUP(2,1/('Engineer Updates'!$B$5:$B$304=A26),'Engineer Updates'!$D$5:$D$304),"") -> 0 | T26: =IFERROR(LOOKUP(2,1/('Engineer Updates'!$B$5:$B$304=A26),'Engineer Updates'!$F$5:$F$304),"") -> 0 | U26: =IFERROR(LOOKUP(2,1/('Engineer Updates'!$B$5:$B$304=A26),'Engineer Updates'!$G$5:$G$304),"") -> 0 | V26: =IFERROR(LOOKUP(2,1/('Engineer Updates'!$B$5:$B$304=A26),'Engineer Updates'!$H$5:$H$304),"") -> 0 | W26: =IFERROR(LOOKUP(2,1/('Engineer Updates'!$B$5:$B$304=A26),'Engineer Updates'!$I$5:$I$304),"") -> 0 | X26: =IF(AND(C26="executing",ISERROR(SEARCH("@",K26))),"Executing without named engineer",IF(AND(N26="Confirmed OOS",C26="executing"),"Confirmed OOS still executing","")) | Y26: CSSP-Decommisioning-1708.xlsx
A27: CSSP10376841 | B27: Decommissioning | C27: executing | D27: 46251 | E27: 46237.103 | F27: 46246.651 | G27: Capability Integrated Management System - CIMS | H27: Upstream Shared Support Services (SecOps) FY2025 for MA, IVA, AD & SA | I27: M | J27: amarja.kawade@petronas.com | K27: =IFERROR(LOOKUP(2,1/('Assignment History'!$B$5:$B$204=A27),'Assignment History'!$D$5:$D$204),IFERROR(VLOOKUP(J27,Configuration!$L$5:$M$50,2,FALSE),J27)) -> amarja.kawade@petronas.com | L27: =IF(K27=IFERROR(VLOOKUP(J27,Configuration!$L$5:$M$50,2,FALSE),J27),"Snapshot PIC","Replacement PIC") -> Snapshot PIC | M27: =IFERROR(VLOOKUP(I27,Configuration!$O$5:$P$8,2,FALSE),Configuration!$S$6) -> 2 | N27: =IFERROR(LOOKUP(2,1/('Scope Review'!$B$5:$B$204=A27),'Scope Review'!$G$5:$G$204),"Not Reviewed") -> Not Reviewed | O27: =IFERROR(LOOKUP(2,1/('Scope Review'!$B$5:$B$204=A27),'Scope Review'!$H$5:$H$204),"") | P27: =IF(AND(C27="executing",N27<>"Confirmed OOS"),M27,0) -> 2 | Q27: =IFERROR(LOOKUP(2,1/('Engineer Updates'!$B$5:$B$304=A27),'Engineer Updates'!$A$5:$A$304),"") -> 46251 | R27: =IFERROR(LOOKUP(2,1/('Engineer Updates'!$B$5:$B$304=A27),'Engineer Updates'!$E$5:$E$304),"") -> Not Started | S27: =IFERROR(LOOKUP(2,1/('Engineer Updates'!$B$5:$B$304=A27),'Engineer Updates'!$D$5:$D$304),"") -> 0 | T27: =IFERROR(LOOKUP(2,1/('Engineer Updates'!$B$5:$B$304=A27),'Engineer Updates'!$F$5:$F$304),"") -> 0 | U27: =IFERROR(LOOKUP(2,1/('Engineer Updates'!$B$5:$B$304=A27),'Engineer Updates'!$G$5:$G$304),"") -> 0 | V27: =IFERROR(LOOKUP(2,1/('Engineer Updates'!$B$5:$B$304=A27),'Engineer Updates'!$H$5:$H$304),"") -> 0 | W27: =IFERROR(LOOKUP(2,1/('Engineer Updates'!$B$5:$B$304=A27),'Engineer Updates'!$I$5:$I$304),"") -> 0 | X27: =IF(AND(C27="executing",ISERROR(SEARCH("@",K27))),"Executing without named engineer",IF(AND(N27="Confirmed OOS",C27="executing"),"Confirmed OOS still executing","")) | Y27: CSSP-Decommisioning-1708.xlsx
A28: CSSP10413108 | B28: Decommissioning | C28: executing | D28: 46251 | E28: 46226.25 | F28: 46239.619 | G28: E-CAKNA PCSB | H28: E-CAKNA PCSB created for PRIVATECLOUD project record | I28: M | J28: amarja.kawade@petronas.com | K28: =IFERROR(LOOKUP(2,1/('Assignment History'!$B$5:$B$204=A28),'Assignment History'!$D$5:$D$204),IFERROR(VLOOKUP(J28,Configuration!$L$5:$M$50,2,FALSE),J28)) -> amarja.kawade@petronas.com | L28: =IF(K28=IFERROR(VLOOKUP(J28,Configuration!$L$5:$M$50,2,FALSE),J28),"Snapshot PIC","Replacement PIC") -> Snapshot PIC | M28: =IFERROR(VLOOKUP(I28,Configuration!$O$5:$P$8,2,FALSE),Configuration!$S$6) -> 2 | N28: =IFERROR(LOOKUP(2,1/('Scope Review'!$B$5:$B$204=A28),'Scope Review'!$G$5:$G$204),"Not Reviewed") -> Not Reviewed | O28: =IFERROR(LOOKUP(2,1/('Scope Review'!$B$5:$B$204=A28),'Scope Review'!$H$5:$H$204),"") | P28: =IF(AND(C28="executing",N28<>"Confirmed OOS"),M28,0) -> 2 | Q28: =IFERROR(LOOKUP(2,1/('Engineer Updates'!$B$5:$B$304=A28),'Engineer Updates'!$A$5:$A$304),"") -> 46251 | R28: =IFERROR(LOOKUP(2,1/('Engineer Updates'!$B$5:$B$304=A28),'Engineer Updates'!$E$5:$E$304),"") -> Not Started | S28: =IFERROR(LOOKUP(2,1/('Engineer Updates'!$B$5:$B$304=A28),'Engineer Updates'!$D$5:$D$304),"") -> 0 | T28: =IFERROR(LOOKUP(2,1/('Engineer Updates'!$B$5:$B$304=A28),'Engineer Updates'!$F$5:$F$304),"") -> 0 | U28: =IFERROR(LOOKUP(2,1/('Engineer Updates'!$B$5:$B$304=A28),'Engineer Updates'!$G$5:$G$304),"") -> 0 | V28: =IFERROR(LOOKUP(2,1/('Engineer Updates'!$B$5:$B$304=A28),'Engineer Updates'!$H$5:$H$304),"") -> 0 | W28: =IFERROR(LOOKUP(2,1/('Engineer Updates'!$B$5:$B$304=A28),'Engineer Updates'!$I$5:$I$304),"") -> 0 | X28: =IF(AND(C28="executing",ISERROR(SEARCH("@",K28))),"Executing without named engineer",IF(AND(N28="Confirmed OOS",C28="executing"),"Confirmed OOS still executing","")) | Y28: CSSP-Decommisioning-1708.xlsx
A29: CSSP10626318 | B29: Decommissioning | C29: executing | D29: 46251 | E29: 46226.166 | F29: 46239.29 | G29: Peer to Peer Energy Trading Platform | H29: Enhancement of Peer to Peer Energy Trading Platform for PRSB | I29: M | J29: amarja.kawade@petronas.com | K29: =IFERROR(LOOKUP(2,1/('Assignment History'!$B$5:$B$204=A29),'Assignment History'!$D$5:$D$204),IFERROR(VLOOKUP(J29,Configuration!$L$5:$M$50,2,FALSE),J29)) -> amarja.kawade@petronas.com | L29: =IF(K29=IFERROR(VLOOKUP(J29,Configuration!$L$5:$M$50,2,FALSE),J29),"Snapshot PIC","Replacement PIC") -> Snapshot PIC | M29: =IFERROR(VLOOKUP(I29,Configuration!$O$5:$P$8,2,FALSE),Configuration!$S$6) -> 2 | N29: =IFERROR(LOOKUP(2,1/('Scope Review'!$B$5:$B$204=A29),'Scope Review'!$G$5:$G$204),"Not Reviewed") -> Not Reviewed | O29: =IFERROR(LOOKUP(2,1/('Scope Review'!$B$5:$B$204=A29),'Scope Review'!$H$5:$H$204),"") | P29: =IF(AND(C29="executing",N29<>"Confirmed OOS"),M29,0) -> 2 | Q29: =IFERROR(LOOKUP(2,1/('Engineer Updates'!$B$5:$B$304=A29),'Engineer Updates'!$A$5:$A$304),"") -> 46251 | R29: =IFERROR(LOOKUP(2,1/('Engineer Updates'!$B$5:$B$304=A29),'Engineer Updates'!$E$5:$E$304),"") -> Not Started | S29: =IFERROR(LOOKUP(2,1/('Engineer Updates'!$B$5:$B$304=A29),'Engineer Updates'!$D$5:$D$304),"") -> 0 | T29: =IFERROR(LOOKUP(2,1/('Engineer Updates'!$B$5:$B$304=A29),'Engineer Updates'!$F$5:$F$304),"") -> 0 | U29: =IFERROR(LOOKUP(2,1/('Engineer Updates'!$B$5:$B$304=A29),'Engineer Updates'!$G$5:$G$304),"") -> 0 | V29: =IFERROR(LOOKUP(2,1/('Engineer Updates'!$B$5:$B$304=A29),'Engineer Updates'!$H$5:$H$304),"") -> 0 | W29: =IFERROR(LOOKUP(2,1/('Engineer Updates'!$B$5:$B$304=A29),'Engineer Updates'!$I$5:$I$304),"") -> 0 | X29: =IF(AND(C29="executing",ISERROR(SEARCH("@",K29))),"Executing without named engineer",IF(AND(N29="Confirmed OOS",C29="executing"),"Confirmed OOS still executing","")) | Y29: CSSP-Decommisioning-1708.xlsx
... A100: CSSP10984683 | B100: Provisioning | C100: executing | D100: 46251 | E100: 46225.1 | F100: 46233.104 | G100: PiriGIS | H100: Provision of Geographic Information System Infrastructure in PETRONAS Azure Cloud for Exploration | I100: M | J100: venkatesh.kalikivayi@petronas.com | K100: =IFERROR(LOOKUP(2,1/('Assignment History'!$B$5:$B$204=A100),'Assignment History'!$D$5:$D$204),IFERROR(VLOOKUP(J100,Configuration!$L$5:$M$50,2,FALSE),J100)) -> venkatesh.kalikivayi@petronas.com | L100: =IF(K100=IFERROR(VLOOKUP(J100,Configuration!$L$5:$M$50,2,FALSE),J100),"Snapshot PIC","Replacement PIC") -> Snapshot PIC | M100: =IFERROR(VLOOKUP(I100,Configuration!$O$5:$P$8,2,FALSE),Configuration!$S$6) -> 2 | N100: =IFERROR(LOOKUP(2,1/('Scope Review'!$B$5:$B$204=A100),'Scope Review'!$G$5:$G$204),"Not Reviewed") -> Not Reviewed | O100: =IFERROR(LOOKUP(2,1/('Scope Review'!$B$5:$B$204=A100),'Scope Review'!$H$5:$H$204),"") | P100: =IF(AND(C100="executing",N100<>"Confirmed OOS"),M100,0) -> 2 | Q100: =IFERROR(LOOKUP(2,1/('Engineer Updates'!$B$5:$B$304=A100),'Engineer Updates'!$A$5:$A$304),"") -> 46251 | R100: =IFERROR(LOOKUP(2,1/('Engineer Updates'!$B$5:$B$304=A100),'Engineer Updates'!$E$5:$E$304),"") -> Not Started | S100: =IFERROR(LOOKUP(2,1/('Engineer Updates'!$B$5:$B$304=A100),'Engineer Updates'!$D$5:$D$304),"") -> 0 | T100: =IFERROR(LOOKUP(2,1/('Engineer Updates'!$B$5:$B$304=A100),'Engineer Updates'!$F$5:$F$304),"") -> 0 | U100: =IFERROR(LOOKUP(2,1/('Engineer Updates'!$B$5:$B$304=A100),'Engineer Updates'!$G$5:$G$304),"") -> 0 | V100: =IFERROR(LOOKUP(2,1/('Engineer Updates'!$B$5:$B$304=A100),'Engineer Updates'!$H$5:$H$304),"") -> 0 | W100: =IFERROR(LOOKUP(2,1/('Engineer Updates'!$B$5:$B$304=A100),'Engineer Updates'!$I$5:$I$304),"") -> 0 | X100: =IF(AND(C100="executing",ISERROR(SEARCH("@",K100))),"Executing without named engineer",IF(AND(N100="Confirmed OOS",C100="executing"),"Confirmed OOS still executing","")) | Y100: CSSP-Provisioning-1708.xlsx

Sheet Daily Targets
A1: Daily Targets
A2: Manager publishes daily executing-task targets; engineers record the actual result and evidence.
A4: Target Date | B4: Request Number | C4: Snapshot Status | D4: Snapshot PIC | E4: Planned PIC | F4: Dispositioned Today | G4: Previous PIC | H4: Target Outcome | I4: Set By | J4: Set At | K4: Engineer Result | L4: Result Time | M4: Completion Evidence | N4: Carryover Reason | O4: Target Achieved | P4: Notes
A5: 46252 | B5: CSSP10231806 | C5: =IF(B5="","",IFERROR(INDEX('Task Master'!$C$5:$C$100,MATCH(B5,'Task Master'!$A$5:$A$100,0)),"")) -> executing | D5: =IF(B5="","",IFERROR(INDEX('Task Master'!$J$5:$J$100,MATCH(B5,'Task Master'!$A$5:$A$100,0)),"")) -> K.saktivelu@petronas.com | E5: =IF(B5="","",IFERROR(INDEX('Task Master'!$K$5:$K$100,MATCH(B5,'Task Master'!$A$5:$A$100,0)),"")) -> abdul.khoir@petronas.com | F5: Yes | G5: k.saktivelu@petronas.com | H5: Confirm Out-of-Scope | I5: Radit | J5: 46252 | K5: In Progress | O5: =IF(OR(A5="",B5=""),"",IF(OR(K5="Achieved",K5="Out-of-Scope Confirmed"),"Yes","No")) -> No
A6: 46252 | B6: CSSP10271745 | C6: =IF(B6="","",IFERROR(INDEX('Task Master'!$C$5:$C$100,MATCH(B6,'Task Master'!$A$5:$A$100,0)),"")) -> executing | D6: =IF(B6="","",IFERROR(INDEX('Task Master'!$J$5:$J$100,MATCH(B6,'Task Master'!$A$5:$A$100,0)),"")) -> venkatesh.kalikivayi@petronas.com | E6: =IF(B6="","",IFERROR(INDEX('Task Master'!$K$5:$K$100,MATCH(B6,'Task Master'!$A$5:$A$100,0)),"")) -> abdul.khoir@petronas.com | F6: Yes | G6: venkatesh.kalikivayi@petronas.com | H6: Confirm Out-of-Scope | I6: Radit | J6: 46252 | K6: In Progress | O6: =IF(OR(A6="",B6=""),"",IF(OR(K6="Achieved",K6="Out-of-Scope Confirmed"),"Yes","No")) -> No
A7: 46252 | B7: CSSP10328360 | C7: =IF(B7="","",IFERROR(INDEX('Task Master'!$C$5:$C$100,MATCH(B7,'Task Master'!$A$5:$A$100,0)),"")) -> executing | D7: =IF(B7="","",IFERROR(INDEX('Task Master'!$J$5:$J$100,MATCH(B7,'Task Master'!$A$5:$A$100,0)),"")) -> K.saktivelu@petronas.com | E7: =IF(B7="","",IFERROR(INDEX('Task Master'!$K$5:$K$100,MATCH(B7,'Task Master'!$A$5:$A$100,0)),"")) -> mardiansyah.rayasa@petronas.com | F7: Yes | G7: k.saktivelu@petronas.com | H7: Confirm Out-of-Scope | I7: Radit | J7: 46252 | K7: In Progress | O7: =IF(OR(A7="",B7=""),"",IF(OR(K7="Achieved",K7="Out-of-Scope Confirmed"),"Yes","No")) -> No
A8: 46252 | B8: CSSP10372916 | C8: =IF(B8="","",IFERROR(INDEX('Task Master'!$C$5:$C$100,MATCH(B8,'Task Master'!$A$5:$A$100,0)),"")) -> executing | D8: =IF(B8="","",IFERROR(INDEX('Task Master'!$J$5:$J$100,MATCH(B8,'Task Master'!$A$5:$A$100,0)),"")) -> abhishek.bhowate@petronas.com | E8: =IF(B8="","",IFERROR(INDEX('Task Master'!$K$5:$K$100,MATCH(B8,'Task Master'!$A$5:$A$100,0)),"")) -> abdul.khoir@petronas.com | F8: Yes | G8: abhishek.bhowate@petronas.com | H8: Confirm Out-of-Scope | I8: Radit | J8: 46252 | K8: In Progress | O8: =IF(OR(A8="",B8=""),"",IF(OR(K8="Achieved",K8="Out-of-Scope Confirmed"),"Yes","No")) -> No
A9: 46252 | B9: CSSP10391895 | C9: =IF(B9="","",IFERROR(INDEX('Task Master'!$C$5:$C$100,MATCH(B9,'Task Master'!$A$5:$A$100,0)),"")) -> executing | D9: =IF(B9="","",IFERROR(INDEX('Task Master'!$J$5:$J$100,MATCH(B9,'Task Master'!$A$5:$A$100,0)),"")) -> nilesh.sankpal@petronas.com | E9: =IF(B9="","",IFERROR(INDEX('Task Master'!$K$5:$K$100,MATCH(B9,'Task Master'!$A$5:$A$100,0)),"")) -> abdul.khoir@petronas.com | F9: Yes | G9: nilesh.sankpal@petronas.com | H9: Confirm Out-of-Scope | I9: Radit | J9: 46252 | K9: In Progress | O9: =IF(OR(A9="",B9=""),"",IF(OR(K9="Achieved",K9="Out-of-Scope Confirmed"),"Yes","No")) -> No
A10: 46255 | B10: CSSP10516713 | C10: =IF(B10="","",IFERROR(INDEX('Task Master'!$C$5:$C$100,MATCH(B10,'Task Master'!$A$5:$A$100,0)),"")) -> executing | D10: =IF(B10="","",IFERROR(INDEX('Task Master'!$J$5:$J$100,MATCH(B10,'Task Master'!$A$5:$A$100,0)),"")) -> amarja.kawde@petronas.com | E10: =IF(B10="","",IFERROR(INDEX('Task Master'!$K$5:$K$100,MATCH(B10,'Task Master'!$A$5:$A$100,0)),"")) -> amarja.kawade@petronas.com | F10: No | G10: amarja.kawade@petronas.com | H10: Complete Task | I10: Radit | J10: 46252 | K10: In Progress | O10: =IF(OR(A10="",B10=""),"",IF(OR(K10="Achieved",K10="Out-of-Scope Confirmed"),"Yes","No")) -> No
A11: 46255 | B11: CSSP10323752 | C11: =IF(B11="","",IFERROR(INDEX('Task Master'!$C$5:$C$100,MATCH(B11,'Task Master'!$A$5:$A$100,0)),"")) -> executing | D11: =IF(B11="","",IFERROR(INDEX('Task Master'!$J$5:$J$100,MATCH(B11,'Task Master'!$A$5:$A$100,0)),"")) -> amarja.kawade@petronas.com | E11: =IF(B11="","",IFERROR(INDEX('Task Master'!$K$5:$K$100,MATCH(B11,'Task Master'!$A$5:$A$100,0)),"")) -> amarja.kawade@petronas.com | F11: No | G11: amarja.kawade@petronas.com | H11: Complete Task | I11: Radit | J11: 46252 | K11: In Progress | O11: =IF(OR(A11="",B11=""),"",IF(OR(K11="Achieved",K11="Out-of-Scope Confirmed"),"Yes","No")) -> No
A12: 46255 | B12: CSSP10689831 | C12: =IF(B12="","",IFERROR(INDEX('Task Master'!$C$5:$C$100,MATCH(B12,'Task Master'!$A$5:$A$100,0)),"")) -> executing | D12: =IF(B12="","",IFERROR(INDEX('Task Master'!$J$5:$J$100,MATCH(B12,'Task Master'!$A$5:$A$100,0)),"")) -> amarja.kawade@petronas.com | E12: =IF(B12="","",IFERROR(INDEX('Task Master'!$K$5:$K$100,MATCH(B12,'Task Master'!$A$5:$A$100,0)),"")) -> amarja.kawade@petronas.com | F12: No | G12: amarja.kawade@petronas.com | H12: Complete Task | I12: Radit | J12: 46252 | K12: In Progress | O12: =IF(OR(A12="",B12=""),"",IF(OR(K12="Achieved",K12="Out-of-Scope Confirmed"),"Yes","No")) -> No
A13: 46255 | B13: CSSP10768118 | C13: =IF(B13="","",IFERROR(INDEX('Task Master'!$C$5:$C$100,MATCH(B13,'Task Master'!$A$5:$A$100,0)),"")) -> executing | D13: =IF(B13="","",IFERROR(INDEX('Task Master'!$J$5:$J$100,MATCH(B13,'Task Master'!$A$5:$A$100,0)),"")) -> amarja.kawde@petronas.com | E13: =IF(B13="","",IFERROR(INDEX('Task Master'!$K$5:$K$100,MATCH(B13,'Task Master'!$A$5:$A$100,0)),"")) -> amarja.kawade@petronas.com | F13: No | G13: amarja.kawade@petronas.com | H13: Complete Task | I13: Radit | J13: 46252 | K13: In Progress | O13: =IF(OR(A13="",B13=""),"",IF(OR(K13="Achieved",K13="Out-of-Scope Confirmed"),"Yes","No")) -> No
A14: 46255 | B14: CSSP10375827 | C14: =IF(B14="","",IFERROR(INDEX('Task Master'!$C$5:$C$100,MATCH(B14,'Task Master'!$A$5:$A$100,0)),"")) -> executing | D14: =IF(B14="","",IFERROR(INDEX('Task Master'!$J$5:$J$100,MATCH(B14,'Task Master'!$A$5:$A$100,0)),"")) -> amarja.kawde@petronas.com | E14: =IF(B14="","",IFERROR(INDEX('Task Master'!$K$5:$K$100,MATCH(B14,'Task Master'!$A$5:$A$100,0)),"")) -> amarja.kawade@petronas.com | F14: No | G14: amarja.kawade@petronas.com | H14: Complete Task | I14: Radit | J14: 46252 | K14: In Progress | O14: =IF(OR(A14="",B14=""),"",IF(OR(K14="Achieved",K14="Out-of-Scope Confirmed"),"Yes","No")) -> No
A15: 46255 | B15: CSSP10668539 | C15: =IF(B15="","",IFERROR(INDEX('Task Master'!$C$5:$C$100,MATCH(B15,'Task Master'!$A$5:$A$100,0)),"")) -> executing | D15: =IF(B15="","",IFERROR(INDEX('Task Master'!$J$5:$J$100,MATCH(B15,'Task Master'!$A$5:$A$100,0)),"")) -> amarja.kawde@petronas.com | E15: =IF(B15="","",IFERROR(INDEX('Task Master'!$K$5:$K$100,MATCH(B15,'Task Master'!$A$5:$A$100,0)),"")) -> amarja.kawade@petronas.com | F15: No | G15: amarja.kawade@petronas.com | H15: Complete Task | I15: Radit | J15: 46252 | K15: In Progress | O15: =IF(OR(A15="",B15=""),"",IF(OR(K15="Achieved",K15="Out-of-Scope Confirmed"),"Yes","No")) -> No
A16: 46255 | B16: CSSP10749532 | C16: =IF(B16="","",IFERROR(INDEX('Task Master'!$C$5:$C$100,MATCH(B16,'Task Master'!$A$5:$A$100,0)),"")) -> executing | D16: =IF(B16="","",IFERROR(INDEX('Task Master'!$J$5:$J$100,MATCH(B16,'Task Master'!$A$5:$A$100,0)),"")) -> amarja.kawade@petronas.com | E16: =IF(B16="","",IFERROR(INDEX('Task Master'!$K$5:$K$100,MATCH(B16,'Task Master'!$A$5:$A$100,0)),"")) -> amarja.kawade@petronas.com | F16: No | G16: amarja.kawade@petronas.com | H16: Complete Task | I16: Radit | J16: 46252 | K16: In Progress | O16: =IF(OR(A16="",B16=""),"",IF(OR(K16="Achieved",K16="Out-of-Scope Confirmed"),"Yes","No")) -> No
... A65: 46255 | B65: CSSP10328360 | C65: =IF(B65="","",IFERROR(INDEX('Task Master'!$C$5:$C$100,MATCH(B65,'Task Master'!$A$5:$A$100,0)),"")) -> executing | D65: =IF(B65="","",IFERROR(INDEX('Task Master'!$J$5:$J$100,MATCH(B65,'Task Master'!$A$5:$A$100,0)),"")) -> K.saktivelu@petronas.com | E65: =IF(B65="","",IFERROR(INDEX('Task Master'!$K$5:$K$100,MATCH(B65,'Task Master'!$A$5:$A$100,0)),"")) -> mardiansyah.rayasa@petronas.com | F65: Yes | G65: k.saktivelu@petronas.com | H65: Complete Task | I65: Radit | J65: 46252 | K65: In Progress | O65: =IF(OR(A65="",B65=""),"",IF(OR(K65="Achieved",K65="Out-of-Scope Confirmed"),"Yes","No")) -> No
C66: =IF(B66="","",IFERROR(INDEX('Task Master'!$C$5:$C$100,MATCH(B66,'Task Master'!$A$5:$A$100,0)),"")) | D66: =IF(B66="","",IFERROR(INDEX('Task Master'!$J$5:$J$100,MATCH(B66,'Task Master'!$A$5:$A$100,0)),"")) | E66: =IF(B66="","",IFERROR(INDEX('Task Master'!$K$5:$K$100,MATCH(B66,'Task Master'!$A$5:$A$100,0)),"")) | O66: =IF(OR(A66="",B66=""),"",IF(OR(K66="Achieved",K66="Out-of-Scope Confirmed"),"Yes","No"))
C67: =IF(B67="","",IFERROR(INDEX('Task Master'!$C$5:$C$100,MATCH(B67,'Task Master'!$A$5:$A$100,0)),"")) | D67: =IF(B67="","",IFERROR(INDEX('Task Master'!$J$5:$J$100,MATCH(B67,'Task Master'!$A$5:$A$100,0)),"")) | E67: =IF(B67="","",IFERROR(INDEX('Task Master'!$K$5:$K$100,MATCH(B67,'Task Master'!$A$5:$A$100,0)),"")) | O67: =IF(OR(A67="",B67=""),"",IF(OR(K67="Achieved",K67="Out-of-Scope Confirmed"),"Yes","No"))
C68: =IF(B68="","",IFERROR(INDEX('Task Master'!$C$5:$C$100,MATCH(B68,'Task Master'!$A$5:$A$100,0)),"")) | D68: =IF(B68="","",IFERROR(INDEX('Task Master'!$J$5:$J$100,MATCH(B68,'Task Master'!$A$5:$A$100,0)),"")) | E68: =IF(B68="","",IFERROR(INDEX('Task Master'!$K$5:$K$100,MATCH(B68,'Task Master'!$A$5:$A$100,0)),"")) | O68: =IF(OR(A68="",B68=""),"",IF(OR(K68="Achieved",K68="Out-of-Scope Confirmed"),"Yes","No"))
C69: =IF(B69="","",IFERROR(INDEX('Task Master'!$C$5:$C$100,MATCH(B69,'Task Master'!$A$5:$A$100,0)),"")) | D69: =IF(B69="","",IFERROR(INDEX('Task Master'!$J$5:$J$100,MATCH(B69,'Task Master'!$A$5:$A$100,0)),"")) | E69: =IF(B69="","",IFERROR(INDEX('Task Master'!$K$5:$K$100,MATCH(B69,'Task Master'!$A$5:$A$100,0)),"")) | O69: =IF(OR(A69="",B69=""),"",IF(OR(K69="Achieved",K69="Out-of-Scope Confirmed"),"Yes","No"))
C70: =IF(B70="","",IFERROR(INDEX('Task Master'!$C$5:$C$100,MATCH(B70,'Task Master'!$A$5:$A$100,0)),"")) | D70: =IF(B70="","",IFERROR(INDEX('Task Master'!$J$5:$J$100,MATCH(B70,'Task Master'!$A$5:$A$100,0)),"")) | E70: =IF(B70="","",IFERROR(INDEX('Task Master'!$K$5:$K$100,MATCH(B70,'Task Master'!$A$5:$A$100,0)),"")) | O70: =IF(OR(A70="",B70=""),"",IF(OR(K70="Achieved",K70="Out-of-Scope Confirmed"),"Yes","No"))
C71: =IF(B71="","",IFERROR(INDEX('Task Master'!$C$5:$C$100,MATCH(B71,'Task Master'!$A$5:$A$100,0)),"")) | D71: =IF(B71="","",IFERROR(INDEX('Task Master'!$J$5:$J$100,MATCH(B71,'Task Master'!$A$5:$A$100,0)),"")) | E71: =IF(B71="","",IFERROR(INDEX('Task Master'!$K$5:$K$100,MATCH(B71,'Task Master'!$A$5:$A$100,0)),"")) | O71: =IF(OR(A71="",B71=""),"",IF(OR(K71="Achieved",K71="Out-of-Scope Confirmed"),"Yes","No"))
C72: =IF(B72="","",IFERROR(INDEX('Task Master'!$C$5:$C$100,MATCH(B72,'Task Master'!$A$5:$A$100,0)),"")) | D72: =IF(B72="","",IFERROR(INDEX('Task Master'!$J$5:$J$100,MATCH(B72,'Task Master'!$A$5:$A$100,0)),"")) | E72: =IF(B72="","",IFERROR(INDEX('Task Master'!$K$5:$K$100,MATCH(B72,'Task Master'!$A$5:$A$100,0)),"")) | O72: =IF(OR(A72="",B72=""),"",IF(OR(K72="Achieved",K72="Out-of-Scope Confirmed"),"Yes","No"))
C73: =IF(B73="","",IFERROR(INDEX('Task Master'!$C$5:$C$100,MATCH(B73,'Task Master'!$A$5:$A$100,0)),"")) | D73: =IF(B73="","",IFERROR(INDEX('Task Master'!$J$5:$J$100,MATCH(B73,'Task Master'!$A$5:$A$100,0)),"")) | E73: =IF(B73="","",IFERROR(INDEX('Task Master'!$K$5:$K$100,MATCH(B73,'Task Master'!$A$5:$A$100,0)),"")) | O73: =IF(OR(A73="",B73=""),"",IF(OR(K73="Achieved",K73="Out-of-Scope Confirmed"),"Yes","No"))
C74: =IF(B74="","",IFERROR(INDEX('Task Master'!$C$5:$C$100,MATCH(B74,'Task Master'!$A$5:$A$100,0)),"")) | D74: =IF(B74="","",IFERROR(INDEX('Task Master'!$J$5:$J$100,MATCH(B74,'Task Master'!$A$5:$A$100,0)),"")) | E74: =IF(B74="","",IFERROR(INDEX('Task Master'!$K$5:$K$100,MATCH(B74,'Task Master'!$A$5:$A$100,0)),"")) | O74: =IF(OR(A74="",B74=""),"",IF(OR(K74="Achieved",K74="Out-of-Scope Confirmed"),"Yes","No"))
C75: =IF(B75="","",IFERROR(INDEX('Task Master'!$C$5:$C$100,MATCH(B75,'Task Master'!$A$5:$A$100,0)),"")) | D75: =IF(B75="","",IFERROR(INDEX('Task Master'!$J$5:$J$100,MATCH(B75,'Task Master'!$A$5:$A$100,0)),"")) | E75: =IF(B75="","",IFERROR(INDEX('Task Master'!$K$5:$K$100,MATCH(B75,'Task Master'!$A$5:$A$100,0)),"")) | O75: =IF(OR(A75="",B75=""),"",IF(OR(K75="Achieved",K75="Out-of-Scope Confirmed"),"Yes","No"))
C76: =IF(B76="","",IFERROR(INDEX('Task Master'!$C$5:$C$100,MATCH(B76,'Task Master'!$A$5:$A$100,0)),"")) | D76: =IF(B76="","",IFERROR(INDEX('Task Master'!$J$5:$J$100,MATCH(B76,'Task Master'!$A$5:$A$100,0)),"")) | E76: =IF(B76="","",IFERROR(INDEX('Task Master'!$K$5:$K$100,MATCH(B76,'Task Master'!$A$5:$A$100,0)),"")) | O76: =IF(OR(A76="",B76=""),"",IF(OR(K76="Achieved",K76="Out-of-Scope Confirmed"),"Yes","No"))
C77: =IF(B77="","",IFERROR(INDEX('Task Master'!$C$5:$C$100,MATCH(B77,'Task Master'!$A$5:$A$100,0)),"")) | D77: =IF(B77="","",IFERROR(INDEX('Task Master'!$J$5:$J$100,MATCH(B77,'Task Master'!$A$5:$A$100,0)),"")) | E77: =IF(B77="","",IFERROR(INDEX('Task Master'!$K$5:$K$100,MATCH(B77,'Task Master'!$A$5:$A$100,0)),"")) | O77: =IF(OR(A77="",B77=""),"",IF(OR(K77="Achieved",K77="Out-of-Scope Confirmed"),"Yes","No"))
... C204: =IF(B204="","",IFERROR(INDEX('Task Master'!$C$5:$C$100,MATCH(B204,'Task Master'!$A$5:$A$100,0)),"")) | D204: =IF(B204="","",IFERROR(INDEX('Task Master'!$J$5:$J$100,MATCH(B204,'Task Master'!$A$5:$A$100,0)),"")) | E204: =IF(B204="","",IFERROR(INDEX('Task Master'!$K$5:$K$100,MATCH(B204,'Task Master'!$A$5:$A$100,0)),"")) | O204: =IF(OR(A204="",B204=""),"",IF(OR(K204="Achieved",K204="Out-of-Scope Confirmed"),"Yes","No"))

Sheet Engineer Updates
A1: Engineer Updates
A2: Engineers append a new row for every meaningful update. Blue cells are editable; gray cells are formula-driven.
A4: Update Timestamp | B4: Request Number | C4: Operational PIC | D4: Workflow Stage | E4: Engineer Update State | F4: Progress Update | G4: Next Action | H4: Blocker | I4: ETA | J4: Scope Assessment | K4: OOS Type | L4: Evidence / Link | M4: Updated By | N4: Is Latest
A5: 46251 | B5: CSSP10916071 | C5: =IF(B5="","",IFERROR(INDEX('Task Master'!$K$5:$K$100,MATCH(B5,'Task Master'!$A$5:$A$100,0)),"")) -> abdul.khoir@petronas.com | E5: Not Started | J5: Not Assessed | M5: System Initial Load | N5: =IF(OR(A5="",B5=""),"",A5=_xludf.MAXIFS($A$5:$A$304,$B$5:$B$304,B5)) -> #NAME?
A6: 46251 | B6: CSSP10372916 | C6: =IF(B6="","",IFERROR(INDEX('Task Master'!$K$5:$K$100,MATCH(B6,'Task Master'!$A$5:$A$100,0)),"")) -> abdul.khoir@petronas.com | E6: Not Started | J6: Not Assessed | M6: System Initial Load | N6: =IF(OR(A6="",B6=""),"",A6=_xludf.MAXIFS($A$5:$A$304,$B$5:$B$304,B6)) -> #NAME?
A7: 46251 | B7: CSSP10989463 | C7: =IF(B7="","",IFERROR(INDEX('Task Master'!$K$5:$K$100,MATCH(B7,'Task Master'!$A$5:$A$100,0)),"")) -> arun.karuppiah@petronas.com | E7: Not Started | J7: Not Assessed | M7: System Initial Load | N7: =IF(OR(A7="",B7=""),"",A7=_xludf.MAXIFS($A$5:$A$304,$B$5:$B$304,B7)) -> #NAME?
A8: 46251 | B8: CSSP10186192 | C8: =IF(B8="","",IFERROR(INDEX('Task Master'!$K$5:$K$100,MATCH(B8,'Task Master'!$A$5:$A$100,0)),"")) -> amarja.kawade@petronas.com | E8: Not Started | J8: Not Assessed | M8: System Initial Load | N8: =IF(OR(A8="",B8=""),"",A8=_xludf.MAXIFS($A$5:$A$304,$B$5:$B$304,B8)) -> #NAME?
A9: 46251 | B9: CSSP10187579 | C9: =IF(B9="","",IFERROR(INDEX('Task Master'!$K$5:$K$100,MATCH(B9,'Task Master'!$A$5:$A$100,0)),"")) -> amarja.kawade@petronas.com | E9: Not Started | J9: Not Assessed | M9: System Initial Load | N9: =IF(OR(A9="",B9=""),"",A9=_xludf.MAXIFS($A$5:$A$304,$B$5:$B$304,B9)) -> #NAME?
A10: 46251 | B10: CSSP10323752 | C10: =IF(B10="","",IFERROR(INDEX('Task Master'!$K$5:$K$100,MATCH(B10,'Task Master'!$A$5:$A$100,0)),"")) -> amarja.kawade@petronas.com | E10: Not Started | J10: Not Assessed | M10: System Initial Load | N10: =IF(OR(A10="",B10=""),"",A10=_xludf.MAXIFS($A$5:$A$304,$B$5:$B$304,B10)) -> #NAME?
A11: 46251 | B11: CSSP10327858 | C11: =IF(B11="","",IFERROR(INDEX('Task Master'!$K$5:$K$100,MATCH(B11,'Task Master'!$A$5:$A$100,0)),"")) -> amarja.kawade@petronas.com | E11: Not Started | J11: Not Assessed | M11: System Initial Load | N11: =IF(OR(A11="",B11=""),"",A11=_xludf.MAXIFS($A$5:$A$304,$B$5:$B$304,B11)) -> #NAME?
A12: 46251 | B12: CSSP10376841 | C12: =IF(B12="","",IFERROR(INDEX('Task Master'!$K$5:$K$100,MATCH(B12,'Task Master'!$A$5:$A$100,0)),"")) -> amarja.kawade@petronas.com | E12: Not Started | J12: Not Assessed | M12: System Initial Load | N12: =IF(OR(A12="",B12=""),"",A12=_xludf.MAXIFS($A$5:$A$304,$B$5:$B$304,B12)) -> #NAME?
A13: 46251 | B13: CSSP10413108 | C13: =IF(B13="","",IFERROR(INDEX('Task Master'!$K$5:$K$100,MATCH(B13,'Task Master'!$A$5:$A$100,0)),"")) -> amarja.kawade@petronas.com | E13: Not Started | J13: Not Assessed | M13: System Initial Load | N13: =IF(OR(A13="",B13=""),"",A13=_xludf.MAXIFS($A$5:$A$304,$B$5:$B$304,B13)) -> #NAME?
A14: 46251 | B14: CSSP10626318 | C14: =IF(B14="","",IFERROR(INDEX('Task Master'!$K$5:$K$100,MATCH(B14,'Task Master'!$A$5:$A$100,0)),"")) -> amarja.kawade@petronas.com | E14: Not Started | J14: Not Assessed | M14: System Initial Load | N14: =IF(OR(A14="",B14=""),"",A14=_xludf.MAXIFS($A$5:$A$304,$B$5:$B$304,B14)) -> #NAME?
A15: 46251 | B15: CSSP10689831 | C15: =IF(B15="","",IFERROR(INDEX('Task Master'!$K$5:$K$100,MATCH(B15,'Task Master'!$A$5:$A$100,0)),"")) -> amarja.kawade@petronas.com | E15: Not Started | J15: Not Assessed | M15: System Initial Load | N15: =IF(OR(A15="",B15=""),"",A15=_xludf.MAXIFS($A$5:$A$304,$B$5:$B$304,B15)) -> #NAME?
A16: 46251 | B16: CSSP10733928 | C16: =IF(B16="","",IFERROR(INDEX('Task Master'!$K$5:$K$100,MATCH(B16,'Task Master'!$A$5:$A$100,0)),"")) -> amarja.kawade@petronas.com | E16: Not Started | J16: Not Assessed | M16: System Initial Load | N16: =IF(OR(A16="",B16=""),"",A16=_xludf.MAXIFS($A$5:$A$304,$B$5:$B$304,B16)) -> #NAME?
... A85: 46251 | B85: CSSP10984683 | C85: =IF(B85="","",IFERROR(INDEX('Task Master'!$K$5:$K$100,MATCH(B85,'Task Master'!$A$5:$A$100,0)),"")) -> venkatesh.kalikivayi@petronas.com | E85: Not Started | J85: Not Assessed | M85: System Initial Load | N85: =IF(OR(A85="",B85=""),"",A85=_xludf.MAXIFS($A$5:$A$304,$B$5:$B$304,B85)) -> #NAME?
C86: =IF(B86="","",IFERROR(INDEX('Task Master'!$K$5:$K$100,MATCH(B86,'Task Master'!$A$5:$A$100,0)),"")) | N86: =IF(OR(A86="",B86=""),"",A86=_xludf.MAXIFS($A$5:$A$304,$B$5:$B$304,B86))
C87: =IF(B87="","",IFERROR(INDEX('Task Master'!$K$5:$K$100,MATCH(B87,'Task Master'!$A$5:$A$100,0)),"")) | N87: =IF(OR(A87="",B87=""),"",A87=_xludf.MAXIFS($A$5:$A$304,$B$5:$B$304,B87))
C88: =IF(B88="","",IFERROR(INDEX('Task Master'!$K$5:$K$100,MATCH(B88,'Task Master'!$A$5:$A$100,0)),"")) | N88: =IF(OR(A88="",B88=""),"",A88=_xludf.MAXIFS($A$5:$A$304,$B$5:$B$304,B88))
C89: =IF(B89="","",IFERROR(INDEX('Task Master'!$K$5:$K$100,MATCH(B89,'Task Master'!$A$5:$A$100,0)),"")) | N89: =IF(OR(A89="",B89=""),"",A89=_xludf.MAXIFS($A$5:$A$304,$B$5:$B$304,B89))
C90: =IF(B90="","",IFERROR(INDEX('Task Master'!$K$5:$K$100,MATCH(B90,'Task Master'!$A$5:$A$100,0)),"")) | N90: =IF(OR(A90="",B90=""),"",A90=_xludf.MAXIFS($A$5:$A$304,$B$5:$B$304,B90))
C91: =IF(B91="","",IFERROR(INDEX('Task Master'!$K$5:$K$100,MATCH(B91,'Task Master'!$A$5:$A$100,0)),"")) | N91: =IF(OR(A91="",B91=""),"",A91=_xludf.MAXIFS($A$5:$A$304,$B$5:$B$304,B91))
C92: =IF(B92="","",IFERROR(INDEX('Task Master'!$K$5:$K$100,MATCH(B92,'Task Master'!$A$5:$A$100,0)),"")) | N92: =IF(OR(A92="",B92=""),"",A92=_xludf.MAXIFS($A$5:$A$304,$B$5:$B$304,B92))
C93: =IF(B93="","",IFERROR(INDEX('Task Master'!$K$5:$K$100,MATCH(B93,'Task Master'!$A$5:$A$100,0)),"")) | N93: =IF(OR(A93="",B93=""),"",A93=_xludf.MAXIFS($A$5:$A$304,$B$5:$B$304,B93))
C94: =IF(B94="","",IFERROR(INDEX('Task Master'!$K$5:$K$100,MATCH(B94,'Task Master'!$A$5:$A$100,0)),"")) | N94: =IF(OR(A94="",B94=""),"",A94=_xludf.MAXIFS($A$5:$A$304,$B$5:$B$304,B94))
C95: =IF(B95="","",IFERROR(INDEX('Task Master'!$K$5:$K$100,MATCH(B95,'Task Master'!$A$5:$A$100,0)),"")) | N95: =IF(OR(A95="",B95=""),"",A95=_xludf.MAXIFS($A$5:$A$304,$B$5:$B$304,B95))
C96: =IF(B96="","",IFERROR(INDEX('Task Master'!$K$5:$K$100,MATCH(B96,'Task Master'!$A$5:$A$100,0)),"")) | N96: =IF(OR(A96="",B96=""),"",A96=_xludf.MAXIFS($A$5:$A$304,$B$5:$B$304,B96))
C97: =IF(B97="","",IFERROR(INDEX('Task Master'!$K$5:$K$100,MATCH(B97,'Task Master'!$A$5:$A$100,0)),"")) | N97: =IF(OR(A97="",B97=""),"",A97=_xludf.MAXIFS($A$5:$A$304,$B$5:$B$304,B97))
... C304: =IF(B304="","",IFERROR(INDEX('Task Master'!$K$5:$K$100,MATCH(B304,'Task Master'!$A$5:$A$100,0)),"")) | N304: =IF(OR(A304="",B304=""),"",A304=_xludf.MAXIFS($A$5:$A$304,$B$5:$B$304,B304))

Sheet Assignment History
A1: Assignment History
A2: Managers append one row for each disposition or PIC replacement. Do not overwrite prior rows.
A4: Effective Time | B4: Request Number | C4: From PIC | D4: To PIC | E4: Reason | F4: Assigned By | G4: Acknowledged By | H4: Acknowledged At | I4: Notes
A5: 46252 | B5: CSSP10231806 | C5: K.saktivelu@petronas.com | D5: raditya.nugraha@petronas.com | E5: Other | F5: Radit | G5: Radit | H5: 46252 | I5: Potential Private Cloud
A6: 46252 | B6: CSSP10271745 | C6: venkatesh.kalikivayi@petronas.com | D6: raditya.nugraha@petronas.com | E6: Other | F6: Radit | G6: Radit | H6: 46252 | I6: Potential Private Cloud
A7: 46252 | B7: CSSP10328360 | C7: K.saktivelu@petronas.com | D7: raditya.nugraha@petronas.com | E7: Other | F7: Radit | G7: Radit | H7: 46252 | I7: Potential Private Cloud
A8: 46252 | B8: CSSP10372916 | C8: abhishek.bhowate@petronas.com | D8: raditya.nugraha@petronas.com | E8: Other | F8: Radit | G8: Radit | H8: 46252 | I8: Potential Private Cloud
A9: 46252 | B9: CSSP10391895 | C9: nilesh.sankpal@petronas.com | D9: raditya.nugraha@petronas.com | E9: Other | F9: Radit | G9: Radit | H9: 46252 | I9: Potential Private Cloud
A10: 46252 | B10: CSSP10685915 | C10: IMS - CLOUD CSSP EXECUTOR | D10: raditya.nugraha@petronas.com | E10: Other | F10: Radit | G10: Radit | H10: 46252
A11: 46252 | B11: CSSP10353907 | C11: IMS - CLOUD CSSP EXECUTOR | D11: raditya.nugraha@petronas.com | E11: Other | F11: Radit | G11: Radit | H11: 46252
A12: 46252 | B12: CSSP10523448 | C12: venkatesh.kalikivayi@petronas.com | D12: raditya.nugraha@petronas.com | E12: Other | F12: Radit | G12: Radit | H12: 46252
A13: 46252 | B13: CSSP10969032 | C13: sairam.villa@petronas.com | D13: raditya.nugraha@petronas.com | E13: Other | F13: Radit | G13: Radit | H13: 46252
A14: 46252 | B14: CSSP10989463 | C14: abhishek.bhowate@petronas.com | D14: arun.karuppiah@petronas.com | E14: Other | F14: Radit | G14: Radit | H14: 46252
A15: 46252 | B15: CSSP10891746 | C15: venkatesh.kalikivayi@petronas.com | D15: arun.karuppiah@petronas.com | E15: Other | F15: Radit | G15: Radit | H15: 46252
A16: 46252 | B16: CSSP10546101 | C16: venkatesh.kalikivayi@petronas.com | D16: arun.karuppiah@petronas.com | E16: Other | F16: Radit | G16: Radit | H16: 46252
A17: 46252 | B17: CSSP10707894 | C17: venkatesh.kalikivayi@petronas.com | D17: arun.karuppiah@petronas.com | E17: Other | F17: Radit | G17: Radit | H17: 46252
A18: 46252 | B18: CSSP10478501 | C18: venkatesh.kalikivayi@petronas.com | D18: arun.karuppiah@petronas.com | E18: Other | F18: Radit | G18: Radit | H18: 46252
A19: 46252 | B19: CSSP10271745 | C19: venkatesh.kalikivayi@petronas.com | D19: abdul.khoir@petronas.com | E19: Other | F19: Radit | G19: Radit | H19: 46252
A20: 46252 | B20: CSSP10372916 | C20: abhishek.bhowate@petronas.com | D20: abdul.khoir@petronas.com | E20: Other | F20: Radit | G20: Radit | H20: 46252
A21: 46252 | B21: CSSP10391895 | C21: nilesh.sankpal@petronas.com | D21: abdul.khoir@petronas.com | E21: Other | F21: Radit | G21: Radit | H21: 46252
... A23: 46252 | B23: CSSP10328360 | C23: K.saktivelu@petronas.com | D23: mardiansyah.rayasa@petronas.com | E23: Other | F23: Radit | G23: Radit | H23: 46252

Sheet Scope Review
A1: Scope Review
A2: Manager approval log for suspected private-cloud/on-prem resources. Confirmed OOS is excluded from active workload.
A4: Submitted At | B4: Request Number | C4: Submitted By | D4: OOS Type | E4: Engineer Justification | F4: Evidence / Link | G4: Manager Decision | H4: Final Disposition | I4: Decision By | J4: Decision At | K4: CSSP Mismatch | L4: Notes
K5: =IF(OR(B5="",G5<>"Confirmed OOS"),"",IF(IFERROR(INDEX('Task Master'!$C$5:$C$100,MATCH(B5,'Task Master'!$A$5:$A$100,0)),"")="executing","Yes","No"))
K6: =IF(OR(B6="",G6<>"Confirmed OOS"),"",IF(IFERROR(INDEX('Task Master'!$C$5:$C$100,MATCH(B6,'Task Master'!$A$5:$A$100,0)),"")="executing","Yes","No"))
K7: =IF(OR(B7="",G7<>"Confirmed OOS"),"",IF(IFERROR(INDEX('Task Master'!$C$5:$C$100,MATCH(B7,'Task Master'!$A$5:$A$100,0)),"")="executing","Yes","No"))
K8: =IF(OR(B8="",G8<>"Confirmed OOS"),"",IF(IFERROR(INDEX('Task Master'!$C$5:$C$100,MATCH(B8,'Task Master'!$A$5:$A$100,0)),"")="executing","Yes","No"))
K9: =IF(OR(B9="",G9<>"Confirmed OOS"),"",IF(IFERROR(INDEX('Task Master'!$C$5:$C$100,MATCH(B9,'Task Master'!$A$5:$A$100,0)),"")="executing","Yes","No"))
K10: =IF(OR(B10="",G10<>"Confirmed OOS"),"",IF(IFERROR(INDEX('Task Master'!$C$5:$C$100,MATCH(B10,'Task Master'!$A$5:$A$100,0)),"")="executing","Yes","No"))
K11: =IF(OR(B11="",G11<>"Confirmed OOS"),"",IF(IFERROR(INDEX('Task Master'!$C$5:$C$100,MATCH(B11,'Task Master'!$A$5:$A$100,0)),"")="executing","Yes","No"))
K12: =IF(OR(B12="",G12<>"Confirmed OOS"),"",IF(IFERROR(INDEX('Task Master'!$C$5:$C$100,MATCH(B12,'Task Master'!$A$5:$A$100,0)),"")="executing","Yes","No"))
K13: =IF(OR(B13="",G13<>"Confirmed OOS"),"",IF(IFERROR(INDEX('Task Master'!$C$5:$C$100,MATCH(B13,'Task Master'!$A$5:$A$100,0)),"")="executing","Yes","No"))
K14: =IF(OR(B14="",G14<>"Confirmed OOS"),"",IF(IFERROR(INDEX('Task Master'!$C$5:$C$100,MATCH(B14,'Task Master'!$A$5:$A$100,0)),"")="executing","Yes","No"))
K15: =IF(OR(B15="",G15<>"Confirmed OOS"),"",IF(IFERROR(INDEX('Task Master'!$C$5:$C$100,MATCH(B15,'Task Master'!$A$5:$A$100,0)),"")="executing","Yes","No"))
K16: =IF(OR(B16="",G16<>"Confirmed OOS"),"",IF(IFERROR(INDEX('Task Master'!$C$5:$C$100,MATCH(B16,'Task Master'!$A$5:$A$100,0)),"")="executing","Yes","No"))
... K204: =IF(OR(B204="",G204<>"Confirmed OOS"),"",IF(IFERROR(INDEX('Task Master'!$C$5:$C$100,MATCH(B204,'Task Master'!$A$5:$A$100,0)),"")="executing","Yes","No"))

Sheet Engineer Capacity
A1: Engineer Capacity
A2: Current and projected workload before assigning processing tasks. Availability and skills are manager inputs.
A4: Engineer | B4: Display Name | C4: Skills | D4: Availability | E4: Base Capacity Points | F4: Effective Capacity | G4: Executing Tasks | H4: Current Workload Points | I4: Current Utilization | J4: Processing Points Assigned | K4: Projected Load | L4: Projected Utilization | M4: Today's Targets | N4: Targets Achieved | O4: Capacity Flag
A5: abdul.khoir@petronas.com | B5: Abdul Khoir | C5: Decommissioning; Provisioning | D5: 1 | E5: =Configuration!$S$5 -> 12 | F5: =D5*E5 -> 12 | G5: =COUNTIFS('Task Master'!$C$5:$C$100,"executing",'Task Master'!$K$5:$K$100,A5,'Task Master'!$N$5:$N$100,"<>Confirmed OOS") -> 11 | H5: =SUMIFS('Task Master'!$P$5:$P$100,'Task Master'!$K$5:$K$100,A5) -> 26 | I5: =IFERROR(H5/F5,0) -> 2.1666667 | J5: =SUMIFS('Task Master'!$M$5:$M$100,'Task Master'!$C$5:$C$100,"processing",'Task Master'!$K$5:$K$100,A5) -> 0 | K5: =H5+J5 -> 26 | L5: =IFERROR(K5/F5,0) -> 2.1666667 | M5: =COUNTIFS('Daily Targets'!$A$5:$A$204,Dashboard!$B$4,'Daily Targets'!$E$5:$E$204,A5) -> 4 | N5: =COUNTIFS('Daily Targets'!$A$5:$A$204,Dashboard!$B$4,'Daily Targets'!$E$5:$E$204,A5,'Daily Targets'!$O$5:$O$204,"Yes") -> 0 | O5: =IF(L5>1,"OVER CAPACITY",IF(L5>=0.8,"NEAR CAPACITY","AVAILABLE")) -> OVER CAPACITY
A6: abhishek.bhowate@petronas.com | B6: Abhishek Bhowate | C6: Decommissioning; Provisioning | D6: 1 | E6: =Configuration!$S$5 -> 12 | F6: =D6*E6 -> 12 | G6: =COUNTIFS('Task Master'!$C$5:$C$100,"executing",'Task Master'!$K$5:$K$100,A6,'Task Master'!$N$5:$N$100,"<>Confirmed OOS") -> 3 | H6: =SUMIFS('Task Master'!$P$5:$P$100,'Task Master'!$K$5:$K$100,A6) -> 8 | I6: =IFERROR(H6/F6,0) -> 0.66666667 | J6: =SUMIFS('Task Master'!$M$5:$M$100,'Task Master'!$C$5:$C$100,"processing",'Task Master'!$K$5:$K$100,A6) -> 0 | K6: =H6+J6 -> 8 | L6: =IFERROR(K6/F6,0) -> 0.66666667 | M6: =COUNTIFS('Daily Targets'!$A$5:$A$204,Dashboard!$B$4,'Daily Targets'!$E$5:$E$204,A6) -> 0 | N6: =COUNTIFS('Daily Targets'!$A$5:$A$204,Dashboard!$B$4,'Daily Targets'!$E$5:$E$204,A6,'Daily Targets'!$O$5:$O$204,"Yes") -> 0 | O6: =IF(L6>1,"OVER CAPACITY",IF(L6>=0.8,"NEAR CAPACITY","AVAILABLE")) -> AVAILABLE
A7: amarja.kawade@petronas.com | B7: Amarja Kawade | C7: Decommissioning; Provisioning | D7: 1 | E7: =Configuration!$S$5 -> 12 | F7: =D7*E7 -> 12 | G7: =COUNTIFS('Task Master'!$C$5:$C$100,"executing",'Task Master'!$K$5:$K$100,A7,'Task Master'!$N$5:$N$100,"<>Confirmed OOS") -> 23 | H7: =SUMIFS('Task Master'!$P$5:$P$100,'Task Master'!$K$5:$K$100,A7) -> 42 | I7: =IFERROR(H7/F7,0) -> 3.5 | J7: =SUMIFS('Task Master'!$M$5:$M$100,'Task Master'!$C$5:$C$100,"processing",'Task Master'!$K$5:$K$100,A7) -> 0 | K7: =H7+J7 -> 42 | L7: =IFERROR(K7/F7,0) -> 3.5 | M7: =COUNTIFS('Daily Targets'!$A$5:$A$204,Dashboard!$B$4,'Daily Targets'!$E$5:$E$204,A7) -> 0 | N7: =COUNTIFS('Daily Targets'!$A$5:$A$204,Dashboard!$B$4,'Daily Targets'!$E$5:$E$204,A7,'Daily Targets'!$O$5:$O$204,"Yes") -> 0 | O7: =IF(L7>1,"OVER CAPACITY",IF(L7>=0.8,"NEAR CAPACITY","AVAILABLE")) -> OVER CAPACITY
A8: arun.karuppiah@petronas.com | B8: Arun Karuppiah | C8: Provisioning | D8: 1 | E8: =Configuration!$S$5 -> 12 | F8: =D8*E8 -> 12 | G8: =COUNTIFS('Task Master'!$C$5:$C$100,"executing",'Task Master'!$K$5:$K$100,A8,'Task Master'!$N$5:$N$100,"<>Confirmed OOS") -> 7 | H8: =SUMIFS('Task Master'!$P$5:$P$100,'Task Master'!$K$5:$K$100,A8) -> 12 | I8: =IFERROR(H8/F8,0) -> 1 | J8: =SUMIFS('Task Master'!$M$5:$M$100,'Task Master'!$C$5:$C$100,"processing",'Task Master'!$K$5:$K$100,A8) -> 0 | K8: =H8+J8 -> 12 | L8: =IFERROR(K8/F8,0) -> 1 | M8: =COUNTIFS('Daily Targets'!$A$5:$A$204,Dashboard!$B$4,'Daily Targets'!$E$5:$E$204,A8) -> 0 | N8: =COUNTIFS('Daily Targets'!$A$5:$A$204,Dashboard!$B$4,'Daily Targets'!$E$5:$E$204,A8,'Daily Targets'!$O$5:$O$204,"Yes") -> 0 | O8: =IF(L8>1,"OVER CAPACITY",IF(L8>=0.8,"NEAR CAPACITY","AVAILABLE")) -> NEAR CAPACITY
A9: k.saktivelu@petronas.com | B9: K Saktivelu | C9: Decommissioning; Provisioning | D9: 1 | E9: =Configuration!$S$5 -> 12 | F9: =D9*E9 -> 12 | G9: =COUNTIFS('Task Master'!$C$5:$C$100,"executing",'Task Master'!$K$5:$K$100,A9,'Task Master'!$N$5:$N$100,"<>Confirmed OOS") -> 4 | H9: =SUMIFS('Task Master'!$P$5:$P$100,'Task Master'!$K$5:$K$100,A9) -> 6 | I9: =IFERROR(H9/F9,0) -> 0.5 | J9: =SUMIFS('Task Master'!$M$5:$M$100,'Task Master'!$C$5:$C$100,"processing",'Task Master'!$K$5:$K$100,A9) -> 0 | K9: =H9+J9 -> 6 | L9: =IFERROR(K9/F9,0) -> 0.5 | M9: =COUNTIFS('Daily Targets'!$A$5:$A$204,Dashboard!$B$4,'Daily Targets'!$E$5:$E$204,A9) -> 0 | N9: =COUNTIFS('Daily Targets'!$A$5:$A$204,Dashboard!$B$4,'Daily Targets'!$E$5:$E$204,A9,'Daily Targets'!$O$5:$O$204,"Yes") -> 0 | O9: =IF(L9>1,"OVER CAPACITY",IF(L9>=0.8,"NEAR CAPACITY","AVAILABLE")) -> AVAILABLE
A10: mardiansyah.rayasa@petronas.com | B10: Mardiansyah Rayasa | C10: Decommissioning; Provisioning | D10: 1 | E10: =Configuration!$S$5 -> 12 | F10: =D10*E10 -> 12 | G10: =COUNTIFS('Task Master'!$C$5:$C$100,"executing",'Task Master'!$K$5:$K$100,A10,'Task Master'!$N$5:$N$100,"<>Confirmed OOS") -> 8 | H10: =SUMIFS('Task Master'!$P$5:$P$100,'Task Master'!$K$5:$K$100,A10) -> 17 | I10: =IFERROR(H10/F10,0) -> 1.4166667 | J10: =SUMIFS('Task Master'!$M$5:$M$100,'Task Master'!$C$5:$C$100,"processing",'Task Master'!$K$5:$K$100,A10) -> 0 | K10: =H10+J10 -> 17 | L10: =IFERROR(K10/F10,0) -> 1.4166667 | M10: =COUNTIFS('Daily Targets'!$A$5:$A$204,Dashboard!$B$4,'Daily Targets'!$E$5:$E$204,A10) -> 1 | N10: =COUNTIFS('Daily Targets'!$A$5:$A$204,Dashboard!$B$4,'Daily Targets'!$E$5:$E$204,A10,'Daily Targets'!$O$5:$O$204,"Yes") -> 0 | O10: =IF(L10>1,"OVER CAPACITY",IF(L10>=0.8,"NEAR CAPACITY","AVAILABLE")) -> OVER CAPACITY
A11: nilesh.sankpal@petronas.com | B11: Nilesh Sankpal | C11: Decommissioning | D11: 1 | E11: =Configuration!$S$5 -> 12 | F11: =D11*E11 -> 12 | G11: =COUNTIFS('Task Master'!$C$5:$C$100,"executing",'Task Master'!$K$5:$K$100,A11,'Task Master'!$N$5:$N$100,"<>Confirmed OOS") -> 0 | H11: =SUMIFS('Task Master'!$P$5:$P$100,'Task Master'!$K$5:$K$100,A11) -> 0 | I11: =IFERROR(H11/F11,0) -> 0 | J11: =SUMIFS('Task Master'!$M$5:$M$100,'Task Master'!$C$5:$C$100,"processing",'Task Master'!$K$5:$K$100,A11) -> 0 | K11: =H11+J11 -> 0 | L11: =IFERROR(K11/F11,0) -> 0 | M11: =COUNTIFS('Daily Targets'!$A$5:$A$204,Dashboard!$B$4,'Daily Targets'!$E$5:$E$204,A11) -> 0 | N11: =COUNTIFS('Daily Targets'!$A$5:$A$204,Dashboard!$B$4,'Daily Targets'!$E$5:$E$204,A11,'Daily Targets'!$O$5:$O$204,"Yes") -> 0 | O11: =IF(L11>1,"OVER CAPACITY",IF(L11>=0.8,"NEAR CAPACITY","AVAILABLE")) -> AVAILABLE
A12: raditya.nugraha@petronas.com | B12: Raditya Nugraha | C12: Decommissioning; Provisioning | D12: 1 | E12: =Configuration!$S$5 -> 12 | F12: =D12*E12 -> 12 | G12: =COUNTIFS('Task Master'!$C$5:$C$100,"executing",'Task Master'!$K$5:$K$100,A12,'Task Master'!$N$5:$N$100,"<>Confirmed OOS") -> 6 | H12: =SUMIFS('Task Master'!$P$5:$P$100,'Task Master'!$K$5:$K$100,A12) -> 12 | I12: =IFERROR(H12/F12,0) -> 1 | J12: =SUMIFS('Task Master'!$M$5:$M$100,'Task Master'!$C$5:$C$100,"processing",'Task Master'!$K$5:$K$100,A12) -> 0 | K12: =H12+J12 -> 12 | L12: =IFERROR(K12/F12,0) -> 1 | M12: =COUNTIFS('Daily Targets'!$A$5:$A$204,Dashboard!$B$4,'Daily Targets'!$E$5:$E$204,A12) -> 0 | N12: =COUNTIFS('Daily Targets'!$A$5:$A$204,Dashboard!$B$4,'Daily Targets'!$E$5:$E$204,A12,'Daily Targets'!$O$5:$O$204,"Yes") -> 0 | O12: =IF(L12>1,"OVER CAPACITY",IF(L12>=0.8,"NEAR CAPACITY","AVAILABLE")) -> NEAR CAPACITY
A13: sairam.villa@petronas.com | B13: Sairam Villa | C13: Decommissioning | D13: 1 | E13: =Configuration!$S$5 -> 12 | F13: =D13*E13 -> 12 | G13: =COUNTIFS('Task Master'!$C$5:$C$100,"executing",'Task Master'!$K$5:$K$100,A13,'Task Master'!$N$5:$N$100,"<>Confirmed OOS") -> 0 | H13: =SUMIFS('Task Master'!$P$5:$P$100,'Task Master'!$K$5:$K$100,A13) -> 0 | I13: =IFERROR(H13/F13,0) -> 0 | J13: =SUMIFS('Task Master'!$M$5:$M$100,'Task Master'!$C$5:$C$100,"processing",'Task Master'!$K$5:$K$100,A13) -> 0 | K13: =H13+J13 -> 0 | L13: =IFERROR(K13/F13,0) -> 0 | M13: =COUNTIFS('Daily Targets'!$A$5:$A$204,Dashboard!$B$4,'Daily Targets'!$E$5:$E$204,A13) -> 0 | N13: =COUNTIFS('Daily Targets'!$A$5:$A$204,Dashboard!$B$4,'Daily Targets'!$E$5:$E$204,A13,'Daily Targets'!$O$5:$O$204,"Yes") -> 0 | O13: =IF(L13>1,"OVER CAPACITY",IF(L13>=0.8,"NEAR CAPACITY","AVAILABLE")) -> AVAILABLE
A14: swaminadh.chirakala@petronas.com | B14: Swaminadh Chirakala | C14: Decommissioning | D14: 1 | E14: =Configuration!$S$5 -> 12 | F14: =D14*E14 -> 12 | G14: =COUNTIFS('Task Master'!$C$5:$C$100,"executing",'Task Master'!$K$5:$K$100,A14,'Task Master'!$N$5:$N$100,"<>Confirmed OOS") -> 16 | H14: =SUMIFS('Task Master'!$P$5:$P$100,'Task Master'!$K$5:$K$100,A14) -> 37 | I14: =IFERROR(H14/F14,0) -> 3.0833333 | J14: =SUMIFS('Task Master'!$M$5:$M$100,'Task Master'!$C$5:$C$100,"processing",'Task Master'!$K$5:$K$100,A14) -> 0 | K14: =H14+J14 -> 37 | L14: =IFERROR(K14/F14,0) -> 3.0833333 | M14: =COUNTIFS('Daily Targets'!$A$5:$A$204,Dashboard!$B$4,'Daily Targets'!$E$5:$E$204,A14) -> 0 | N14: =COUNTIFS('Daily Targets'!$A$5:$A$204,Dashboard!$B$4,'Daily Targets'!$E$5:$E$204,A14,'Daily Targets'!$O$5:$O$204,"Yes") -> 0 | O14: =IF(L14>1,"OVER CAPACITY",IF(L14>=0.8,"NEAR CAPACITY","AVAILABLE")) -> OVER CAPACITY
A15: venkatesh.kalikivayi@petronas.com | B15: Venkatesh Kalikivayi | C15: Decommissioning; Provisioning | D15: 1 | E15: =Configuration!$S$5 -> 12 | F15: =D15*E15 -> 12 | G15: =COUNTIFS('Task Master'!$C$5:$C$100,"executing",'Task Master'!$K$5:$K$100,A15,'Task Master'!$N$5:$N$100,"<>Confirmed OOS") -> 3 | H15: =SUMIFS('Task Master'!$P$5:$P$100,'Task Master'!$K$5:$K$100,A15) -> 8 | I15: =IFERROR(H15/F15,0) -> 0.66666667 | J15: =SUMIFS('Task Master'!$M$5:$M$100,'Task Master'!$C$5:$C$100,"processing",'Task Master'!$K$5:$K$100,A15) -> 0 | K15: =H15+J15 -> 8 | L15: =IFERROR(K15/F15,0) -> 0.66666667 | M15: =COUNTIFS('Daily Targets'!$A$5:$A$204,Dashboard!$B$4,'Daily Targets'!$E$5:$E$204,A15) -> 0 | N15: =COUNTIFS('Daily Targets'!$A$5:$A$204,Dashboard!$B$4,'Daily Targets'!$E$5:$E$204,A15,'Daily Targets'!$O$5:$O$204,"Yes") -> 0 | O15: =IF(L15>1,"OVER CAPACITY",IF(L15>=0.8,"NEAR CAPACITY","AVAILABLE")) -> AVAILABLE

Sheet Configuration
A1: Configuration & Control Lists
A2: Yellow cells are manager-maintained assumptions; lists drive validation and formulas.
A4: Engineer Update States | B4: Provisioning Stages | C4: Decommissioning Stages | D4: Scope Assessments | E4: OOS Types | F4: Manager Decisions | G4: Final Dispositions | H4: Target Outcomes | I4: Target Results | J4: Assignment Reasons | L4: Raw PIC | M4: Canonical PIC | O4: Request Size | P4: Workload Points | R4: Assumption | S4: Value | U4: All Workflow Stages
A5: Not Started | B5: Information & Access Validation | C5: Requestor Green-Light | D5: Not Assessed | E5: Private Cloud | F5: Not Reviewed | G5: Return to Requestor | H5: Complete Task | I5: Not Started | J5: Workload Rebalance | L5: CCoE Operations | M5: CCoE Operations | O5: S | P5: 1 | R5: Default Capacity Points | S5: 12 | U5: Information & Access Validation
A6: In Progress | B6: Create Vending | C6: Resource Validation | D6: In Scope | E6: On-Premises | F6: Pending Review | G6: Route to Private Cloud Team | H6: Confirm Out-of-Scope | I6: In Progress | J6: Skill Match | L6: IMS - CLOUD CSSP EXECUTOR | M6: IMS - CLOUD CSSP EXECUTOR | O6: Small | P6: 1 | R6: Missing Size Points | S6: 2 | U6: Create Vending
A7: Waiting/Blocked | B7: Scripting | C7: Terraform Plan / Drift Check | D7: Suspected Out-of-Scope | E7: Other | F7: Confirmed OOS | G7: Route to On-Prem Team | I7: Achieved | J7: Leave / Availability | L7: K.saktivelu@petronas.com | M7: k.saktivelu@petronas.com | O7: M | P7: 2 | R7: Stale Update Days | S7: 2 | U7: Scripting
A8: Out-of-Scope Suspected | B8: Awaiting Approval | C8: SME Confirmation | F8: Rejected OOS | G8: Continue In Scope | I8: Blocked | J8: Handover | L8: abdul.khoir@petronas.com | M8: abdul.khoir@petronas.com | O8: L | P8: 3 | U8: Awaiting Approval
A9: Completed by Engineer | B9: Done | C9: Remediate Drift / Delete | I9: Missed | J9: Correction | L9: abhishek.bhowate@petronas.com | M9: abhishek.bhowate@petronas.com | U9: Done
A10: Returned for Clarification | C10: RFC Document | I10: Out-of-Scope Submitted | J10: Other | L10: amarja.kawade@petronas.com | M10: amarja.kawade@petronas.com | U10: Requestor Green-Light
C11: ITSM Change Request | I11: Out-of-Scope Confirmed | L11: amarja.kawde@petronas.com | M11: amarja.kawade@petronas.com | U11: Resource Validation
C12: Awaiting Approval | L12: arun.karuppiah@petronas.com | M12: arun.karuppiah@petronas.com | U12: Terraform Plan / Drift Check
C13: Done | L13: mardiansyah.rayasa@petronas.com | M13: mardiansyah.rayasa@petronas.com | U13: SME Confirmation
L14: nilesh.sankpal@petronas.com | M14: nilesh.sankpal@petronas.com | U14: Remediate Drift / Delete
L15: raditya.nugraha@petronas.com | M15: raditya.nugraha@petronas.com | U15: RFC Document
L16: sairam.villa@petronas.com | M16: sairam.villa@petronas.com | U16: ITSM Change Request
L17: swaminadh.chirakala@petronas.com | M17: swaminadh.chirakala@petronas.com
L18: venkatesh.kalikivayi@petronas.com | M18: venkatesh.kalikivayi@petronas.com

Sheet Raw Decommissioning
A1: id | B1: request_number | C1: requestor_id | D1: request_type | E1: request_status | F1: date_created | G1: date_updated | H1: date_submitted | I1: application_name | J1: project_name | K1: decommission_type | L1: powerapps_id | M1: manager_email | N1: dns_records | O1: app_centre_ref | P1: justification | Q1: backup | R1: reason | S1: origin | T1: gate_1_status | U1: gate_1_id | V1: gate_1_date | W1: gate_1_comments | X1: gate_2_status | Y1: gate_2_id | Z1: gate_2_date | AA1: gate_2_comments | AB1: gate_3_status | AC1: gate_3_id | AD1: gate_3_date | AE1: gate_3_comments | AF1: gate_4_status | AG1: gate_4_id | AH1: gate_4_date | AI1: gate_4_comments | AJ1: application_id | AK1: project_code | AL1: request_size | AM1: sr_number | AN1: data_retention | AO1: data_retention_duration
A2: 6ef3ecb9-948b-4541-9e2a-8170c8b4d27d | B2: CSSP10149822 | C2: maffendy.bobmazmi@petronas.com | D2: decommission-cloud | E2: rejected | F2: 2025-04-09T03:59:01.573 | G2: 46121.167 | H2: 2025-04-09T03:59:01.573 | I2: Asset Integrity Database Axis | J2: NA | M2: CCoE Core Services (Private) | N2: https://aida.petronas.com | O2: 2637 | P2: Application no longer in use. | Q2: 2W | R2: Obsolete | S2: cssp-v1 | T2: approved | U2: maffendy.bobmazmi@petronas.com | V2: 2025-04-09T03:59:01.573 | X2: rejected | Y2: huajin.tan@petronas.com | Z2: 46121.167 | AC2: CCoE Core Services (Private) | AG2: CCoE Core Services (Private)
A3: 8bc99c2f-ccb7-4219-b8be-9e0c4b545b00 | B3: CSSP10864680 | C3: zahar.ismail@petronas.com | D3: decommission-cloud | E3: rejected | F3: 45827.261 | G3: 46050.086 | H3: 45827.261 | I3: Integrated Project Monitoring & Performance Tracking (i-PROMPT) | J3: Enhancement of Integrated Project Monitoring & Performance Tracking (i-PROMPT), Phase 2 for Malaysia Petroleum Management (MPM) | K3: partial | M3: karlai.foong@petronas.com.my | P3: Service Retirement : TLS 1.0 and 1.1 To decomm Resource Group iPrompt D365 ptazsg-dev-ipms-rg ptazsg-prod-ipms-rg | Q3: 12M | R3: Obsolete | T3: approved | U3: zahar.ismail@petronas.com | V3: 45827.265 | W3: iPrompt D365 is no longer in used. In the process of decommission. | X3: rejected | Y3: azwan.badari@petronas.com | Z3: 46050.086 | AA3: Please cancel if this request is no longer required. | AC3: CCoE Business | AG3: CCoE Operations | AJ3: A-000399 | AK3: 2894
A4: ec7f5c14-eb0e-42b7-b177-cff3ae2fea77 | B4: CSSP10929930 | C4: marcus.leongkahsung@petronas.com | D4: decommission-cloud | E4: cancelled | F4: 45876.222 | G4: 46050.088 | H4: 45876.222 | I4: MyMinutes | J4: Project Implementation of myMinutes in Azure under myFinder OPSR | K4: partial | M4: mfaizal.sidek@petronas.com.my | P4: no longer required | Q4: 2W | R4: Not in Used | T4: rejected | U4: azwan.badari@petronas.com | V4: 46050.088 | Y4: mfaizal.sidek@petronas.com | AC4: CCoE Business | AG4: CCoE Operations | AJ4: A-000487 | AK4: PSR05071_1
A5: cf939f0d-e824-462f-ba3a-778ac45e27f7 | B5: CSSP10288728 | C5: engken.choo@petronas.com | D5: decommission-cloud | E5: rejected | F5: 45881.273 | G5: 46050.087 | H5: 45881.285 | I5: Integrated Process Safety System (IPSS) | J5: Enhancement of Integrated Process Safety Solution (IPSS) | K5: partial | M5: bryan.dewitt@petronas.com.my | N5: hsseipssqa.petronas.com, apihsseipssqa.petronas.com | P5: the website is no longer required hsseipssqa.petronas.com apihsseipssqa.petronas.com | Q5: 2W | R5: Not in Used | T5: approved | U5: engken.choo@petronas.com | V5: 45881.286 | W5: The following websites are no longer required: hsseipssqa.petronas.com and apihsseipssqa.petronas.com. Therefore, there is no need to renew their SSL certificates | X5: rejected | Y5: azwan.badari@petronas.com | Z5: 46050.087 | AA5: Please cancel if this request is no longer required. | AC5: CCoE Business | AG5: CCoE Business | AJ5: A-000401 | AK5: 3020
A6: 112a04b8-d292-413d-b6f2-5f78833e3d93 | B6: CSSP10737090 | C6: vu.bui@petronas.com | D6: decommission-cloud | E6: rejected | F6: 45918.153 | G6: 46050.083 | H6: 45918.153 | I6: PETRONAS HSSE Incident Management System | J6: HSSE Incident Management System (HSSE IM) 6.0 Enhancement | K6: partial | M6: mfadhlulwafi.mahadi@petronas.com | P6: This is resource need decommissioning https://portal.azure.com/#@PETRONAS.onmicrosoft.com/resource/subscriptions/2be5068f-e0ac-4d57-aedc-96bc9798a265/resourceGroups/PTAZSG-IAC-DEV-MYHSSE-RG/providers/Microsoft.Web/sites/ptazsg-5myhsseimwb01/appServices | Q6: 2W | R6: Not in Used | T6: approved | U6: vu.bui@petronas.com | V6: 45918.156 | W6: This is resource need decommissioning https://portal.azure.com/#@PETRONAS.onmicrosoft.com/resource/subscriptions/2be5068f-e0ac-4d57-aedc-96bc9798a265/resourceGroups/PTAZSG-IAC-DEV-MYHSSE-RG/providers/Microsoft.Web/sites/ptazsg-5myhsseimwb01/appServices | X6: rejected | Y6: azwan.badari@petronas.com | Z6: 46050.083 | AA6: Please cancel and resubmit if still require to decommission the resources. Please select the correct project code related to the resources. | AC6: CCoE Business | AG6: CCoE Operations | AJ6: A-000388 | AK6: 4129
A7: 81f1d54a-21c5-4b45-b1b2-33b4f09c674d | B7: CSSP10998132 | C7: ismail.azman@petronas.com | D7: decommission-cloud | E7: cancelled | F7: 45933.333 | G7: 46050.079 | H7: 45933.333 | I7: Sitecom / Real time Operation - RTO | J7: SecOps of Development (Dev.) Chapter for Upstream Technology, Digital & Innovation | K7: partial | M7: ismail.azman@petronas.com | N7: Na | O7: NA | P7: Test requests CSSP | Q7: 2W | R7: Not in Used | T7: rejected | U7: azwan.badari@petronas.com | V7: 46050.079 | W7: Not required | Y7: ismail.azman@petronas.com | AC7: CCoE Business | AG7: CCoE Operations | AJ7: A-000766 | AK7: 4064
A8: a8a5792f-a50e-47df-8ad4-b7b033a505c7 | B8: CSSP10613042 | C8: syafiqfathyamer.moh@petronas.com | D8: decommission-cloud | E8: rejected | F8: 45945.384 | G8: 46139.102 | H8: 45945.384 | I8: PIVOT AA FeedProp | J8: Implementation of PIVOT AA FeedProp Phase 2 | K8: partial | M8: sunny.khiani@petronas.com.my | P8: Decommission leftover infrastructure. | Q8: 1M | R8: Not in Used | T8: approved | U8: sunny.khiani@petronas.com | V8: 46136.179 | W8: approved | X8: approved | Y8: sunny.khiani@petronas.com | Z8: 46136.179 | AA8: approved | AB8: rejected | AC8: azwan.badari@petronas.com | AD8: 46139.102 | AE8: Rejected because no resources to be decommissioned has been selected and no approval been attached. | AG8: CCoE Operations | AJ8: A-000607 | AK8: 1221
A9: 0daf85c0-fa94-4cfa-83fb-50b5382fa146 | B9: CSSP10685915 | C9: syafiqfathyamer.moh@petronas.com | D9: decommission-cloud | E9: executing | F9: 45945.389 | G9: 46229.695 | H9: 46217.116 | I9: PIVOT CGC Fouling | J9: OSR00154: Support and Maintenance for PIVOT Program for Group Digital – CAPEX – PIVOT CGC Fouling | K9: partial | M9: sunny.khiani@petronas.com.my | P9: Business agreed to decommission this application | Q9: 1M | R9: Not in Used | T9: approved | U9: syafiqfathyamer.moh@petronas.com | V9: 46217.259 | W9: Requesting approval for decommission CGC Fouling | X9: approved | Y9: sunny.khiani@petronas.com | Z9: 46220.102 | AA9: please do a scream test and make necessary data backups | AB9: approved | AC9: abhishek.bhowate@petronas.com | AD9: 46229.695 | AE9: approve | AG9: IMS - CLOUD CSSP EXECUTOR | AJ9: A-000610 | AK9: OSR00154_1 | AL9: M | AM9: REQ000008194179
A10: b8d9c41d-6ef1-4a89-ae40-a399e55eb53b | B10: CSSP10541419 | C10: mizznajwan.mzaki@petronas.com | D10: decommission-cloud | E10: completed | F10: 45947.114 | G10: 46069.334 | H10: 46059.378 | I10: Regasification Terminal Sungai Udang Digital Transformation - RGTSU-DX | J10: Digital Transformation at RGTSU (RGTSU-DX Phase 2) | K10: partial | M10: masmaliza.zolkefli@petronas.com.my | P10: Application interface moved from FUSE to Graffiquo VIP | Q10: 3M | R10: Consolidation | T10: approved | U10: mizznajwan.mzaki@petronas.com | V10: 46059.379 | W10: Decomm request as Application interface moved from FUSE to Graffiquo VIP | X10: approved | Y10: masmaliza.zolkefli@petronas.com | Z10: 46059.551 | AA10: To ensure no interruption to current system. | AB10: approved | AC10: azwan.badari@petronas.com | AD10: 46064.081 | AE10: Decommissioned under CSSP10136862 / REQ000007261851 | AF10: approved | AG10: azwan.badari@petronas.com | AH10: 46069.334 | AI10: Completed | AJ10: A-000689 | AK10: 1938 | AL10: S | AM10: REQ000007870526
A11: 6056a465-c1d3-4d7e-bce5-d60e154e7c1e | B11: CSSP10512939 | C11: mfaizal.suriyat@petronas.com | D11: decommission-cloud | E11: rejected | F11: 45958.016 | G11: 46050.378 | H11: 45958.016 | I11: Predictive Analytics for Pipeline Freespan - PrAnSpan | J11: Support and Maintenance of Predictive Analytic Freespan (PrAnSpan) for GTS | K11: partial | M11: shekha.mahdhar@petronas.com.my | O11: 2090 | P11: Cloud Migration - modernization | Q11: 1M | R11: Cloud Migration | T11: approved | U11: mfaizal.suriyat@petronas.com | V11: 45958.018 | W11: Remove All Component and RG in this RG - PTAZSG-PROD-PRANSPAN-ANALYTICS-GTS-RG | X11: approved | Y11: shekha.mahdhar@petronas.com | Z11: 46050.342 | AA11: Ok | AB11: rejected | AC11: azwan.badari@petronas.com | AD11: 46050.378 | AE11: Duplicate. RG PTAZSG-PROD-PRANSPAN-ANALYTICS-GTS-RG has been deleted under CSSP10803658. Please cancel this request. | AG11: CCoE Operations | AJ11: A-000644 | AK11: 2090 | AN11: noretention | AO11: 0
A12: b5a262c2-6796-42be-83da-2a301b1d6e76 | B12: CSSP10596587 | C12: mfaizal.suriyat@petronas.com | D12: decommission-cloud | E12: pending | F12: 45958.019 | G12: 46050.342 | H12: 45958.019 | I12: Predictive Analytics for Pipeline Freespan - PrAnSpan | J12: Support and Maintenance of Predictive Analytic Freespan (PrAnSpan) for GTS | K12: partial | M12: shekha.mahdhar@petronas.com.my | O12: 2090 | P12: Cloud Migration - Modernization | Q12: 1M | R12: Cloud Migration | T12: approved | U12: shekha.mahdhar@petronas.com | V12: 46050.342 | W12: As requested | Y12: shekha.mahdhar@petronas.com | AC12: CCoE Business | AG12: CCoE Operations | AJ12: A-000644 | AK12: 2090 | AN12: noretention | AO12: 0
A13: 6107ea3c-5eec-487f-985c-73ea8f886762 | B13: CSSP10170875 | C13: waffiudin.aziz@petronas.com | D13: decommission-cloud | E13: completed | F13: 45981.192 | G13: 46048.295 | H13: 45981.192 | I13: Mobile View for Aeroscout Location Engine - ALE | J13: Mobile View for Aeroscout Location Engine - ALE created for PRIVATECLOUD project record | K13: full | L13: NA | M13: rohaizad_rozali@petronas.com.my | P13: Apps no longer in used by asset | Q13: 2W | R13: Not in Used | T13: approved | U13: waffiudin.aziz@petronas.com | V13: 45981.193 | W13: Reviewed with Abd Latif M Tobi (Gas Business Product Management) | X13: approved | Y13: rohaizad_rozali@petronas.com | Z13: 45995.215 | AA13: Approved | AB13: approved | AC13: azwan.badari@petronas.com | AD13: 46042.308 | AE13: Shutdown for more than 1 month but no reports or complain. vCENPPGBMVAP02.PETRONAS.PETRONET.DIR 10.14.65.131 TM KVDC vCENPPGBMVDB01.PETRONAS.PETRONET.DIR 10.14.65.132 TM KVDC | AF13: approved | AG13: azlisham.md@petronas.com | AH13: 46048.295 | AI13: The decommission request has been completed, and the status is now updated accordingly. Kindly verify from your end and confirm once reviewed. | AJ13: A-000040 | AK13: 10017 | AL13: M | AM13: REQ000007829202 | AN13: disposal | AO13: 0
A14: bdb2e056-1eb1-4173-90d0-d6d1435b1b61 | B14: CSSP10703990 | C14: essam.arab@petronas.com | D14: decommission-cloud | E14: completed | F14: 45986.377 | G14: 46136.178 | H14: 45986.377 | I14: Alpha LNG | J14: Alpha LNG Phase 4 (PDSB) | K14: partial | M14: sunny.khiani@petronas.com | P14: Resources to be deleted are in DEV ENVIRONMENT ONLY Azure App Service: ptazsg-5alphalngap01 Azure App Service Plan: ptazsg-5alphalngasp01 | Q14: 1M | R14: Not in Used | T14: approved | U14: essam.arab@petronas.com | V14: 45986.377 | W14: Resources to be deleted are in DEV ENVIRONMENT ONLY Azure App Service: ptazsg-5alphalngap01 Azure App Service Plan: ptazsg-5alphalngasp01 | X14: approved | Y14: sunny.khiani@petronas.com | Z14: 46136.176 | AA14: approved | AB14: approved | AC14: sunny.khiani@petronas.com | AD14: 46136.177 | AE14: approved | AF14: approved | AG14: sunny.khiani@petronas.com | AH14: 46136.178 | AI14: approved | AJ14: A-000043 | AK14: 1266 | AL14: M | AM14: REQ000008009892 | AN14: noretention | AO14: 0
A15: 6d98f3d9-2a38-460b-8c86-8d8820e4820f | B15: CSSP10528936 | C15: nursyazana.z@petronas.com | D15: decommission-cloud | E15: rejected | F15: 45988.319 | G15: 46047.724 | H15: 45991.895 | I15: Upstream Technical Applications SCUS | J15: Provision of Additional Capacity SCUS for Mexico Operation | K15: full | L15: DCOM202512011a6 | M15: mhafiz.samsudin@petronas.com | N15: Not Applicable | P15: Mexico office already close. Resources under Project_Code : 00592 has been shutdown and there is no issue as Ahmad Syazali has done the screaming test. You may refer to attached email | Q15: 2W | R15: Not in Used | T15: approved | U15: nursyazana.z@petronas.com | V15: 45991.903 | W15: To Azwan and Ahmad Syazali, there are few resources is not being listed as per list above. I believe this is due to we already shutdown during screaming test e.g. VM. Thus, please proceed with the decommissioning of the resources also. Fyi, for financial discovery, I have attached the no in CSSP request and in progress to complete 7 chapters of financial discovery list. | X15: approved | Y15: mhafiz.samsudin@petronas.com | Z15: 46000.287 | AA15: Reviewed and Aproved | AB15: rejected | AC15: azwan.badari@petronas.com | AD15: 46047.724 | AE15: Please resubmit as there is no confirmation. | AG15: CCoE Business | AJ15: A-000803 | AK15: 592 | AN15: retention | AO15: 30
A16: c0a60393-9927-4fc3-80fc-1e06da243f5f | B16: CSSP10984549 | C16: azrel.nasaruddin@petronas.com | D16: decommission-cloud | E16: cancelled | F16: 45989.449 | G16: 46050.078 | H16: 45989.449 | I16: Enterprise Software Defined Wide Area Network - SDWAN | J16: Implementation of Enterprise Software Defined Wide Area Network (SDWAN) for PETRONAS | K16: partial | M16: mhaslan.abuhassan@petronas.com | O16: 704D905153 | P16: To Decommission Resource under RG - PTAZSG-PROD-WAF-RG, CPU Utilization for PTAZSG-PROD-OnPrem-WAFv1-01 PTAZSG-PROD-OnPrem-WAFv1-01 PTAZSG-PROD-Onprem-WAFv1-01-PIP | Q16: 2W | R16: Not in Used | T16: rejected | U16: azwan.badari@petronas.com | V16: 46050.078 | W16: Not required | Y16: mhaslan.abuhassan@petronas.com | AC16: CCoE Business | AG16: CCoE Operations | AJ16: A-000754 | AK16: 00480_1 | AN16: noretention | AO16: 0
A17: c256d4f6-56d9-4654-aae2-e852fc1db966 | B17: CSSP10767995 | C17: nursyazana.z@petronas.com | D17: decommission-cloud | E17: rejected | F17: 45991.907 | G17: 46047.724 | H17: 45991.907 | I17: Upstream Technology and Digital Innovation (UTDI) Data Operations | J17: 2023 - DSG repurpose for UTDI Data Ops as instruction from upstream tribe Provision of Azure Cloud Services for Halliburton Decision Space Geoscience (DSG) Application for Group Technical Data | K17: partial | M17: mhafiz.samsudin@petronas.com | N17: Not Applicable | O17: PSR04669 | P17: Resources under Project_Code : PSR04469 has been shutdown except ptazscusprodgtdstor and ptscustdmexicostorage01 as per agreed. There is no issue as Ahmad Syazali has done the screaming test. You may refer to attached email | Q17: 1M | R17: Not in Used | T17: approved | U17: nursyazana.z@petronas.com | V17: 45991.911 | W17: I have reviewed the list. All can be decommissioned except for ptazscusprodgtdstor and ptscustdmexicostorage01 and also resources related to them such as queue and table | X17: approved | Y17: mhafiz.samsudin@petronas.com | Z17: 46000.287 | AA17: Align with Cloud Cost Optimization initiative. Approved. | AB17: rejected | AC17: azwan.badari@petronas.com | AD17: 46047.724 | AE17: Please resubmit as there is no confirmation. | AG17: CCoE Operations | AJ17: A-000241 | AK17: PSR04669 | AN17: retention | AO17: 30
A18: 42303bf0-4804-4229-9b4d-601b156d79bc | B18: CSSP10547052 | C18: azrel.nasaruddin@petronas.com | D18: decommission-cloud | E18: cancelled | F18: 45993.124 | G18: 46050.078 | H18: 45993.124 | I18: Common Security | J18: Common infrastructure related to security such as DDOS protection, WAF and others | K18: partial | M18: mhaslan.abuhassan@petronas.com | P18: to be decomm resources for : CPU Utilization for PTAZSG-PROD-OnPrem-WAFv1-01 PTAZSG-PROD-OnPrem-WAFv1-01 PTAZSG-PROD-Onprem-WAFv1-01-PIP | Q18: 2W | R18: Not in Used | T18: rejected | U18: azwan.badari@petronas.com | V18: 46050.078 | W18: Not required | Y18: mhaslan.abuhassan@petronas.com | AC18: CCoE Business | AG18: CCoE Operations | AJ18: C-000017 | AK18: Common-Security | AN18: noretention | AO18: 0
A19: 9dba099f-8a6d-42f2-ac79-698ccc7fa5fb | B19: CSSP10619105 | C19: nursyazana.z@petronas.com | D19: decommission-cloud | E19: rejected | F19: 45995.349 | G19: 46047.724 | H19: 45995.349 | I19: Upstream Technical Applications GOMSCUS | J19: AZURE Resource Provisioning for EIV US Gulf of Mexico (GOM) In PETRONAS AZURE South Central U.S. (SCUS) | K19: full | L19: DCOM20251204726 | M19: mhafiz.samsudin@petronas.com | N19: Not Applicable | O19: PSR05689_3 | P19: As discussed with Syazali, all resources has been shutdown and can be decommissioned | Q19: 2W | R19: Not in Used | T19: approved | U19: nursyazana.z@petronas.com | V19: 45995.349 | W19: This will be done by Ahmad Syazali and Khairul Azwan | X19: approved | Y19: mhafiz.samsudin@petronas.com | Z19: 46000.288 | AA19: Crucial as part of Cloud Cost Optimization exercise. Approved. | AB19: rejected | AC19: azwan.badari@petronas.com | AD19: 46047.724 | AE19: Please resubmit as there is no confirmation. | AG19: CCoE Operations | AJ19: A-000798 | AK19: PSR05689_3 | AN19: retention | AO19: 30
A20: 67b0ede6-e19a-4ac3-9b27-563c45721825 | B20: CSSP10851603 | C20: mohamadfaisal.maasah@petronas.com | D20: decommission-cloud | E20: completed | F20: 46002.121 | G20: 46037.247 | H20: 46029.094 | I20: Daily Operations Tracking System - DOTS | J20: Cloud Migration Program - Daily Operations Tracking System (DOTS) | K20: full | L20: DCOM20260107c0d | M20: halim.matnoh@petronas.com | N20: https://dots.digitalfields.petronas.com/ | P20: Application not in used. To include shared managed databased for DOTS. | Q20: 2W | R20: Not in Used | T20: approved | U20: mohamadfaisal.maasah@petronas.com | V20: 46029.094 | W20: To decomm the application (full decommission) | X20: approved | Y20: halim.matnoh@petronas.com | Z20: 46030.139 | AA20: approved | AB20: approved | AC20: azwan.badari@petronas.com | AD20: 46031.305 | AE20: Full Decommission DOTS (00915_4) including DB in shared managed instance in, ptazsg-1udsqlmi01 ptazsg-4udsqlmi01 ptazsg-5udsqlmi01) | AF20: approved | AG20: azwan.badari@petronas.com | AH20: 46037.247 | AI20: Completed | AJ20: A-000221 | AK20: 00915_4 | AL20: M | AM20: REQ000007803645 | AN20: retention | AO20: 14
A21: c6a129dd-daca-4be4-aad4-3f4bb646fe74 | B21: CSSP10204527 | C21: sitisoleha.mnizam@petronas.com | D21: decommission-cloud | E21: completed | F21: 46010.099 | G21: 46027.371 | H21: 46010.099 | I21: Project Management Solution | J21: Implementation of Interim Project Management Solution for Malaysia Petroleum Management (MPM) | K21: partial | M21: sharulazlan.ahmad@petronas.com.my | N21: https://ipromptpac.petronas.com/iPROMPT/ | O21: 4594 | P21: COC team has confirmed that the both dev and prod i-PROMPT resource groups can be decom because most of the services are stopped and the storage account last activity was in 2022. Hence, before we decom the whole RG, below are the estimated costs for both dev and prod RG. The slight differences between the costs is due to the higher number of storage account found in prod RG. Production RG: PTAZSG-PROD-IPMS-RG Development RG: PTAZSG-DEV-IPMS-RG | Q21: 1M | R21: Consolidation | T21: approved | U21: sitisoleha.mnizam@petronas.com | V21: 46010.131 | W21: COC team has confirmed that the both dev and prod i-PROMPT resource groups can be decom because most of the services are stopped and the storage account last activity was in 2022. Hence, before we decom the whole RG, below are the estimated costs for both dev and prod RG. The slight differences between the costs is due to the higher number of storage account found in prod RG. Production RG: PTAZSG-PROD-IPMS-RG Development RG: PTAZSG-DEV-IPMS-RG | X21: approved | Y21: sharulazlan.ahmad@petronas.com | Z21: 46013.416 | AA21: Approved | AB21: approved | AC21: azwan.badari@petronas.com | AD21: 46015.125 | AE21: Decommission 2 RG only. Production RG: PTAZSG-PROD-IPMS-RG Development RG: PTAZSG-DEV-IPMS-RG DNS provided in the form is still in use (Outsystem). | AF21: approved | AG21: azlisham.md@petronas.com | AH21: 46027.371 | AI21: The decommission request has been completed, and the status is now updated accordingly. Kindly verify from your end and confirm once reviewed. | AJ21: A-000662 | AK21: 584 | AL21: M | AM21: REQ000007761967 | AN21: noretention | AO21: 0
A22: 75e71d16-4e6b-4a65-9d08-118dd73320c6 | B22: CSSP10745533 | C22: norhamizah.hasni@petronas.com | D22: decommission-cloud | E22: completed | F22: 46013.305 | G22: 46031.087 | H22: 46013.305 | I22: CI Academy Portal | J22: Cloud Transformation Programme - CI Academy Portal | K22: partial | M22: sazali.mokhtar@petronas.com | P22: To decommission old resources in Singapore region due to completed migration in MY region | Q22: 2W | R22: Cloud Migration | T22: approved | U22: norhamizah.hasni@petronas.com | V22: 46013.306 | W22: To decommission resources in SG region | X22: approved | Y22: sazali.mokhtar@petronas.com | Z22: 46027.139 | AA22: To decommission old resources in Singapore region due to completed migration in MY region - ( Hamizah ) | AB22: approved | AC22: azwan.badari@petronas.com | AD22: 46028.101 | AE22: Repatriation | AF22: approved | AG22: azwan.badari@petronas.com | AH22: 46031.087 | AI22: Completed | AJ22: A-000111 | AK22: 02421_89 | AL22: S | AM22: REQ000007790054 | AN22: noretention | AO22: 0
A23: 19a4096f-0ee7-4553-b3bf-ebf4344efc24 | B23: CSSP10759471 | C23: fahmi.badurisam@petronas.com | D23: decommission-cloud | E23: completed | F23: 46014.152 | G23: 46048.323 | H23: 46014.152 | I23: UPS Monitoring | J23: UPS Monitoring | K23: full | L23: DCOM20251223e29 | M23: hafiz.awahab@petronas.com | P23: INDY 500 decommissioning. | Q23: 2W | R23: Not in Used | T23: approved | U23: fahmi.badurisam@petronas.com | V23: 46014.153 | W23: Based on INDY 500 the UPS Monitoring System can be decommissioned by the end of December 2025. | X23: approved | Y23: hafiz.awahab@petronas.com | Z23: 46027.267 | AA23: N/A | AB23: approved | AC23: azwan.badari@petronas.com | AD23: 46028.104 | AE23: Full decommission. Delete all resources and RG PTAZSG-IAC-PROD-UPSMON-RG | AF23: approved | AG23: abdullah.haziq@petronas.com | AH23: 46048.323 | AI23: completed. | AJ23: A-000825 | AK23: PC-00074 | AL23: M | AM23: REQ000007789495 | AN23: disposal | AO23: 0
A24: b3e9a526-8855-4213-a5e0-c6b29a4822c1 | B24: CSSP10150850 | C24: chuah_kenneth@petronas.com | D24: decommission-cloud | E24: completed | F24: 46014.292 | G24: 46059.216 | H24: 46014.292 | I24: Cyber Security Trend Micro | J24: Cyber Security Trend Micro created for PRIVATECLOUD project record | K24: full | L24: DCOM202512232b1 | M24: ahmadfajar.faeiz@petronas.com | P24: All endpoints and servers protection (antimalware) migrated to Microsoft Defender for Endpoint (MDE). | Q24: 3M | R24: End of Lease | T24: approved | U24: chuah_kenneth@petronas.com | V24: 46014.295 | W24: Resources has been submitted to Azlisham for further validation. Actual Resources for Trend Micro Deep Security ; vcentmdsm01 - 10.14.17.149 vcentmdsm02 - 10.14.17.151 vcentmdsmdb - 10.14.17.150 | X24: approved | Y24: ahmadfajar.faeiz@petronas.com | Z24: 46050.336 | AA24: endpoint are protected by MDE | AB24: approved | AC24: azwan.badari@petronas.com | AD24: 46050.349 | AE24: Decommission vcentmdsm01 - 10.14.17.149, vcentmdsm02 - 10.14.17.151, vcentmdsmdb - 10.14.17.150 | AF24: approved | AG24: azlisham.md@petronas.com | AH24: 46059.216 | AI24: The decommission request has been completed, and the status is now updated accordingly. Kindly verify from your end and confirm once reviewed. | AJ24: A-000181 | AK24: 10055 | AL24: M | AM24: REQ000007847048 | AN24: retention
A25: 05ee9847-ff57-4050-a9e1-aec0b95b5284 | B25: CSSP10737482 | C25: syahir.shaiful@petronas.com | D25: decommission-cloud | E25: completed | F25: 46014.321 | G25: 46083.353 | H25: 46014.321 | I25: Upstream Technology and Digital Innovation - UTDI Data Operations | J25: 2023 - DSG repurpose for UTDI Data Ops as instruction from upstream tribe Provision of Azure Cloud Services for Halliburton Decision Space Geoscience (DSG) Application for Group Technical Data | K25: partial | M25: wanzul-atfi.matnawi@petronas.com | P25: There’s 19 storages tagged to the old PSR04669 “Provision of Azure Cloud Services for Halliburton Decision Space Geoscience (DSG) Application for Group Technical Data”, which was previously raised by Yusmaizi (no longer with the company) and then without clear reason tagged to my name. Upon checking, the resources was longer in used (refer attached communication). Checking was done with: Wan Zul-atfi Mat Nawi (Senior Manager - Technology Accelerator, UTDI) Joeffry Sham B Jamaludin (Senior Manager - Data Operations - Subsurface, UTDI) M Shazmeer M Jamaludin (Executive - G&G Data Operations, UTDI) M Haslan Abu Hassan (Manager - Cloud Demand, IS Digital) Attached is the list of resources: No NAME 1 azurebackuprgsouthcen324 2 ptazcusprodfw01 3 ptscustdmexicostorage01 4 ptazscusprodfw02 5 ptazscusprodgtdstor 6 csg1003200042685dd9 7 cs15f782fe28948x4fd8x8bc 8 csg8a71ac8104edx4e9bxade 9 cs18a71ac8104edx4e9bxade 10 csgb4ff1bb85058x44a6x880 11 cs1b4ff1bb85058x44a6x880 12 csbb4ff1bb85058x44a6x880 13 ptazsg5cloudshell 14 csgb9c4e2a3a10dx4a47x94b 15 uroqbositerecovasrcache 16 ptazweuprodgtdtargdiag 17 ptazweuprodstag 18 ptweutechdata 19 ptweutechdatabackup | Q25: 1M | R25: Not in Used | T25: approved | U25: syahir.shaiful@petronas.com | V25: 46014.328 | W25: There’s 19 storages tagged to the old PSR04669 “Provision of Azure Cloud Services for Halliburton Decision Space Geoscience (DSG) Application for Group Technical Data”, which was previously raised by Yusmaizi (no longer with the company) and then without clear reason tagged to my name. Upon checking, the resources was longer in used (refer attached communication). Checking was done with: Wan Zul-atfi Mat Nawi (Senior Manager - Technology Accelerator, UTDI) Joeffry Sham B Jamaludin (Senior Manager - Data Operations - Subsurface, UTDI) M Shazmeer M Jamaludin (Executive - G&G Data Operations, UTDI) M Haslan Abu Hassan (Manager - Cloud Demand, IS Digital) Attached is the list of resources: | X25: approved | Y25: wanzul-atfi.matnawi@petronas.com | Z25: 46076.157 | AA25: As have been identified and validated by Data team. | AB25: approved | AC25: azwan.badari@petronas.com | AD25: 46077.098 | AE25: Proceed as per listed | AF25: approved | AG25: azlisham.md@petronas.com | AH25: 46083.353 | AI25: The decommission request has been completed, and the status is now updated accordingly. Kindly verify from your end and confirm once reviewed. The storage account (highlighted in red) cannot be deleted due to its artifacts being in use | AJ25: A-000241 | AK25: PSR04669 | AL25: M | AM25: REQ000007888792 | AN25: noretention | AO25: 0
A26: 26802f94-96c1-42b1-8695-2b1d58cb4e08 | B26: CSSP10471891 | C26: syahir.shaiful@petronas.com | D26: decommission-cloud | E26: completed | F26: 46014.33 | G26: 46084.15 | H26: 46014.33 | I26: Upstream Technology and Digital Innovation - UTDI Data Operations | J26: 2023 - DSG repurpose for UTDI Data Ops as instruction from upstream tribe Provision of Cloud Services for Gabon Office - DSG West Europe | K26: partial | M26: wanzul-atfi.matnawi@petronas.com | P26: There’s 19 storages tagged to the old PSR04669 “Provision of Azure Cloud Services for Halliburton Decision Space Geoscience (DSG) Application for Group Technical Data”, which was previously raised by Yusmaizi (no longer with the company) and then without clear reason tagged to my name. Upon checking, the resources was longer in used (refer attached communication). Checking was done with: Wan Zul-atfi Mat Nawi (Senior Manager - Technology Accelerator, UTDI) Joeffry Sham B Jamaludin (Senior Manager - Data Operations - Subsurface, UTDI) M Shazmeer M Jamaludin (Executive - G&G Data Operations, UTDI) M Haslan Abu Hassan (Manager - Cloud Demand, IS Digital) Attached is the list of resources: No NAME 1 azurebackuprgsouthcen324 2 ptazcusprodfw01 3 ptscustdmexicostorage01 4 ptazscusprodfw02 5 ptazscusprodgtdstor 6 csg1003200042685dd9 7 cs15f782fe28948x4fd8x8bc 8 csg8a71ac8104edx4e9bxade 9 cs18a71ac8104edx4e9bxade 10 csgb4ff1bb85058x44a6x880 11 cs1b4ff1bb85058x44a6x880 12 csbb4ff1bb85058x44a6x880 13 ptazsg5cloudshell 14 csgb9c4e2a3a10dx4a47x94b 15 uroqbositerecovasrcache 16 ptazweuprodgtdtargdiag 17 ptazweuprodstag 18 ptweutechdata 19 ptweutechdatabackup | Q26: 1M | R26: Not in Used | T26: approved | U26: syahir.shaiful@petronas.com | V26: 46014.331 | W26: There’s 19 storages tagged to the old PSR04669 “Provision of Azure Cloud Services for Halliburton Decision Space Geoscience (DSG) Application for Group Technical Data”, which was previously raised by Yusmaizi (no longer with the company) and then without clear reason tagged to my name. Upon checking, the resources was longer in used (refer attached communication). Checking was done with: Wan Zul-atfi Mat Nawi (Senior Manager - Technology Accelerator, UTDI) Joeffry Sham B Jamaludin (Senior Manager - Data Operations - Subsurface, UTDI) M Shazmeer M Jamaludin (Executive - G&G Data Operations, UTDI) M Haslan Abu Hassan (Manager - Cloud Demand, IS Digital) Attached is the list of resources: No NAME 1 azurebackuprgsouthcen324 2 ptazcusprodfw01 3 ptscustdmexicostorage01 4 ptazscusprodfw02 5 ptazscusprodgtdstor 6 csg1003200042685dd9 7 cs15f782fe28948x4fd8x8bc 8 csg8a71ac8104edx4e9bxade 9 cs18a71ac8104edx4e9bxade 10 csgb4ff1bb85058x44a6x880 11 cs1b4ff1bb85058x44a6x880 12 csbb4ff1bb85058x44a6x880 13 ptazsg5cloudshell 14 csgb9c4e2a3a10dx4a47x94b 15 uroqbositerecovasrcache 16 ptazweuprodgtdtargdiag 17 ptazweuprodstag 18 ptweutechdata 19 ptweutechdatabackup | X26: approved | Y26: wanzul-atfi.matnawi@petronas.com | Z26: 46076.157 | AA26: As have been identified and validated by Data team. | AB26: approved | AC26: azwan.badari@petronas.com | AD26: 46077.098 | AE26: Proceed as per listed | AF26: approved | AG26: azlisham.md@petronas.com | AH26: 46084.15 | AI26: same request with CSSP10737482 | AJ26: A-000241 | AK26: AZ-DSG-WEU | AL26: M | AM26: REQ000007888791 | AN26: noretention | AO26: 0
A27: 280ff278-f9e5-4b4e-801a-bd7fcb23f040 | B27: CSSP10985709 | C27: nurulnajwa.mud@petronas.com | D27: decommission-cloud | E27: completed | F27: 46014.361 | G27: 46028.333 | H27: 46014.363 | I27: Business Intelligence Reporting and Analytic - BIRA | J27: Cloud Migration- BIRA (Business Intelligence Reporting & Analytic) | K27: partial | M27: kuek.chiayin@petronas.com.my | N27: - | P27: Approval to proceed with the decommissioning of these specified Azure Storage Account. due to not in used ptazsg5birastrdl Storage account StorageV2 ptazsg4birastrdl Storage account StorageV2 ptazsg1birastrlrs Storage account StorageV2 | Q27: 3M | R27: Not in Used | T27: approved | U27: nurulnajwa.mud@petronas.com | V27: 46014.365 | W27: Decom the following Storage account: DEV: ptazsg5birastrdl, UAT: ptazsg4birastrdl, PROD: ptazsg1birastrlrs | X27: approved | Y27: kuek.chiayin@petronas.com | Z27: 46027.306 | AA27: Verified that the storage account is not in use, and can be decommissioned. | AB27: approved | AC27: azlisham.md@petronas.com | AD27: 46027.553 | AE27: proceed to decom | AF27: approved | AG27: azlisham.md@petronas.com | AH27: 46028.333 | AI27: The decommission request has been completed, and the status is now updated accordingly. Kindly verify from your end and confirm once reviewed. | AJ27: A-000092 | AK27: 02421_15 | AL27: M | AM27: REQ000007789020 | AN27: noretention | AO27: 0
A28: dbdb4c36-7ab2-4bd2-a432-02c4d278d555 | B28: CSSP10217386 | C28: izdihar.roslan@petronas.com | D28: decommission-cloud | E28: completed | F28: 46015.073 | G28: 46031.086 | H28: 46015.073 | I28: Visual Integrated Solution for Material - VISMA | J28: VISUAL INTEGRATED SOLUTION for MATERIAL | K28: partial | M28: sazali.mokhtar@petronas.com | P28: To decommission old resources in Singapore region due to completed migration in MY region | Q28: 2W | R28: Cloud Migration | T28: approved | U28: izdihar.roslan@petronas.com | V28: 46015.075 | W28: To decommission old resources in Singapore region due to completed migration in MY region | X28: approved | Y28: sazali.mokhtar@petronas.com | Z28: 46027.139 | AA28: To decommission old resources in Singapore region due to completed migration in MY region - ( Hamizah ) | AB28: approved | AC28: azwan.badari@petronas.com | AD28: 46028.09 | AE28: Decommission VISMA in SG region. ptawsg-iac-nonprod-corporatecommon-visma-dev-bucket iam/ptaw_iac_nonprod_corporatecommon_visma_user | AF28: approved | AG28: azwan.badari@petronas.com | AH28: 46031.086 | AI28: Completed | AJ28: A-000847 | AK28: 4631 | AL28: S | AM28: REQ000007789469 | AN28: noretention | AO28: 0
A29: 1eacd220-97a0-4e97-9a5b-0673c47648a5 | B29: CSSP10442429 | C29: nurizzati.mbasir@petronas.com | D29: decommission-cloud | E29: completed | F29: 46015.17 | G29: 46049.135 | H29: 46015.17 | I29: SMART / DPVA Upstream | J29: Vessel Analytics (VA) | K29: full | L29: DCOM2025122461e | M29: salita.yami@petronas.com.my | N29: https://app.powerbi.com/reportEmbed?reportId=f414f4f3-df10-4736-a643-7fb9016513c0&autoAuth=true&ctid=3b2e8941-7948-4131-978a-b2dfc7295091 | O29: 3866 | P29: This application is no longer in used by the users. | Q29: 12M | R29: Not in Used | T29: approved | U29: nurizzati.mbasir@petronas.com | V29: 46015.197 | W29: Please decom RG that related with Vessel Analytics(VA) application only for all enviroments. PTAZSG-PROD-DPVA-RG PTAZSG-DEV-DPVA-RG | X29: approved | Y29: salita.yami@petronas.com | Z29: 46017.056 | AA29: Proceed | AB29: approved | AC29: azwan.badari@petronas.com | AD29: 46028.111 | AE29: Full decommission. PTAZSG-PROD-DPVA-RG & PTAZSG-DEV-DPVA-RG | AF29: approved | AG29: azlisham.md@petronas.com | AH29: 46049.135 | AI29: The decommission request has been completed, and the status is now updated accordingly. Kindly verify from your end and confirm once reviewed. | AJ29: A-000779 | AK29: 3866 | AL29: M | AM29: REQ000007790074 | AN29: retention | AO29: 1095
A30: d8a012f7-8228-43ae-90b2-567d90948366 | B30: CSSP10818859 | C30: noorsabrina.mahhussi@petronas.com | D30: decommission-cloud | E30: completed | F30: 46020.19 | G30: 46030.281 | H30: 46020.19 | I30: MyProcure | J30: Procurement Innovation Through Automation And Procurement Marketplace | K30: partial | M30: mosman.mhassanomar@petronas.com.my | O30: PSR04343 | P30: Resources are no longer in use. Previous request to decomm had been raised in 2024 but did not go through. Raising a new urgent request in order to comply with DPIA requirements. Kindly refer to attachment for specific resources to be decommissioned. | Q30: 3M | R30: Obsolete | T30: approved | U30: noorsabrina.mahhussi@petronas.com | V30: 46020.194 | W30: Confirmed based on list provided by Zul Fakar. List is attached | X30: approved | Y30: mosman.mhassanomar@petronas.com | Z30: 46021.084 | AA30: As per recommended by the Support Team/ Technical Team | AB30: approved | AC30: azwan.badari@petronas.com | AD30: 46028.112 | AE30: Decommission listed storage account | AF30: approved | AG30: azlisham.md@petronas.com | AH30: 46030.281 | AI30: The decommission request has been completed, and the status is now updated accordingly. Kindly verify from your end and confirm once reviewed. | AJ30: A-000490 | AK30: 4343 | AL30: M | AM30: REQ000007789503 | AN30: retention | AO30: 90
A31: b6820993-44bf-4101-ba58-bee50b0da18d | B31: CSSP10371521 | C31: azrin.azizan@petronas.com | D31: decommission-cloud | E31: completed | F31: 46021.159 | G31: 46035.397 | H31: 46021.159 | I31: M365 SharePoint - SPO | J31: Cloud Migration Program - Migration SharePoint 2013 to SharePoint 2019 | K31: partial | M31: nshahidahothman@petronas.com.my | P31: The SP2019 staging environment is no longer required, as all relevant testing, validation, and migration activities have been completed. There are currently no active applications, users, or business processes dependent on this staging farm. Additionally, SharePoint Server 2019 is approaching its end-of-life (EOL) in July 2026. | Q31: 2W | R31: Obsolete | T31: approved | U31: azrin.azizan@petronas.com | V31: 46021.303 | W31: Application Server 172.25.52.142 PTSG-4SPss01 172.25.52.143 PTSG-4SPss02 172.25.52.144 PTSG-4SPss03 172.25.52.145 PTSG-4SPss04 172.25.52.177 PTSG-4SPos01 172.25.52.147 PTSG-4SPfs01 172.25.52.148 PTSG-4SPap01 172.25.52.149 PTSG-4SPap02 SP Load Balancer 172.25.50.35 PTAZSG-4SPWB-LB WFE Server 172.25.50.31 PTSG-4SPwb01 172.25.50.32 PTSG-4SPwb02 DB Load Balancer 172.25.56.45 PTAZSG-4SPDB-LB Database Server 172.25.56.37 PTSG-4SPdb01 | X31: approved | Y31: nshahidahothman@petronas.com | Z31: 46021.375 | AA31: total resource for staging : 53 | AB31: approved | AC31: azwan.badari@petronas.com | AD31: 46028.114 | AE31: Decommission listed resources | AF31: approved | AG31: azlisham.md@petronas.com | AH31: 46035.397 | AI31: The decommission request has been completed, and the status is now updated accordingly. Kindly verify from your end and confirm once reviewed. | AJ31: A-000449 | AK31: 00915_1 | AL31: L | AM31: REQ000007789505 | AN31: noretention | AO31: 0
A32: 4b944bb2-7e2b-4d62-b883-9faa363798d6 | B32: CSSP10672556 | C32: izdihar.roslan@petronas.com | D32: decommission-cloud | E32: completed | F32: 46021.251 | G32: 46031.086 | H32: 46021.251 | I32: Freight-X | J32: Freight-X | K32: partial | M32: sazali.mokhtar@petronas.com | P32: To decommission old resources in Singapore region due to completed migration in MY region | Q32: 2W | R32: Cloud Migration | T32: approved | U32: izdihar.roslan@petronas.com | V32: 46021.253 | W32: To decommission old resources in AWS Singapore region due to completed migration in AWS MY region | X32: approved | Y32: sazali.mokhtar@petronas.com | Z32: 46027.139 | AA32: To decommission old resources in Singapore region due to completed migration in MY region - (Hamizah) | AB32: approved | AC32: azwan.badari@petronas.com | AD32: 46028.098 | AE32: Repatriation. | AF32: approved | AG32: azwan.badari@petronas.com | AH32: 46031.086 | AI32: Completed | AJ32: A-000326 | AK32: 3217 | AL32: S | AM32: REQ000007789492 | AN32: noretention | AO32: 0
A33: fadb5b26-da4e-4bb7-be40-533763a9818e | B33: CSSP10774226 | C33: wanmiqbal.wanmhdnoor@petronas.com | D33: decommission-cloud | E33: completed | F33: 46021.345 | G33: 46048.323 | H33: 46021.345 | I33: Upstream Real Time Data Program - URTD | J33: Installation of Upstream Real Time Data Program (URTD) for Centre of Excellence, PCSB | K33: partial | M33: mohammadsani.johari@petronas.com | N33: stg.urtd.petronas.com | P33: PaaS DB and Dev Server are no longer in used. | Q33: 3M | R33: Not in Used | T33: approved | U33: wanmiqbal.wanmhdnoor@petronas.com | V33: 46021.349 | W33: Only Decomm resources related to ptsg-1urtdsvrdb01.database.windows.net & 172.25.32.16, PTSG-1URTDAP02 | X33: approved | Y33: mohammadsani.johari@petronas.com | Z33: 46021.468 | AA33: Resources not in used. | AB33: approved | AC33: azwan.badari@petronas.com | AD33: 46028.122 | AE33: Decommission listed resources only | AF33: approved | AG33: abdullah.haziq@petronas.com | AH33: 46048.323 | AI33: completed. | AJ33: A-000827 | AK33: 747 | AL33: M | AM33: REQ000007790220 | AN33: retention | AO33: 30
A34: e59f0759-3ddf-4f24-845b-2520cb3a8fdd | B34: CSSP10719729 | C34: wanmiqbal.wanmhdnoor@petronas.com | D34: decommission-cloud | E34: completed | F34: 46021.355 | G34: 46031.328 | H34: 46021.355 | I34: Decision Ready Data - DRD | J34: Implementation of Decision Ready Data (DRD) | K34: full | L34: DCOM20251230434 | M34: mohammadsani.johari@petronas.com | N34: mmpd.drd.petronas.com.my, downstream.drd.petronas.com | P34: The DRD for downstream is part of the decommissioning exercise under Black Swan. | Q34: 12M | R34: Not in Used | T34: approved | U34: wanmiqbal.wanmhdnoor@petronas.com | V34: 46021.355 | W34: The DRD for downstream is part of the decommissioning exercise under Black Swan | X34: approved | Y34: mohammadsani.johari@petronas.com | Z34: 46021.467 | AA34: Approved as per indy500. | AB34: approved | AC34: azwan.badari@petronas.com | AD34: 46028.117 | AE34: Full decommission for project code 03418 including DNS | AF34: approved | AG34: azwan.badari@petronas.com | AH34: 46031.328 | AI34: Completed | AJ34: A-000232 | AK34: 3418 | AL34: L | AM34: REQ000007789509 | AN34: retention | AO34: 30
A35: 554aa139-262d-4c6f-87cd-e03c650d15e4 | B35: CSSP10932025 | C35: maffendy.bobmazmi@petronas.com | D35: decommission-cloud | E35: completed | F35: 46027.266 | G35: 46052.203 | H35: 46027.268 | I35: Asset Integrity Management Database - AIDA GPU | J35: GPU Asset Integrity Management Database AIDA | K35: full | L35: DCOM20260105ade | M35: huajin.tan@petronas.com.my | N35: aida.petronas.com | P35: Asset has been expanded to enterprise level (MAVIS). The asset originally initiated by GPU and has been expanded to PETRONAS enterprise level (MAVIS) by collaboration with GTS. New application replacing AIDA, has been launched and deployed at GPU namely Machine Vision & Inspection Workflow Management System. The asset write-off and disposal has been endorsed by PGB DSC. | Q35: 2W | R35: Not in Used | T35: approved | U35: maffendy.bobmazmi@petronas.com | V35: 46027.269 | W35: Confirmed | X35: approved | Y35: huajin.tan@petronas.com | Z35: 46051.127 | AA35: Approved as business have provided their endorsement | AB35: approved | AC35: azwan.badari@petronas.com | AD35: 46051.189 | AE35: Full decommission ptazsg-dev-gpu-aida-rg and DNS aida.petronas.com | AF35: approved | AG35: azwan.badari@petronas.com | AH35: 46052.203 | AI35: Completed | AJ35: A-000036 | AK35: 2637 | AL35: M | AM35: REQ000007849037 | AN35: noretention | AO35: 0
A36: bb20d2ac-320e-49d2-bb7e-ba31119ecf21 | B36: CSSP10561989 | C36: norhamizah.hasni@petronas.com | D36: decommission-cloud | E36: cancelled | F36: 46027.266 | G36: 46050.095 | H36: 46027.266 | I36: MyProcure | J36: Procurement Innovation Through Automation And Procurement Marketplace | K36: partial | M36: sazali.mokhtar@petronas.com | P36: To decommission old resources in Singapore region due to completed migration in MY region | Q36: 2W | R36: Cloud Migration | T36: rejected | U36: azwan.badari@petronas.com | V36: 46050.095 | W36: No longer required | Y36: sazali.mokhtar@petronas.com | AC36: CCoE Business | AG36: CCoE Operations | AJ36: A-000490 | AK36: 4343 | AN36: noretention | AO36: 0
A37: 4586e4b5-916f-4c51-9e27-fe55a08e3eb7 | B37: CSSP10474599 | C37: izdihar.roslan@petronas.com | D37: decommission-cloud | E37: cancelled | F37: 46027.332 | G37: 46057.284 | H37: 46027.332 | I37: FORTS | J37: AWS Cloud Migration - FORTS | K37: full | L37: NA | M37: mdkhiri@petronas.com | P37: FFFF | Q37: 2W | R37: Not in Used | T37: rejected | U37: azwan.badari@petronas.com | V37: 46057.284 | W37: Cancelled | Y37: mdkhiri@petronas.com | AC37: CCoE Business | AG37: CCoE Operations | AJ37: A-000321 | AK37: 00915_117 | AN37: noretention | AO37: 0
A38: 0a1cea43-c926-4b79-956d-98225c0a684c | B38: CSSP10578777 | C38: zulhasyidi.hassan@petronas.com | D38: decommission-cloud | E38: completed | F38: 46028.12 | G38: 46043.164 | H38: 46028.12 | I38: Plant Information - PI GTS | J38: AWS-Cloud Migration - PI GTS | K38: full | L38: DCOM20260106247 | M38: mohammadsani.johari@petronas.com.my | N38: gts.pi.petronas.com | P38: Not in used | Q38: 1M | R38: Not in Used | T38: approved | U38: zulhasyidi.hassan@petronas.com | V38: 46028.122 | W38: Full decommissioning for GTS PI application | X38: approved | Y38: mohammadsani.johari@petronas.com | Z38: 46041.164 | AA38: Approved, as per Indy500 requirement. | AB38: approved | AC38: azwan.badari@petronas.com | AD38: 46041.216 | AE38: Full decommission PI (00915_107) | AF38: approved | AG38: azwan.badari@petronas.com | AH38: 46043.164 | AI38: Completed | AJ38: A-000570 | AK38: 00915_107 | AL38: M | AM38: REQ000007826332 | AN38: noretention | AO38: 0
A39: 4e611de9-a52a-41ed-b37f-bb0808c8e961 | B39: CSSP10828102 | C39: izdihar.roslan@petronas.com | D39: decommission-cloud | E39: completed | F39: 46028.12 | G39: 46043.468 | H39: 46028.12 | I39: Enterprise Decarbonization iCON - ED-iCON | J39: Enterprise Decarbonization (ED) iCON | K39: partial | M39: sazali.mokhtar@petronas.com | O39: 3476 | P39: Cloud Repatriation - To decommission old resources in Singapore region due to completed migration in MY region | Q39: 2W | R39: Cloud Migration | T39: approved | U39: izdihar.roslan@petronas.com | V39: 46028.122 | W39: Cloud Repatriation - To decommission old resources in Singapore region due to completed migration in MY region | X39: approved | Y39: sazali.mokhtar@petronas.com | Z39: 46042.115 | AA39: Cloud Repatriation - To decommission old resources in Singapore region due to completed migration in MY region | AB39: approved | AC39: azwan.badari@petronas.com | AD39: 46042.118 | AE39: Cloud Repatriation - Decomm 03476 in SG | AF39: approved | AG39: azwan.badari@petronas.com | AH39: 46043.468 | AI39: Completed | AJ39: A-000033 | AK39: 3476 | AL39: M | AM39: REQ000007828185 | AN39: noretention | AO39: 0
A40: 90120b9f-5cea-46de-a540-4ff191469fc6 | B40: CSSP10960000 | C40: mohamadsyafiq.mnoor@petronas.com | D40: decommission-cloud | E40: completed | F40: 46030.268 | G40: 46037.127 | H40: 46030.268 | I40: Azure Machine Learning - PC Derivatives | J40: Run & Maintain Citizen Analytics Use Case for Sales Gas Optimization for PC Derivatives Sdn Bhd | K40: partial | M40: khairulnizam.bahari@petronas.com | P40: To decommission Azure Resource Group PTAZSG-IAC-DAA-PROD-PCOGD_SGO-RG | Q40: 2W | R40: End of Lease | T40: approved | U40: mohamadsyafiq.mnoor@petronas.com | V40: 46030.27 | W40: As per email from business, this Azure Resource Group PTAZSG-IAC-DAA-PROD-PCOGD_SGO-RG need to be decommissioned | X40: approved | Y40: khairulnizam.bahari@petronas.com | Z40: 46031.343 | AA40: Decommission Azure Resource Group PTAZSG-IAC-DAA-PROD-PCOGD_SGO-RG | AB40: approved | AC40: azwan.badari@petronas.com | AD40: 46036.32 | AE40: Decommission all resources and delete RG PTAZSG-IAC-DAA-PROD-PCOGD-SGO-RG | AF40: approved | AG40: azlisham.md@petronas.com | AH40: 46037.127 | AI40: The decommission request has been completed, and the status is now updated accordingly. Kindly verify from your end and confirm once reviewed. | AJ40: A-001304 | AK40: 4758 | AL40: M | AM40: REQ000007815155 | AN40: retention | AO40: 7
A41: 9f28ea8a-b13b-4a5b-84ba-cb9eb6ad0d0d | B41: CSSP10159861 | C41: mibrahim.sulaima@petronas.com | D41: decommission-cloud | E41: cancelled | F41: 46031.086 | G41: 46031.086 | H41: 46031.086 | I41: Enhancement of Enhanced Resource Monetization by Artificial Intelligence - ERMAI Phase 3 for Malaysia Petroleum Management - MPM | J41: Implementation of Enhanced Resource Monetization Artificial Intelligence (ERMAI) for Malaysia Petroleum Management (MPM) | K41: partial | M41: limeng.tan@petronas.com.my | P41: To decom ermai dev resources that not being used anymore | Q41: 2W | R41: Not in Used | T41: rejected | U41: mibrahim.sulaima@petronas.com | V41: 46031.086 | Y41: limeng.tan@petronas.com | AC41: CCoE Business | AG41: CCoE Operations | AJ41: A-000303 | AK41: 2123 | AN41: noretention | AO41: 0
A42: 410ea196-1243-4e2c-b845-57ce8b099e18 | B42: CSSP10622149 | C42: mibrahim.sulaima@petronas.com | D42: decommission-cloud | E42: cancelled | F42: 46031.088 | G42: 46031.088 | H42: 46031.088 | I42: Enhancement of Enhanced Resource Monetization by Artificial Intelligence - ERMAI Phase 3 for Malaysia Petroleum Management - MPM | J42: Enhancement of Enhanced Resource Monetization by Artificial Intelligence (ERMAI) Phase 4 | K42: partial | M42: limeng.tan@petronas.com.my | P42: To decom AKS and PosgreSQL DB resources for ERMAI dev since not being used anymore | Q42: 2W | R42: Not in Used | T42: rejected | U42: mibrahim.sulaima@petronas.com | V42: 46031.088 | Y42: limeng.tan@petronas.com | AC42: CCoE Business | AG42: CCoE Operations | AJ42: A-000303 | AK42: 100 | AN42: noretention | AO42: 0
A43: 9aecfc02-2056-4390-879d-2a2098196200 | B43: CSSP10527994 | C43: mibrahim.sulaima@petronas.com | D43: decommission-cloud | E43: completed | F43: 46031.089 | G43: 46038.078 | H43: 46031.089 | I43: Enhancement of Enhanced Resource Monetization by Artificial Intelligence - ERMAI Phase 3 for Malaysia Petroleum Management - MPM | J43: Implementation of Enhanced Resource Monetization Artificial Intelligence (ERMAI) Malaysia Petroleum Management (MPM) | K43: partial | M43: limeng.tan@petronas.com.my | P43: To decom AKS and PosgreSQL temp01 in ERMAI dev since not being used anymore | Q43: 2W | R43: Not in Used | T43: approved | U43: mibrahim.sulaima@petronas.com | V43: 46031.096 | W43: To decom AKS - ptsg-5ermaiaks01 and PosgreSQL Flexible server - ptazsg-5ermaisql01temp. These resources have been confirmed not being used anymore. This can save cost in Dev environment for about 30% monthly. | X43: approved | Y43: limeng.tan@petronas.com | Z43: 46031.388 | AA43: approved as requested | AB43: approved | AC43: azwan.badari@petronas.com | AD43: 46036.324 | AE43: Decommission AKS - ptsg-5ermaiaks01 and PosgreSQL Flexible server - ptazsg-5ermaisql01temp | AF43: approved | AG43: azwan.badari@petronas.com | AH43: 46038.078 | AI43: Completed | AJ43: A-000303 | AK43: 4443 | AL43: M | AM43: REQ000007815159 | AN43: noretention | AO43: 0
A44: e09d2466-1f5f-48a0-8531-127ecf1af6ec | B44: CSSP10175424 | C44: mnizar.omar@petronas.com | D44: decommission-cloud | E44: cancelled | F44: 46031.139 | G44: 46031.145 | H44: 46031.139 | I44: Active Directory Domain Controller - ADDC KVDC | J44: Active Directory Domain Controller - ADDC KVDC created for PRIVATECLOUD project record | K44: partial | M44: zulizzi.yasin@petronas.com.my | P44: This domain controller is not required anymore as part of domain controllers decommissioning plan. | Q44: 2W | R44: Not in Used | T44: rejected | U44: mnizar.omar@petronas.com | V44: 46031.145 | Y44: zulizzi.yasin@petronas.com | AC44: CCoE Business | AG44: CCoE Operations | AJ44: A-000015 | AK44: 10002_03 | AN44: noretention | AO44: 0
A45: 5d8ee9f0-2be6-4505-be54-65b3bf899f4d | B45: CSSP10240613 | C45: mnizar.omar@petronas.com | D45: decommission-cloud | E45: cancelled | F45: 46031.158 | G45: 46031.159 | H45: 46031.158 | I45: Common Active Directory - AD | J45: Common infrastructure for COC dashboard, integration, ict2u, labs | K45: partial | M45: zulizzi.yasin@petronas.com.my | P45: Domain controllers are not in use anymore. Please refer the attachment for the list of items to be decommed. | Q45: 2W | R45: Not in Used | T45: rejected | U45: mnizar.omar@petronas.com | V45: 46031.159 | Y45: zulizzi.yasin@petronas.com | AC45: CCoE Business | AG45: CCoE Operations | AJ45: C-000004 | AK45: Common-AD | AN45: noretention | AO45: 0
A46: 7f765445-b497-44da-8017-8873ca22791f | B46: CSSP10262348 | C46: mnizar.omar@petronas.com | D46: decommission-cloud | E46: completed | F46: 46031.173 | G46: 46041.14 | H46: 46031.173 | I46: Common Active Directory - AD | J46: Common infrastructure for COC dashboard, integration, ict2u, labs | K46: partial | M46: zulizzi.yasin@petronas.com.my | P46: The domain controllers are not in use anymore which are part of our decommissioning plan. Please refer the attachment for the list of servers to be decommissioned. CEN308-INFDC-03 PTSCUS-1INFdc01 PTSCUS-1INFdc02 PTWEU-1INFdc01 PTWEU-1INFdc02 AZRSAPRODADDS01 | Q46: 2W | R46: Not in Used | T46: approved | U46: mnizar.omar@petronas.com | V46: 46031.175 | W46: Servers have been shut down and confirmed not in use. | X46: approved | Y46: zulizzi.yasin@petronas.com | Z46: 46035.093 | AA46: Reviewed | AB46: approved | AC46: azwan.badari@petronas.com | AD46: 46036.357 | AE46: Decommission listed VM CEN308-INFDC-03 10.3.193.171 PTSCUS-1INFdc01 172.18.32.11 PTSCUS-1INFdc02 172.18.32.12 PTWEU-1INFdc01 172.24.32.11 PTWEU-1INFdc02 172.24.32.4 AZRSAPRODADDS01 172.24.9.1 | AF46: approved | AG46: azlisham.md@petronas.com | AH46: 46041.14 | AI46: The decommission request has been completed, and the status is now updated accordingly. Kindly verify from your end and confirm once reviewed. | AJ46: C-000004 | AK46: Common-AD | AL46: M | AM46: REQ000007815546 | AN46: noretention | AO46: 0
A47: a4db4910-6efc-4ec6-adcc-0c92781fa443 | B47: CSSP10861160 | C47: izdihar.roslan@petronas.com | D47: decommission-cloud | E47: cancelled | F47: 46031.299 | G47: 46051.195 | H47: 46031.299 | I47: MyProcure | J47: Procurement Innovation Through Automation And Procurement Marketplace | K47: partial | M47: sazali.mokhtar@petronas.com | O47: 4343 | P47: Cloud Repatriation - To decommission old resources in Singapore region due to completed migration in MY region | Q47: 2W | R47: Cloud Migration | T47: rejected | U47: azwan.badari@petronas.com | V47: 46051.195 | W47: Cancelled | Y47: sazali.mokhtar@petronas.com | AC47: CCoE Business | AG47: CCoE Operations | AJ47: A-000490 | AK47: 4343 | AN47: noretention | AO47: 0
A48: 9b7f550e-e5cb-4f88-94d2-23a74bc7c118 | B48: CSSP10888172 | C48: izdihar.roslan@petronas.com | D48: decommission-cloud | E48: cancelled | F48: 46031.302 | G48: 46051.195 | H48: 46031.302 | I48: MyProcure | J48: Procurement Innovation Through Automation And Procurement Marketplace | K48: partial | M48: sazali.mokhtar@petronas.com | P48: Cloud Repatriation - To decommission old resources in Singapore region due to completed migration in MY region | Q48: 2W | R48: Cloud Migration | T48: rejected | U48: azwan.badari@petronas.com | V48: 46051.195 | W48: Cancelled | Y48: sazali.mokhtar@petronas.com | AC48: CCoE Business | AG48: CCoE Operations | AJ48: A-000490 | AK48: 4343 | AN48: noretention | AO48: 0
A49: 170c452c-8ff0-4744-b0fe-2d5884db40b4 | B49: CSSP10280084 | C49: izdihar.roslan@petronas.com | D49: decommission-cloud | E49: cancelled | F49: 46031.303 | G49: 46051.195 | H49: 46031.303 | I49: MyProcure | J49: Procurement Innovation Through Automation And Procurement Marketplace | K49: partial | M49: sazali.mokhtar@petronas.com | P49: Cloud Repatriation - To decommission old resources in Singapore region due to completed migration in MY region | Q49: 2W | R49: Cloud Migration | T49: rejected | U49: azwan.badari@petronas.com | V49: 46051.195 | W49: Cancelled | Y49: sazali.mokhtar@petronas.com | AC49: CCoE Business | AG49: CCoE Operations | AJ49: A-000490 | AK49: 4343 | AN49: noretention | AO49: 0
A50: 10815a01-d922-4fc6-aa81-7d131c5d370f | B50: CSSP10575261 | C50: izdihar.roslan@petronas.com | D50: decommission-cloud | E50: cancelled | F50: 46031.305 | G50: 46219.26 | H50: 46031.305 | I50: MyProcure | J50: Procurement Innovation Through Automation And Procurement Marketplace | K50: partial | M50: sazali.mokhtar@petronas.com | P50: Cloud Repatriation - To decommission old resources in Singapore region due to completed migration in MY region | Q50: 2W | R50: Cloud Migration | T50: rejected | U50: izdihar.roslan@petronas.com | V50: 46219.26 | Y50: sazali.mokhtar@petronas.com | AC50: CCoE Business | AG50: CCoE Operations | AJ50: A-000490 | AK50: 2800 | AN50: noretention | AO50: 0
A51: e9494d31-0e6e-46f7-b930-083021ca8133 | B51: CSSP10692553 | C51: izdihar.roslan@petronas.com | D51: decommission-cloud | E51: cancelled | F51: 46031.315 | G51: 46057.285 | H51: 46031.315 | I51: FORTS | J51: AWS Cloud Migration - FORTS | K51: full | L51: DCOM202601094c5 | M51: mkhiri.msharif@petronas.com.my | P51: As in attached email | Q51: 2W | R51: Not in Used | T51: rejected | U51: azwan.badari@petronas.com | V51: 46057.285 | W51: Cancelled | Y51: mkhiri.msharif@petronas.com | AC51: CCoE Business | AG51: CCoE Operations | AJ51: A-000321 | AK51: 00915_117 | AN51: noretention | AO51: 0
A52: d0967d7a-2fa4-4c39-bbdd-e72c29b361f7 | B52: CSSP10215372 | C52: izdihar.roslan@petronas.com | D52: decommission-cloud | E52: completed | F52: 46031.316 | G52: 46041.015 | H52: 46031.316 | I52: FORTS | J52: AWS Cloud Migration - FORTS | K52: full | L52: DCOM202601094c5 | M52: mkhiri.msharif@petronas.com.my | P52: As communicated in attached email | Q52: 2W | R52: Not in Used | T52: approved | U52: izdihar.roslan@petronas.com | V52: 46031.316 | W52: Full decomission | X52: approved | Y52: mkhiri.msharif@petronas.com | Z52: 46031.319 | AA52: Approced. Data has been backup | AB52: approved | AC52: azwan.badari@petronas.com | AD52: 46036.363 | AE52: Decommission FORTS under code 00915_117 | AF52: approved | AG52: azwan.badari@petronas.com | AH52: 46041.015 | AI52: Completed | AJ52: A-000321 | AK52: 00915_117 | AL52: M | AM52: REQ000007815636 | AN52: disposal | AO52: 0
A53: fe23029d-5099-4b04-b757-7557c66cb686 | B53: CSSP10783734 | C53: izdihar.roslan@petronas.com | D53: decommission-cloud | E53: cancelled | F53: 46031.323 | G53: 46051.195 | H53: 46031.323 | I53: MyProcure | J53: Procurement Innovation Through Automation And Procurement Marketplace | K53: partial | M53: sazali.mokhtar@petronas.com | P53: Cloud Repatriation - To decommission old resources in Singapore region due to completed migration in MY region | Q53: 2W | R53: Cloud Migration | T53: rejected | U53: azwan.badari@petronas.com | V53: 46051.195 | W53: Cancelled | Y53: sazali.mokhtar@petronas.com | AC53: CCoE Business | AG53: CCoE Operations | AJ53: A-000490 | AK53: 4343 | AN53: noretention | AO53: 0
A54: 8d44e34e-b191-49d0-9af6-a21890477bbc | B54: CSSP10466320 | C54: izdihar.roslan@petronas.com | D54: decommission-cloud | E54: cancelled | F54: 46031.324 | G54: 46051.195 | H54: 46031.324 | I54: MyProcure | J54: Procurement Innovation Through Automation And Procurement Marketplace | K54: partial | M54: sazali.mokhtar@petronas.com | P54: Cloud Repatriation - To decommission old resources in Singapore region due to completed migration in MY region | Q54: 2W | R54: Cloud Migration | T54: rejected | U54: azwan.badari@petronas.com | V54: 46051.195 | W54: Cancelled | Y54: sazali.mokhtar@petronas.com | AC54: CCoE Business | AG54: CCoE Operations | AJ54: A-000490 | AK54: 4343 | AN54: noretention | AO54: 0
A55: b4d3c314-6ea6-4c32-b1b9-32e033e4544a | B55: CSSP10764031 | C55: izdihar.roslan@petronas.com | D55: decommission-cloud | E55: cancelled | F55: 46031.325 | G55: 46219.259 | H55: 46031.325 | I55: MyProcure | J55: Procurement Innovation Through Automation And Procurement Marketplace | K55: partial | M55: sazali.mokhtar@petronas.com | P55: Cloud Repatriation - To decommission old resources in Singapore region due to completed migration in MY region | Q55: 2W | R55: Cloud Migration | T55: rejected | U55: izdihar.roslan@petronas.com | V55: 46219.259 | Y55: sazali.mokhtar@petronas.com | AC55: CCoE Business | AG55: CCoE Operations | AJ55: A-000490 | AK55: 2800 | AN55: noretention | AO55: 0
A56: 4d27c2ff-c345-45bf-9411-d4aae3fb161a | B56: CSSP10618851 | C56: izdihar.roslan@petronas.com | D56: decommission-cloud | E56: cancelled | F56: 46031.326 | G56: 46051.195 | H56: 46031.326 | I56: MyProcure | J56: Procurement Innovation Through Automation And Procurement Marketplace | K56: partial | M56: sazali.mokhtar@petronas.com | P56: Cloud Repatriation - To decommission old resources in Singapore region due to completed migration in MY region | Q56: 2W | R56: Cloud Migration | T56: rejected | U56: azwan.badari@petronas.com | V56: 46051.195 | W56: Cancelled | Y56: sazali.mokhtar@petronas.com | AC56: CCoE Business | AG56: CCoE Operations | AJ56: A-000490 | AK56: 4343 | AN56: noretention | AO56: 0
A57: 5a6a6648-d1fc-46cb-8f5d-a053dd4e3fc9 | B57: CSSP10913240 | C57: izdihar.roslan@petronas.com | D57: decommission-cloud | E57: completed | F57: 46031.327 | G57: 46047.732 | H57: 46031.328 | I57: MyProcure | J57: Procurement Innovation Through Automation And Procurement Marketplace | K57: partial | M57: sazali.mokhtar@petronas.com | P57: Cloud Repatriation - To decommission old resources in Singapore region due to completed migration in MY region | Q57: 2W | R57: Cloud Migration | T57: approved | U57: izdihar.roslan@petronas.com | V57: 46031.333 | W57: To decom AWS SG Resources for Myprocure as in attached excel file. | X57: approved | Y57: sazali.mokhtar@petronas.com | Z57: 46042.115 | AA57: Cloud Repatriation - To decommission old resources in Singapore region due to completed migration in MY region | AB57: approved | AC57: azwan.badari@petronas.com | AD57: 46042.119 | AE57: Cloud Repatriation - Decomm 04343 in SG | AF57: approved | AG57: azwan.badari@petronas.com | AH57: 46047.732 | AI57: Completed | AJ57: A-000490 | AK57: 4343 | AL57: M | AM57: REQ000007828187 | AN57: noretention | AO57: 0
A58: 9355a540-93bd-43a2-a7c5-cc43fb898fb9 | B58: CSSP10212506 | C58: wanmiqbal.wanmhdnoor@petronas.com | D58: decommission-cloud | E58: completed | F58: 46034.146 | G58: 46042.077 | H58: 46034.146 | I58: Upstream Real Time Data Program - URTD | J58: Installation of Upstream Real Time Data Program (URTD) for Centre of Excellence, PCSB | K58: partial | M58: mohammadsani.johari@petronas.com | N58: NA | P58: Decom only storage account | Q58: 3M | R58: Not in Used | T58: approved | U58: wanmiqbal.wanmhdnoor@petronas.com | V58: 46034.15 | W58: To decomm only storage account. | X58: approved | Y58: mohammadsani.johari@petronas.com | Z58: 46041.165 | AA58: Approved, as per Indy500 requirement. | AB58: approved | AC58: azwan.badari@petronas.com | AD58: 46041.213 | AE58: Decommission ptsg1urtd2func01strg only | AF58: approved | AG58: azlisham.md@petronas.com | AH58: 46042.077 | AI58: The decommission request has been completed, and the status is now updated accordingly. Kindly verify from your end and confirm once reviewed. | AJ58: A-000827 | AK58: 747 | AL58: S | AM58: REQ000007825797 | AN58: disposal | AO58: 0
A59: e11ae033-64c5-4dc0-94b6-bbeef2b9f8d0 | B59: CSSP10256227 | C59: yenheung.yap@petronas.com | D59: decommission-cloud | E59: completed | F59: 46038.084 | G59: 46044.292 | H59: 46038.084 | I59: Business Intelligence Reporting and Analytic - BIRA | J59: Cloud Migration- BIRA (Business Intelligence Reporting & Analytic) | K59: partial | M59: adi.razali@petronas.com | P59: Decom CCM Database only | Q59: 3M | R59: Not in Used | T59: approved | U59: yenheung.yap@petronas.com | V59: 46038.085 | W59: decom CCM database only | X59: approved | Y59: adi.razali@petronas.com | Z59: 46041.078 | AA59: As per planned by Eric Yap | AB59: approved | AC59: azwan.badari@petronas.com | AD59: 46041.152 | AE59: Decommission database named, (backup 3 months) CCMAppMart in PTSG-4BIRADB01. CCMAppMart in PTSG-1BIRADBC2 | AF59: approved | AG59: badri.shaharudin@petronas.com | AH59: 46044.292 | AI59: CCMAppMart deleted | AJ59: A-000092 | AK59: 02421_15 | AL59: M | AM59: REQ000007825744 | AN59: retention | AO59: 30
A60: 6320ba63-3c83-4b37-b605-b4211b85dca9 | B60: CSSP10721535 | C60: rajila.vadakkalthund@petronas.com | D60: decommission-cloud | E60: rejected | F60: 46041.135 | G60: 46050.383 | H60: 46041.135 | I60: Sitecom / Real time Operation - RTO | J60: SecOps of Development (Dev.) Chapter for Upstream Technology, Digital & Innovation | K60: full | L60: DCOM20260119c60 | M60: afiqah.aziz@petronas.com.my | P60: Sitecom has been replaced with Halvue application | Q60: 12M | R60: Not in Used | T60: approved | U60: rajila.vadakkalthund@petronas.com | V60: 46043.232 | W60: Need to backup all resources and decom | X60: approved | Y60: afiqah.aziz@petronas.com | Z60: 46050.313 | AA60: Agreed to decom as no further utilisation | AB60: rejected | AC60: azwan.badari@petronas.com | AD60: 46050.383 | AE60: RG ptazsg-iac-daa-dev-rto-poc-rg and all resources in it already decommissioned under CSSP10728584. | AG60: CCoE Operations | AJ60: A-000766 | AK60: 4064 | AN60: retention | AO60: 365
A61: c4e0a46f-d841-4035-9b2f-e63a373218bd | B61: CSSP10715412 | C61: rajila.vadakkalthund@petronas.com | D61: decommission-cloud | E61: cancelled | F61: 46041.175 | G61: 46042.253 | H61: 46041.199 | I61: SiteCom and DrillScene Applications for Wells COE PETRON | J61: SiteCom and DrillScene Applications for Wells COE PETRON created for PRIVATECLOUD project record | K61: full | L61: DCOM20260119778 | M61: afiqah.aziz@petronas.com.my | P61: Sitecom has been replaced with Halvue application | Q61: 12M | R61: Not in Used | T61: rejected | U61: rajila.vadakkalthund@petronas.com | V61: 46042.253 | Y61: afiqah.aziz@petronas.com | AC61: CCoE Business | AG61: CCoE Business | AJ61: A-000236 | AK61: 10071 | AN61: retention
A62: 46ca1a48-c732-48b2-8cfd-bed3eff22d43 | B62: CSSP10481206 | C62: wanmiqbal.wanmhdnoor@petronas.com | D62: decommission-cloud | E62: cancelled | F62: 46041.307 | G62: 46041.311 | H62: 46041.307 | I62: Upstream Real Time Data Program - URTD | J62: Installation of Upstream Real Time Data Program (URTD) for Centre of Excellence, PCSB | K62: partial | M62: mohammadsani.johari@petronas.com | P62: Decom storage account that are not in used | Q62: 1M | R62: Not in Used | T62: rejected | U62: wanmiqbal.wanmhdnoor@petronas.com | V62: 46041.311 | Y62: mohammadsani.johari@petronas.com | AC62: CCoE Business | AG62: CCoE Operations | AJ62: A-000827 | AK62: 747 | AN62: retention | AO62: 14
A63: 4e3dda71-64e0-47a0-b520-ea0415748772 | B63: CSSP10936679 | C63: wanmiqbal.wanmhdnoor@petronas.com | D63: decommission-cloud | E63: completed | F63: 46041.314 | G63: 46042.157 | H63: 46041.314 | I63: Upstream Real Time Data Program - URTD | J63: Installation of Upstream Real Time Data Program (URTD) for Centre of Excellence, PCSB | K63: partial | M63: mohammadsani.johari@petronas.com | P63: Storage account not in used | Q63: 1M | R63: Not in Used | T63: approved | U63: wanmiqbal.wanmhdnoor@petronas.com | V63: 46041.316 | W63: sqlauditsousvoocdslrlc3q - BlobStorage account to be decommision because not in use | X63: approved | Y63: mohammadsani.johari@petronas.com | Z63: 46041.317 | AA63: Approved. | AB63: approved | AC63: azwan.badari@petronas.com | AD63: 46042.098 | AE63: Decommission storage account sqlauditsousvoocdslrlc3q | AF63: approved | AG63: azlisham.md@petronas.com | AH63: 46042.157 | AI63: The decommission request has been completed, and the status is now updated accordingly. Kindly verify from your end and confirm once reviewed. | AJ63: A-000827 | AK63: 747 | AL63: S | AM63: REQ000007828065 | AN63: retention | AO63: 9
A64: 2ea4f262-8abb-4125-a0ca-85fa740ccdac | B64: CSSP10136110 | C64: mirfan.mazuki@petronas.com | D64: decommission-cloud | E64: completed | F64: 46042.355 | G64: 46049.267 | H64: 46043.084 | I64: ACFIN Website | J64: ACFIN Website for PETRONAS Advisor Office | K64: full | L64: DCOM202601206d4 | M64: amirshazlan.mshah@petronas.com.my | N64: www.acfin.com.my, www.acfin.my | P64: User request | Q64: 2W | R64: Not in Used | T64: approved | U64: mirfan.mazuki@petronas.com | V64: 46043.1 | W64: NA | X64: approved | Y64: amirshazlan.mshah@petronas.com | Z64: 46045.1 | AA64: approved | AB64: approved | AC64: azwan.badari@petronas.com | AD64: 46045.307 | AE64: Full decommission 03284 | AF64: approved | AG64: azwan.badari@petronas.com | AH64: 46049.267 | AI64: Completed | AJ64: A-000004 | AK64: 3284 | AL64: M | AM64: REQ000007837744 | AN64: disposal | AO64: 0
A65: 4cb5421c-76ee-4918-91f4-9015721e68f2 | B65: CSSP10956620 | C65: rajila.vadakkalthund@petronas.com | D65: decommission-cloud | E65: completed | F65: 46042.406 | G65: 46057.188 | H65: 46042.406 | I65: SiteCom and DrillScene Applications for Wells COE PETRON | J65: SiteCom and DrillScene Applications for Wells COE PETRON created for PRIVATECLOUD project record | K65: full | L65: DCOM20260119778 | M65: afiqah.aziz@petronas.com.my | P65: Sitecom has been replaced with Halvue application | Q65: 12M | R65: Not in Used | T65: approved | U65: rajila.vadakkalthund@petronas.com | V65: 46043.219 | W65: need to take backup of all servers listed in the attachment. | X65: approved | Y65: afiqah.aziz@petronas.com | Z65: 46050.312 | AA65: Proceed to decom as discussed. | AB65: approved | AC65: azwan.badari@petronas.com | AD65: 46050.351 | AE65: Full Decommission (10071) listed on-premise VM. Keep backup for 12 months | AF65: approved | AG65: azlisham.md@petronas.com | AH65: 46057.188 | AI65: The decommission request has been completed, and the status is now updated accordingly. Kindly verify from your end and confirm once reviewed. | AJ65: A-000236 | AK65: 10071 | AL65: M | AM65: REQ000007847422 | AN65: retention | AO65: 365
A66: a6c49856-9f68-47d2-b48a-632ad105b938 | B66: CSSP10693653 | C66: nurulirdawaty.mnabi@petronas.com | D66: decommission-cloud | E66: completed | F66: 46043.153 | G66: 46045.374 | H66: 46043.172 | I66: Visual Inspection Corrosion Interface - VINCI | J66: Enhancement Of Visual Inspection Corrosion Interface (VINCI) System For Operation Excellence (OE), PCSB | K66: full | L66: - | M66: halim.matnoh@petronas.com.my | P66: Full Decommission for PTAZSG-DEV-VINCI-RG (PSR0609) and PTAZSG-UAT-VINCI-RG(PSR0609). Please refer to previous decommission as reference. | Q66: 2W | R66: Obsolete | T66: approved | U66: nurulirdawaty.mnabi@petronas.com | V66: 46043.173 | W66: Yes, please proceed to decomm all. | X66: approved | Y66: halim.matnoh@petronas.com | Z66: 46044.121 | AA66: approved | AB66: approved | AC66: azwan.badari@petronas.com | AD66: 46044.13 | AE66: Decommission both RG, PTAZSG-DEV-VINCI-RG (PSR0609) and PTAZSG-UAT-VINCI-RG(PSR0609) | AF66: approved | AG66: azlisham.md@petronas.com | AH66: 46045.374 | AI66: The decommission request has been completed, and the status is now updated accordingly. Kindly verify from your end and confirm once reviewed. | AJ66: A-000846 | AK66: PSR06029 | AL66: M | AM66: REQ000007834437 | AN66: noretention | AO66: 0
A67: a11e5124-0a1e-4c64-b612-5bb136c7bd95 | B67: CSSP10361019 | C67: keanseng.lim@petronas.com | D67: decommission-cloud | E67: completed | F67: 46043.351 | G67: 46093.293 | H67: 46058.276 | I67: PIVOT Enterprise Knowledge Advisor Cerebro | J67: OSR00154: Support and Maintenance for PIVOT Program for Group Digital – Enterprise Knowledge Advisor for Cerebro | K67: partial | M67: lim.hoongkeng@petronas.com | P67: Both EKIH & CEREBRO has been decommisioned. The identified resources is obsolted and not in used. This has been confirmed by Business Product Owner. | Q67: 2W | R67: Obsolete | T67: approved | U67: keanseng.lim@petronas.com | V67: 46059.065 | W67: Uploaded the approval email and reselected all resources to be decommissioned | X67: approved | Y67: lim.hoongkeng@petronas.com | Z67: 46092.279 | AA67: Reapproving as requested. | AB67: approved | AC67: azwan.badari@petronas.com | AD67: 46092.325 | AE67: Proceed to decommission listed resources | AF67: approved | AG67: azwan.badari@petronas.com | AH67: 46093.293 | AI67: Completed | AJ67: A-000609 | AK67: OSR00154_10 | AL67: M | AM67: REQ000007928247 | AN67: disposal | AO67: 0
A68: 77f1a609-e277-4a20-8446-fa2cd0b7234e | B68: CSSP10644672 | C68: wanmiqbal.wanmhdnoor@petronas.com | D68: decommission-cloud | E68: rejected | F68: 46044.072 | G68: 46044.301 | H68: 46044.072 | I68: Upstream Real Time Data Program - URTD | J68: Installation of Upstream Real Time Data Program (URTD) for Centre of Excellence, PCSB | K68: partial | M68: mohammadsani.johari@petronas.com | P68: Not in used | Q68: 1M | R68: Not in Used | T68: approved | U68: wanmiqbal.wanmhdnoor@petronas.com | V68: 46044.084 | W68: Decomm only for resources related to: 1. PTSG-1URTDAP02 2. ptsg-1urtdsvrdb01 3. ptsg1urtd2func01strg 4.ptazsg-devurtd2-apim 5.sqlauditsousvoocdslrlc3q | X68: rejected | Y68: mohammadsani.johari@petronas.com | Z68: 46044.301 | AC68: CCoE Business | AG68: CCoE Operations | AJ68: A-000827 | AK68: 747 | AN68: retention | AO68: 14
A69: fcd598c0-a60b-40ad-96c2-6de6f09d5bc9 | B69: CSSP10177449 | C69: anissyafiqah.matzail@petronas.com | D69: decommission-cloud | E69: completed | F69: 46045.057 | G69: 46086.08 | H69: 46080.1 | I69: Winglue | J69: OCI MIGRATION - WINGLUE | K69: full | L69: - | M69: halim.matnoh@petronas.com.my | N69: - | P69: User confirmed that Winglue's application are no longer in used. Refer to the attachment for the focal confirmation. | Q69: 2W | R69: Not in Used | T69: approved | U69: anissyafiqah.matzail@petronas.com | V69: 46080.101 | W69: Yes, please proceed to decomm all. | X69: approved | Y69: halim.matnoh@petronas.com | Z69: 46080.163 | AA69: approved | AB69: approved | AC69: azwan.badari@petronas.com | AD69: 46083.159 | AE69: Proceed to decommission resources in the list. | AF69: approved | AG69: azlisham.md@petronas.com | AH69: 46086.08 | AI69: The decommission request has been completed, and the status is now updated accordingly. Kindly verify from your end and confirm once reviewed. | AJ69: A-000860 | AK69: OCI-00037 | AL69: M | AM69: REQ000007906393 | AN69: noretention | AO69: 0
A70: 9a805d0b-bb21-480b-b88d-10371246b4e8 | B70: CSSP10521638 | C70: anissyafiqah.matzail@petronas.com | D70: decommission-cloud | E70: rejected | F70: 46045.057 | G70: 46045.079 | H70: 46045.071 | I70: IDAMS / WINCAIRS PMA | J70: OCI MIGRATION - IDAMS (PMA) | K70: full | L70: - | M70: halim.matnoh@petronas.com.my | P70: Contract has expired on 31/05/2025, and user confirmed that they are no longer in used. Refer to the attachment for PMA focal confirmation. | Q70: 2W | R70: Not in Used | T70: rejected | U70: anissyafiqah.matzail@petronas.com | V70: 46045.079 | X70: rejected | Y70: anissyafiqah.matzail@petronas.com | Z70: 46045.079 | AB70: rejected | AC70: anissyafiqah.matzail@petronas.com | AD70: 46045.079 | AG70: CCoE Business | AJ70: A-000371 | AK70: OCI-00019 | AN70: noretention | AO70: 0
A71: f94988b0-1141-4fc1-8762-18add88c3e9d | B71: CSSP10603924 | C71: anissyafiqah.matzail@petronas.com | D71: decommission-cloud | E71: completed | F71: 46045.057 | G71: 46051.162 | H71: 46045.279 | I71: IDAMS / WINCAIRS SKO | J71: OCI MIGRATION - IDAMS (SKO) | K71: full | L71: - | M71: halim.matnoh@petronas.com.my | P71: Contract has expired on 31/05/2025, and user confirmed that they are no longer in used. Refer to the attachment for SKO focal confirmation. | Q71: 2W | R71: Not in Used | T71: approved | U71: anissyafiqah.matzail@petronas.com | V71: 46045.281 | W71: Yes, please proceed to decomm all. | X71: approved | Y71: halim.matnoh@petronas.com | Z71: 46048.26 | AA71: approved | AB71: approved | AC71: azwan.badari@petronas.com | AD71: 46049.122 | AE71: Decommission ptawsg-1skodb01 | AF71: approved | AG71: azwan.badari@petronas.com | AH71: 46051.162 | AI71: Completed | AJ71: A-000373 | AK71: OCI-00024 | AL71: M | AM71: REQ000007842863 | AN71: noretention | AO71: 0
A72: a58e5bb6-2b1f-4c45-9438-7b4ec6f1fe9c | B72: CSSP10705796 | C72: anissyafiqah.matzail@petronas.com | D72: decommission-cloud | E72: completed | F72: 46045.058 | G72: 46051.162 | H72: 46045.278 | I72: IDAMS / WINCAIRS SBO | J72: OCI MIGRATION - IDAMS (SBO) | K72: full | L72: - | M72: halim.matnoh@petronas.com.my | P72: Contract has expired on 31/05/2025, and user confirmed that they are no longer in used. Refer to the attachment for SBO focal confirmation. | Q72: 2W | R72: Not in Used | T72: approved | U72: anissyafiqah.matzail@petronas.com | V72: 46045.281 | W72: Yes, please proceed to decomm all. | X72: approved | Y72: halim.matnoh@petronas.com | Z72: 46048.259 | AA72: approved | AB72: approved | AC72: azwan.badari@petronas.com | AD72: 46049.124 | AE72: Decommission ptawsg-1sbodb01 | AF72: approved | AG72: azwan.badari@petronas.com | AH72: 46051.162 | AI72: Completed | AJ72: A-000372 | AK72: OCI-00023 | AL72: M | AM72: REQ000007842867 | AN72: noretention | AO72: 0
A73: b8581bb4-3858-4233-b3ac-6f559264b410 | B73: CSSP10334029 | C73: anissyafiqah.matzail@petronas.com | D73: decommission-cloud | E73: completed | F73: 46045.108 | G73: 46051.162 | H73: 46045.278 | I73: IDAMS / WINCAIRS PMA | J73: OCI MIGRATION - IDAMS (PMA) | K73: full | L73: - | M73: halim.matnoh@petronas.com.my | P73: Contract has expired on 31/05/2025, and user confirmed that they are no longer in used. Refer to the attachment for PMA focal confirmation. | Q73: 2W | R73: Not in Used | T73: approved | U73: anissyafiqah.matzail@petronas.com | V73: 46045.28 | W73: Yes, please proceed to decomm all. | X73: approved | Y73: halim.matnoh@petronas.com | Z73: 46048.259 | AA73: approved | AB73: approved | AC73: azwan.badari@petronas.com | AD73: 46049.124 | AE73: Decommission ptawsg-1pmadb01 | AF73: approved | AG73: azwan.badari@petronas.com | AH73: 46051.162 | AI73: Completed | AJ73: A-000371 | AK73: OCI-00019 | AL73: M | AM73: REQ000007842787 | AN73: noretention | AO73: 0
A74: 7acb7bd0-bec5-46cf-a488-6c0e833afa26 | B74: CSSP10303191 | C74: wanmiqbal.wanmhdnoor@petronas.com | D74: decommission-cloud | E74: completed | F74: 46048.09 | G74: 46052.149 | H74: 46048.09 | I74: Upstream Real Time Data Program - URTD | J74: Installation of Upstream Real Time Data Program (URTD) for Centre of Excellence, PCSB | K74: partial | M74: mohammadsani.johari@petronas.com | N74: NA | O74: NA | P74: APIM not in used | Q74: 2W | R74: Not in Used | T74: approved | U74: wanmiqbal.wanmhdnoor@petronas.com | V74: 46048.091 | W74: API Management not in used. | X74: approved | Y74: mohammadsani.johari@petronas.com | Z74: 46050.264 | AA74: APIM not in used anymore. | AB74: approved | AC74: azwan.badari@petronas.com | AD74: 46050.281 | AE74: Decommission ptazsg-devurtd2-apim only | AF74: approved | AG74: abdullah.haziq@petronas.com | AH74: 46052.149 | AI74: decomm complete | AJ74: A-000827 | AK74: 747 | AL74: S | AM74: REQ000007846354 | AN74: retention | AO74: 14
A75: 4bb4f4d7-db29-42d7-911e-33bbeff5c3cc | B75: CSSP10810813 | C75: abdullahnaqib.hassa@petronas.com | D75: decommission-cloud | E75: completed | F75: 46048.294 | G75: 46066.294 | H75: 46048.296 | I75: SAP 30 ECC6 | J75: ERP Transformation - Central Finance Implementation – Global Design (Remark : PETRONAS CFIN Source System Box MC1)(Y30) | K75: partial | M75: rizuanatan@petronas.com | N75: sapy30scs.petronas.com,peteccmc1.petronas.com | P75: No longer required. Project went live | Q75: 2W | R75: Not in Used | T75: approved | U75: abdullahnaqib.hassa@petronas.com | V75: 46048.319 | W75: Please decom all resource under PTAZSG-UAT-SAP-CFIN-QAS-Y30-RG | X75: approved | Y75: rizuanatan@petronas.com | Z75: 46048.352 | AA75: No longer required by project team. | AB75: approved | AC75: azwan.badari@petronas.com | AD75: 46049.12 | AE75: Decommission all resources and delete RG PTAZSG-UAT-SAP-CFIN-QAS-Y30-RG | AF75: approved | AG75: azlisham.md@petronas.com | AH75: 46066.294 | AI75: The decommission request has been completed, and the status is now updated accordingly. Kindly verify from your end and confirm once reviewed. | AJ75: A-000714 | AK75: 01405_13 | AL75: M | AM75: REQ000007842778 | AN75: noretention | AO75: 0
A76: 16cec1dd-b569-468b-9d9f-b4bf5d5e1465 | B76: CSSP10900691 | C76: abdullahnaqib.hassa@petronas.com | D76: decommission-cloud | E76: completed | F76: 46048.321 | G76: 46050.136 | H76: 46048.321 | I76: SAP 68 Central Finance - CFIN | J76: ERP Transformation - Central Finance Implementation – Global Design (Remark : PETRONAS CFIN - MC1 - CFIN)(X68) | K76: partial | M76: rizuanatan@petronas.com | P76: No longer required, migrated to SAP RISE | Q76: 2W | R76: Not in Used | T76: approved | U76: abdullahnaqib.hassa@petronas.com | V76: 46048.322 | W76: Delete all in PTAZSG-UAT-SAP-CFIN-X68-RG resource group | X76: approved | Y76: rizuanatan@petronas.com | Z76: 46048.347 | AA76: X68 SID no longer use. | AB76: approved | AC76: azwan.badari@petronas.com | AD76: 46049.12 | AE76: Decommission all resources and delete RG PTAZSG-UAT-SAP-CFIN-X68-RG | AF76: approved | AG76: azlisham.md@petronas.com | AH76: 46050.136 | AI76: The decommission request has been completed, and the status is now updated accordingly. Kindly verify from your end and confirm once reviewed. | AJ76: A-000731 | AK76: 01803_19 | AL76: M | AM76: REQ000007842862 | AN76: disposal | AO76: 0
A77: 4768ac08-8ace-4aa5-9cf6-c8e017043438 | B77: CSSP10853444 | C77: joharizam.mahmood@petronas.com | D77: decommission-cloud | E77: completed | F77: 46048.373 | G77: 46076.168 | H77: 46048.378 | I77: PETRONAS Unified Search and Personal Assistant - PUSPA for REAL | J77: PETRONAS Unified Search and Personal Assistant (PUSPA) EPIC 1 and EPIC 2 Development | K77: partial | M77: khairuldin.zubai@petronas.com.my | P77: Request to delete the resource group ptazsg-dev-pdb-rg, as it is no longer required by PUSPA+ REAL Dashboard on post‑decommissioning of PUSPA in Sept 2024 | Q77: 2W | R77: Not in Used | T77: approved | U77: joharizam.mahmood@petronas.com | V77: 46048.382 | W77: Confirmation to delete all related resources under RG: ptazsg-dev-pdb-rg, as it is no longer required by PUSPA+ REAL Dashboard on post‑decommissioning of PUSPA | X77: approved | Y77: khairuldin.zubai@petronas.com | Z77: 46066.185 | AA77: Confirmed with PUSPA Product Manager Joharizam that the RG is not used by PUSPA and REAL Dashboard | AB77: approved | AC77: azwan.badari@petronas.com | AD77: 46072.292 | AE77: Proceed | AF77: approved | AG77: azlisham.md@petronas.com | AH77: 46076.168 | AI77: The decommission request has been completed, and the status is now updated accordingly. Kindly verify from your end and confirm once reviewed. | AJ77: A-001245 | AK77: 1478 | AL77: M | AM77: REQ000007881185 | AN77: noretention | AO77: 0
A78: b6b412df-de85-45dd-81f0-30040e4604b4 | B78: CSSP10790999 | C78: izham.ajmaan@petronas.com | D78: decommission-cloud | E78: completed | F78: 46049.193 | G78: 46059.17 | H78: 46049.193 | I78: VMware vCenter PRPC RTOT | J78: VMware vCenter PRPC RTOT created for PRIVATECLOUD project record | K78: ci | M78: raihan_ahmad@petronas.com | P78: OPZ-2-MAC vms-0291101 vms-0291102 OPZ-7-MAC vms-0791101 vms-0791102 | Q78: 3M | R78: Not in Used | T78: approved | U78: izham.ajmaan@petronas.com | V78: 46050.139 | W78: vms-0291101 | 172.19.100.151 vms-0291102 | 172.19.100.153 vms-0791101 | 172.24.100.151 vms-0791102 | 172.24.100.153 | X78: approved | Y78: raihan_ahmad@petronas.com | Z78: 46050.28 | AA78: Approved since there is no utilizing on the VM and for optimizing the cost. | AB78: approved | AC78: azwan.badari@petronas.com | AD78: 46050.282 | AE78: On-premise VM | AF78: approved | AG78: azlisham.md@petronas.com | AH78: 46059.17 | AI78: The decommission request has been completed, and the status is now updated accordingly. Kindly verify from your end and confirm once reviewed. | AJ78: P-000049 | AK78: 10188_11 | AL78: M | AM78: REQ000007846201 | AN78: noretention | AO78: 0
A79: 6a73b2fb-bd5b-4932-94ab-131925f5df5b | B79: CSSP10214238 | C79: ramzan.mujib@petronas.com | D79: decommission-cloud | E79: completed | F79: 46049.297 | G79: 46098.176 | H79: 46049.297 | I79: Plant Incident Reporting System - PIRS PCMTBE | J79: Cloud Migration Programme - Plant Incident Report | K79: full | L79: Not Applicable | M79: amelia_yeow@petronas.com.my | P79: PIR app. in black swan 2025 list and approved for decom by management after migrate to APM PLA | Q79: 6M | R79: End of Lease | T79: approved | U79: ramzan.mujib@petronas.com | V79: 46049.298 | W79: Proceed as per approval PC MTBE Black Swan 2025 | X79: approved | Y79: amelia_yeow@petronas.com | Z79: 46097.11 | AA79: Necessary steps have been completed prior to decom | AB79: approved | AC79: azwan.badari@petronas.com | AD79: 46097.285 | AE79: Proceed to full decommission. Delete resources and RG, PTAZSG-IAC-DEV-PIR-PC-MTBE-RG & PTAZSG-IAC-PROD-PIR-PC-MTBE-RG | AF79: approved | AG79: azwan.badari@petronas.com | AH79: 46098.176 | AI79: Completed with the listed resources. To check the activity of the DB in SQLMI with the same project code, if not in use decide if those will be decommissioned too or not. | AJ79: A-000600 | AK79: 02421_124 | AL79: S | AM79: REQ000007937995 | AN79: disposal | AO79: 0
A80: 77524547-9556-4680-8e15-ff261708c2a8 | B80: CSSP10289737 | C80: sengchin.leong@petronas.com | D80: decommission-cloud | E80: pending | F80: 46050.013 | G80: 46050.016 | H80: 46050.013 | I80: Cyber Security Mandiant Security Validation - MSV BFDC | J80: Cyber Security Mandiant Security Validation - MSV BFDC created for PRIVATECLOUD project record | K80: partial | M80: mshafri.hatta@petronas.com | P80: One of the module (172.25.8.83) has been unsubscribed due to cost optimization. the VM no longer in use | Q80: 12M | R80: End of Lease | T80: approved | U80: sengchin.leong@petronas.com | V80: 46050.016 | W80: decommission for MSV (Mandiant Security Validation) - Protected Theatre module - 172.25.8.83 The module has been unsubscribed and VM no longer in used | Y80: mshafri.hatta@petronas.com | AC80: CCoE Business | AG80: CCoE Operations | AJ80: A-000170 | AK80: 10213 | AN80: retention | AO80: 30
A81: b00ce160-a1aa-4225-b953-1a9e8b334600 | B81: CSSP10385911 | C81: mfaizal.suriyat@petronas.com | D81: decommission-cloud | E81: completed | F81: 46050.128 | G81: 46072.825 | H81: 46051.305 | I81: RISER | J81: RISER | K81: full | L81: DCOM2026012946c | M81: sarkunan.tigarajan@petronas.com.my | P81: Decommissioning for RISER | Q81: 1M | R81: Not in Used | T81: approved | U81: mfaizal.suriyat@petronas.com | V81: 46051.307 | W81: 1. Staging (Non-Production): PTAW-IAC-NonPROD-AIP-Environment-01 2. Production: PTAW-IAC-PROD-AIP-Environment-01 | X81: approved | Y81: sarkunan.tigarajan@petronas.com | Z81: 46051.313 | AA81: Approved | AB81: approved | AC81: azwan.badari@petronas.com | AD81: 46052.035 | AE81: Decommission 03457 | AF81: approved | AG81: azwan.badari@petronas.com | AH81: 46072.825 | AI81: Completed | AJ81: A-000690 | AK81: 3457 | AL81: M | AM81: REQ000007850113 | AN81: noretention | AO81: 0
A82: fffd0b9b-2361-49c7-ad9e-ff9f5e9d733a | B82: CSSP10696569 | C82: mfuad.ahmadrafee@petronas.com | D82: decommission-cloud | E82: completed | F82: 46050.137 | G82: 46076.307 | H82: 46050.137 | I82: M365 Teams Message Broadcast | J82: MS Teams Message Broadcast (POC Environment) for Group Risk Demonstration | K82: full | L82: - | M82: nshahidahothman@petronas.com | P82: The RG is not in used | Q82: 2W | R82: Not in Used | T82: approved | U82: mfuad.ahmadrafee@petronas.com | V82: 46050.147 | W82: These resources were identified during the DPIA remediation process. After further review, we found that they were originally requested during the previous M365 project for POC purposes and are no longer in use. | X82: approved | Y82: nshahidahothman@petronas.com | Z82: 46057.174 | AA82: proceed | AB82: approved | AC82: azwan.badari@petronas.com | AD82: 46058.091 | AE82: Decommission all resources and RG PTAZSG-DEV-ENS-POC-RG | AF82: approved | AG82: abdullah.haziq@petronas.com | AH82: 46076.307 | AI82: Decommission all resources and RG PTAZSG-DEV-ENS-POC-RG | AJ82: A-000450 | AK82: PC-00012 | AL82: M | AM82: REQ000007859287 | AN82: disposal | AO82: 0
A83: 2f24b3bc-d655-44dc-8935-32ed396c7554 | B83: CSSP10342452 | C83: mfuad.ahmadrafee@petronas.com | D83: decommission-cloud | E83: completed | F83: 46050.159 | G83: 46076.298 | H83: 46050.159 | I83: President Townhall | J83: Subscription for Azure Media Services for President Townhall | K83: full | L83: - | M83: nshahidahothman@petronas.com | P83: These resources were identified during the DPIA remediation process. After further review, we found that they were originally requested during the previous M365 project for POC purposes and are no longer in use. | Q83: 2W | R83: Not in Used | T83: approved | U83: mfuad.ahmadrafee@petronas.com | V83: 46050.165 | W83: These resources were identified during the DPIA remediation process. After further review, we found that they were originally requested during the previous M365 project for POC purposes and are no longer in use. | X83: approved | Y83: nshahidahothman@petronas.com | Z83: 46057.173 | AA83: proceed | AB83: approved | AC83: azwan.badari@petronas.com | AD83: 46058.084 | AE83: Decommission all resources and both RG, PTAZSG-DEV-PRESTH-RG & PTAZSG-PROD-PRESTH-RG | AF83: approved | AG83: abdullah.haziq@petronas.com | AH83: 46076.298 | AI83: Resource decommission complete | AJ83: C-000036 | AK83: PC-00003 | AL83: M | AM83: REQ000007859727 | AN83: disposal | AO83: 0
A84: 0eb38b0d-c959-4e8d-a296-62530cad6454 | B84: CSSP10522577 | C84: aqeelah.rashidi@petronas.com | D84: decommission-cloud | E84: completed | F84: 46050.164 | G84: 46064.167 | H84: 46050.164 | I84: ATG TotaLizer Automation System - ATLAS | J84: Cloud Migration Program - ATLAS - ATG Tota(L)izer Automation System | K84: full | L84: DCOM20250912867 | M84: mohammadsani.johari@petronas.com | P84: The application is no longer use by end user. End users agree to decommissioning all related VM and physical server related with application. Below is the list for related physical server that yet to decommission. 1. cenppdbpiap01- 10.13.4.56 2. sbappdbpiap01- 10.45.224.56 3. Easppdbpiap01- 10.18.96.56 4. skappdbpiap01- 10.43.64.56 | Q84: 2W | R84: Not in Used | T84: approved | U84: aqeelah.rashidi@petronas.com | V84: 46050.165 | W84: physical server related | X84: approved | Y84: mohammadsani.johari@petronas.com | Z84: 46050.267 | AA84: To decom ATLAS physical server | AB84: approved | AC84: azwan.badari@petronas.com | AD84: 46050.286 | AE84: Decommission 4 physical server. 1. cenppdbpiap01- 10.13.4.56 2. sbappdbpiap01- 10.45.224.56 3. Easppdbpiap01- 10.18.96.56 4. skappdbpiap01- 10.43.64.56 | AF84: approved | AG84: azlisham.md@petronas.com | AH84: 46064.167 | AI84: The decommission request has been completed, and the status is now updated accordingly. Kindly verify from your end and confirm once reviewed. | AJ84: A-000080 | AK84: 02421_135 | AL84: L | AM84: REQ000007846361 | AN84: noretention | AO84: 0
A85: 11dd9fd0-3e28-4ca5-a850-18be9ce90734 | B85: CSSP10577735 | C85: mfuad.ahmadrafee@petronas.com | D85: decommission-cloud | E85: completed | F85: 46050.255 | G85: 46076.326 | H85: 46050.255 | I85: M365 | J85: Microsoft 365 (M365) Deployment for PETRONAS Groupwide. | K85: full | L85: - | M85: nshahidahothman@petronas.com | P85: These resources were identified during the DPIA remediation process. After further review, we found that they were originally requested during the previous M365 project for POC purposes and are no longer in use. | Q85: 2W | R85: Not in Used | T85: approved | U85: mfuad.ahmadrafee@petronas.com | V85: 46050.327 | W85: These resources were identified during the DPIA remediation process. After further review, we found that they were originally requested during the previous M365 project for POC purposes and are no longer in use. | X85: approved | Y85: nshahidahothman@petronas.com | Z85: 46057.172 | AA85: proceed | AB85: approved | AC85: azwan.badari@petronas.com | AD85: 46058.116 | AE85: Decommission all resources and both RG PTAZSG-CORE-RMS-RG & PTAZSG-PROD-CMG04-RG | AF85: approved | AG85: abdullah.haziq@petronas.com | AH85: 46076.326 | AI85: Decommission all resources and both RG PTAZSG-CORE-RMS-RG & PTAZSG-PROD-CMG04-RG | AJ85: A-000440 | AK85: M365 | AL85: M | AM85: REQ000007859928 | AN85: disposal | AO85: 0
A86: 43f520a7-aecc-4f2b-8665-a17b83e9a4df | B86: CSSP10999243 | C86: mfaizal.suriyat@petronas.com | D86: decommission-cloud | E86: completed | F86: 46050.274 | G86: 46052.201 | H86: 46050.274 | I86: PETRONAS Pipeline Engineering Solution - P-PIES | J86: Development of Phase 2 PETRONAS Pipeline Engineering Solution (P-PiES) System for GTS | K86: partial | M86: shekha.mahdhar@petronas.com.my | P86: VM replaced with other VM | Q86: 2W | R86: Obsolete | T86: approved | U86: mfaizal.suriyat@petronas.com | V86: 46050.275 | W86: ptsg-4piesap01,ptsg-4piesap01_disk1_db1501356f2c4d7b8b9932f92b31f1fe | X86: approved | Y86: shekha.mahdhar@petronas.com | Z86: 46050.34 | AA86: As requested. | AB86: approved | AC86: azwan.badari@petronas.com | AD86: 46051.186 | AE86: Decommission ptsg-4piesap01 | AF86: approved | AG86: azwan.badari@petronas.com | AH86: 46052.201 | AI86: Completed | AJ86: A-000640 | AK86: 313 | AL86: M | AM86: REQ000007848216 | AN86: disposal | AO86: 0
A87: b60c3fa6-59c1-4e01-a90b-402d28a4a538 | B87: CSSP10175519 | C87: aziah.azahari@petronas.com | D87: decommission-cloud | E87: completed | F87: 46050.331 | G87: 46052.156 | H87: 46050.333 | I87: Authorization For Expenditure Management System - AFEMS PCSB | J87: Cloud Migration Program - Authorization For Expenditure Management System (AFEMS) 4.0 | K87: partial | M87: rafedah.mdtap@petronas.com.my | N87: afems-pccmo.petronas.com | P87: DNS still exist and tagged to UAT RG ptazscus-uat-afems-rg which not included in earlier full decommission request. Previous AFEMS PCCMO decommission CSSP No is CSSP10132527. | Q87: 2W | R87: Not in Used | T87: approved | U87: aziah.azahari@petronas.com | V87: 46050.362 | W87: To decommission selected resource | X87: approved | Y87: rafedah.mdtap@petronas.com | Z87: 46051.127 | AA87: Approved as discussed | AB87: approved | AC87: azwan.badari@petronas.com | AD87: 46051.164 | AE87: Decommission ptazscus-uat-afems-rg and DNS afems-pccmo.petronas.com | AF87: approved | AG87: azwan.badari@petronas.com | AH87: 46052.156 | AI87: Completed | AJ87: A-000028 | AK87: 00915_65 | AL87: M | AM87: REQ000007848196 | AN87: retention
A88: a7a986de-fcbe-4f4e-9eff-254a29772caf | B88: CSSP10454461 | C88: zuwina.masaat@petronas.com | D88: decommission-cloud | E88: completed | F88: 46050.367 | G88: 46058.078 | H88: 46050.367 | I88: Asset Ageing Life Extension System - ALES | J88: ALES for MPM | K88: ci | M88: wadiah.rusli@petronas.com | P88: No backup required. This request to remove CMDB Record for CI Name - ALE Suite and retain CI Name - Asset Ageing Life Extension System (ALES) 2.0 | Q88: 1M | R88: Consolidation | T88: approved | U88: zuwina.masaat@petronas.com | V88: 46050.368 | W88: No resource to be removed. | X88: approved | Y88: wadiah.rusli@petronas.com | Z88: 46050.372 | AA88: Please remove ALE Suite | AB88: approved | AC88: saniza.ismail@petronas.com | AD88: 46051.199 | AE88: To update CI record in CMDB | AF88: approved | AG88: saniza.ismail@petronas.com | AH88: 46058.078 | AI88: Update CI ALE Suite to Status Disposed in CMDB | AJ88: A-000041 | AK88: 3374 | AL88: S | AM88: REQ000007849045 | AN88: noretention | AO88: 0
A89: 3986ddb3-b49e-409a-9e59-64dd4affe2a1 | B89: CSSP10783990 | C89: diana.ali@petronas.com | D89: decommission-cloud | E89: cancelled | F89: 46051.077 | G89: 46051.078 | H89: 46051.077 | I89: Enterprise Application Integration - EAI WebMethod | J89: EAI WebMethod Integration Platform Cloud Migration and Upgrade | K89: partial | M89: mahzan.musa@petronas.com | N89: myeai.petronas.com, myeaiext.petronas.com | P89: Migrated to MuleSoft | Q89: 6M | R89: Upgrade | T89: rejected | U89: diana.ali@petronas.com | V89: 46051.078 | Y89: mahzan.musa@petronas.com | AC89: CCoE Business | AG89: CCoE Operations | AJ89: A-000253 | AK89: 1726 | AN89: retention | AO89: 90
A90: d778a5ce-abff-4322-ad68-1474fea0794d | B90: CSSP10238871 | C90: diana.ali@petronas.com | D90: decommission-cloud | E90: completed | F90: 46051.146 | G90: 46064.311 | H90: 46051.146 | I90: Enterprise Application Integration - EAI WebMethod | J90: EAI WebMethod Integration Platform Cloud Migration and Upgrade | K90: ci | M90: mahzan.musa@petronas.com | P90: The WebMethods integration has been migrated to MuleSoft. We will proceed with an application decommission for now. A full decommission request will be submitted later in February once the stabilization period ends. | Q90: 6M | R90: Upgrade | T90: approved | U90: diana.ali@petronas.com | V90: 46051.265 | W90: The WebMethods integration has been migrated to MuleSoft. We will proceed with an application decommission for now. A full decommission request will be submitted later in February once the stabilization period ends. | X90: approved | Y90: mahzan.musa@petronas.com | Z90: 46057.308 | AA90: Approve decommissioning as EAI webMethods replaced with MuleSoft. Migration completed Jan-2026. | AB90: approved | AC90: saniza.ismail@petronas.com | AD90: 46064.307 | AE90: To change Webmethod EAI to Disposed in CMDB. | AF90: approved | AG90: saniza.ismail@petronas.com | AH90: 46064.311 | AI90: Change Webmethod EAI CI Status to Disposed in CMDB 1. WebMethods EAI (onCloud 10.7 External) 2. WebMethods EAI (onCloud 10.7 Internal) | AJ90: A-000253 | AK90: 1726 | AL90: S | AM90: REQ000007870614 | AN90: retention | AO90: 90
A91: 553c9672-36e8-48ac-8730-da383cbf82ca | B91: CSSP10654103 | C91: izmir.marzuki@petronas.com | D91: decommission-cloud | E91: completed | F91: 46051.291 | G91: 46053.176 | H91: 46051.291 | I91: GoAnywhere MFT | J91: Provision of Hosting Infrastructure-as-a-Service (IaaS) for GoAnywhere MFT for PETRONAS Group | K91: partial | M91: saiful.zahari@petronas.com | P91: 1) ptazsg1mftgofilestrggrs is not in used. 2) ptazsg5mftgofilestrglrs is not in used. 3) ptazsg5mftgostrglrs is not in used. | Q91: 2W | R91: Not in Used | T91: approved | U91: izmir.marzuki@petronas.com | V91: 46051.293 | W91: 1) ptazsg1mftgofilestrggrs is not in used. 2) ptazsg5mftgofilestrglrs is not in used. 3) ptazsg5mftgostrglrs is not in used. | X91: approved | Y91: saiful.zahari@petronas.com | Z91: 46052.071 | AA91: Ensure that all related and non interdependent resources are also deleted eg snapshots and backup (if any) | AB91: approved | AC91: azwan.badari@petronas.com | AD91: 46052.163 | AE91: Decommission listed storage account | AF91: approved | AG91: azwan.badari@petronas.com | AH91: 46053.176 | AI91: Completed | AJ91: A-000342 | AK91: 1335 | AL91: M | AM91: REQ000007850888 | AN91: noretention | AO91: 0
A92: 75aa387d-efbb-4f36-b7e7-29d01ccacb86 | B92: CSSP10892983 | C92: mfaizal.salleh@petronas.com | D92: decommission-cloud | E92: completed | F92: 46052.07 | G92: 46058.291 | H92: 46052.07 | I92: Malaysian Financial Reporting Standards - MFRS | J92: Implementation Malaysian Financial Reporting Standards (MFRS) Statutory Reporting (MFRS16) for PETRONAS Group of Companies | K92: partial | M92: amirshazlan.mshah@petronas.com.my | P92: Not in used | Q92: 2W | R92: Not in Used | T92: approved | U92: mfaizal.salleh@petronas.com | V92: 46052.076 | W92: Not in used - Resource not found ptsg4mfrsblobstrg ptazsguatmfrsrgdiag ptsg4mfrsfunc01strg ptsg1mfrsblobstrg | X92: approved | Y92: amirshazlan.mshah@petronas.com | Z92: 46052.093 | AA92: approval | AB92: approved | AC92: azwan.badari@petronas.com | AD92: 46052.21 | AE92: Proceed | AF92: approved | AG92: azlisham.md@petronas.com | AH92: 46058.291 | AI92: The decommission request has been completed, and the status is now updated accordingly. Kindly verify from your end and confirm once reviewed. | AJ92: A-000461 | AK92: 789 | AL92: M | AM92: REQ000007851251 | AN92: noretention | AO92: 0
A93: 34877244-ad85-4856-bd47-9fbef95c822d | B93: CSSP10245126 | C93: hari.amirchow@petronas.com | D93: decommission-cloud | E93: completed | F93: 46052.6 | G93: 46066.103 | H93: 46052.6 | I93: SAP 40 BPC | J93: Migration and Optimization of SAP P40 to BPC 10.1 using HANA Database for Group Financial Control (GFC) | K93: partial | M93: rizuanatan@petronas.com | P93: Issue with DB corruption. DB had to be restored in new server | Q93: 2W | R93: Not in Used | T93: approved | U93: hari.amirchow@petronas.com | V93: 46052.604 | W93: Old VM that has been replaced with new VM due to restore issue | X93: approved | Y93: rizuanatan@petronas.com | Z93: 46062.119 | AA93: Due to a database corruption issue, the server was moved to a new VM. The old VM is no longer being used. | AB93: approved | AC93: azwan.badari@petronas.com | AD93: 46062.149 | AE93: Proceed to decommission listed VM. | AF93: approved | AG93: azlisham.md@petronas.com | AH93: 46066.103 | AI93: The decommission request has been completed, and the status is now updated accordingly. Kindly verify from your end and confirm once reviewed. | AJ93: A-000723 | AK93: PSR05474 | AL93: M | AM93: REQ000007865007 | AN93: noretention | AO93: 0
A94: dbdae2f3-d153-4f86-aed1-be13cc473370 | B94: CSSP10431985 | C94: azad.johari@petronas.com | D94: decommission-cloud | E94: rejected | F94: 46057.034 | G94: 46132.354 | H94: 46057.034 | I94: Talent Analytics - TA | J94: VM for Talent Analytics POC | K94: partial | M94: amirshazlan.mshah@petronas.com | P94: PTSG-1TLDap01, PTSG-5TLDap01 not in used. | Q94: 12M | R94: Not in Used | T94: approved | U94: azad.johari@petronas.com | V94: 46057.035 | W94: no resource found. these 2 servers to be decomm PTSG-1TLDap01, PTSG-5TLDap01. both in AWS. | X94: approved | Y94: amirshazlan.mshah@petronas.com | Z94: 46126.383 | AA94: approved | AB94: rejected | AC94: azwan.badari@petronas.com | AD94: 46132.354 | AE94: Server PTSG-1TLDap01, PTSG-5TLDap01 not found, might has been decommissioned. | AG94: CCoE Operations | AJ94: A-000801 | AK94: 845 | AN94: noretention | AO94: 0
A95: 8836aca8-9ff7-4684-975e-5433333a7be1 | B95: CSSP10348510 | C95: marziah.mahmod@petronas.com | D95: decommission-cloud | E95: completed | F95: 46057.044 | G95: 46078.248 | H95: 46076.226 | I95: Plant Information - PI Enterprise | J95: CTP Old to New LZ - PI Enterprise | K95: full | L95: DCOM20260204e88 | M95: mohammadsani.johari@petronas.com.my | N95: PTAWSG-1PIGDA01;10.102.21.191, PTAWSG-1PIGDA02;10.102.22.28 | P95: Server consolidation as part of cost optimization for EPH. | Q95: 1M | R95: Consolidation | T95: approved | U95: marziah.mahmod@petronas.com | V95: 46076.3 | W95: Server consolidation as part of cost optimization for EPH. | X95: approved | Y95: mohammadsani.johari@petronas.com | Z95: 46076.318 | AA95: Approved | AB95: approved | AC95: azwan.badari@petronas.com | AD95: 46077.101 | AE95: PTAWSG-1PIGDA01;10.102.21.191, PTAWSG-1PIGDA02;10.102.22.28 in AWS, PTAW-IAC-PROD-PEnT-Environment-01 | AF95: approved | AG95: azlisham.md@petronas.com | AH95: 46078.248 | AI95: The decommission request has been completed, and the status is now updated accordingly. Kindly verify from your end and confirm once reviewed. | AJ95: A-000568 | AK95: 02421_71 | AL95: M | AM95: REQ000007889231 | AN95: noretention | AO95: 0
A96: a210e434-a6eb-4702-8acc-5a76408edc4b | B96: CSSP10650004 | C96: syahadah.salleh@petronas.com | D96: decommission-cloud | E96: completed | F96: 46057.19 | G96: 46092.4 | H96: 46057.19 | I96: SharePoint - SPO ShareGate Desktop | J96: Cloud Migration Program - Sharepoint ShareGate Desktop Migration | K96: partial | M96: nshahidahothman@petronas.com.my | N96: na | O96: na | P96: COC enforcement. | Q96: 1M | R96: Not in Used | T96: approved | U96: syahadah.salleh@petronas.com | V96: 46057.191 | W96: Storage account not in use, 0 usage for past years. | X96: approved | Y96: nshahidahothman@petronas.com | Z96: 46078.248 | AA96: proceed | AB96: approved | AC96: azwan.badari@petronas.com | AD96: 46079.045 | AE96: Decommission selected storage account, ptsg1spsgstrg | AF96: approved | AG96: abdullah.haziq@petronas.com | AH96: 46092.4 | AI96: completed | AJ96: A-000787 | AK96: 00915_32 | AL96: S | AM96: REQ000007894393 | AN96: noretention | AO96: 0
A97: f191af8a-ec87-42d5-8835-d7dd954ffe0d | B97: CSSP10132385 | C97: izdihar.roslan@petronas.com | D97: decommission-cloud | E97: completed | F97: 46057.284 | G97: 46063.166 | H97: 46057.284 | I97: Lab Information Management System - LIMS PDB | J97: OCI MIGRATION - LIMS PDB | K97: partial | M97: sazali.mokhtar@petronas.com.my | P97: Cloud Repatriation - To decommission old resources in Singapore region due to completed migration in MY region | Q97: 2W | R97: Cloud Migration | T97: approved | U97: izdihar.roslan@petronas.com | V97: 46057.289 | W97: Cloud Repatriation - To decommission old resources in Singapore region due to completed migration in MY region | X97: approved | Y97: sazali.mokhtar@petronas.com | Z97: 46058.074 | AA97: Cloud Repatriation - To decommission old resources in Singapore region due to completed migration in MY region. | AB97: approved | AC97: azwan.badari@petronas.com | AD97: 46058.144 | AE97: Decommission as per listed resources | AF97: approved | AG97: azwan.badari@petronas.com | AH97: 46063.166 | AI97: Completed | AJ97: A-000426 | AK97: 00915_209 | AL97: M | AM97: REQ000007859789 | AN97: disposal | AO97: 0
A98: 8e017d90-1def-41d9-8d66-b921ead6c49f | B98: CSSP10359052 | C98: izdihar.roslan@petronas.com | D98: decommission-cloud | E98: pending | F98: 46057.29 | G98: 46219.263 | H98: 46057.29 | I98: Lab Information Management System - LIMS PDB | J98: OCI MIGRATION - Integrated Lab Information System (PDB) | K98: partial | M98: sazali.mokhtar@petronas.com.my | P98: Cloud Repatriation - To decommission old resources in Singapore region due to completed migration in MY region | Q98: 2W | R98: Cloud Migration | T98: pending | U98: izdihar.roslan@petronas.com | Y98: sazali.mokhtar@petronas.com | AC98: CCoE Business | AG98: CCoE Operations | AJ98: A-000426 | AK98: OCI-00021 | AN98: noretention | AO98: 0
